Workbook

Sheet SOA-TSL Payable
A2: Statement of Accounts (SOA)
A3: Tata Bluescope (TBSL)
A5: TSL Payable - TBSL Receivable
A7: Sl.No | B7: Particulars | C7: As per Tata Steel (Rs.) | D7: As per TBSL (Rs.) | E7: Difference
A8: 1 | B8: Opening Balance as on 01.04.2019 | C8: 46541723 | D8: 50979645 | E8: =C8-D8 -> -4437921.9
A9: 2a. | B9: Transactions | C9: =-C20 -> 2.3083245e+08 | D9: =C26 -> 2.2011657e+08 | E9: =C9-D9 -> 10715876
A10: 2b. | B10: GST | C10: =-TSL!Q671 -> 34636394 | D10: =TBSL!Q1494 -> 39671816 | E10: =C10-D10 -> -5035421.6 | F10: Take Totals of GST column by filtering via same dcument type as in Txn
A11: 2 | B11: Total Transaction | C11: =SUM(C9:C10) -> 2.6546884e+08 | D11: =SUM(D9:D10) -> 2.5978839e+08 | E11: =C11-D11 -> 5680454
A12: 3 | B12: Total Payments/Collection | C12: =C13-C11-C8 -> -2.5124551e+08 | D12: =D13-D11-D8 -> -2.3460043e+08 | E12: =C12-D12 -> -16645082
A13: 4 | B13: Closing Balance as on 31.03.2020 | C13: 60765053 | D13: 76167603 | E13: =C13-D13 -> -15402550
B17: provision | C17: -3562266.1
B18: GRIR | C18: -36247052
B19: Transaction | C19: =TSL!L671 -> -1.9102313e+08 | D19: (RE,RL,RA, SA, SB Summ) | E19: (Amt in Loc Curr – GST amt+wTA) | F19: amt in loc cur + wTA = (2)(Total Txn)
B20: Tata steel total transaction | C20: =SUM(C17:C19) -> -2.3083245e+08
B25: Transaction | C25: =TBSL!L1493 -> 2.2011657e+08 | D25: (only RV) | E25: (Amt in Loc Curr – GST amt+wTA)
B26: TBSL total transaction | C26: =SUM(C25:C25) -> 2.2011657e+08
C38: 72978936
C39: -81433170

Sheet Form 2 TSL Payable
A1: TATA STEEL LIMITED - CONSOLIDATED FINANCIAL STATEMENTS | E1: Form - 2
A3: Details of transactions and balances
A5: Category : Subsidiary
A7: Name of the Company : Tata Bluescope (TBSL) | E7: (From the stand point of Tata Steel)
A8: Period : April 2019 to March 2020
A9: Nature of transactions | B9: Balance as per TSL | C9: Balance as per RP | D9: Difference | E9: Remarks (*)
A11: Purchases of Goods | B11: ='SOA-TSL Payable'!C9 -> 2.3083245e+08
A12: Sale of Goods | C12: ='SOA-TSL Payable'!D9 -> 2.2011657e+08
A13: Purchase of Fixed Assets
A14: Sale of Fixed Assets
A15: Purchase of Investments
A16: Sale of Investments
A17: Rendering of Services | D17: =B11-C12 -> 10715876 | E17: See Transaction reco
A18: Receiving of Services
A19: Agency arrangements (income)
A20: Leasing or hire purchase arrangements
A21: Finance provided(including loans and equity contributions in cash or in kind)
A22: Interest income during the year
A23: Finance received (including loans and equity contributions in cash or in kind)
A24: Interest paid during the year
A25: Guarantees and collaterals given
A26: Contributions made to employee benefit trusts
A27: Management Contracts including deputation of employees
A28: Dividend income
A29: Provision for receivables made during the year
... A37: Debit balances outstanding as on 31.03.2020
A38: Outstanding receivables- Debtors | C38: =Balances!C6 -> 76387905
A39: Outstanding receivables- Advance
A43: Credit balances outstanding as on 31.03.2020
A44: Outstanding payables- Creditors | B44: ='SOA-TSL Payable'!C13 -> 60765053 | D44: =B44-(C38-C45) -> -15402550 | E44: See BL Reco
A45: Outstanding payables- Advance | C45: =-Balances!C5 -> 220301.86
A47: Provision for outstanding receivables
A49: * If any figure does not agree and there are differences then the reconciliation must accompany the statement. However, reconciliation
A50: item should not be a result of any items which should have been recognised and accounted for by Tata Steel.
A55: Note :
A56: 1. The location must have full transaction level / financial code level back up for each of the figures given below.
A57: 2. If there are no transaction with any of the companies referred to in Annexure 1, then a NIL certificate should be enclosed.

Sheet Transaction reco-TSL Pay
B2: Transaction Reconciliation for the period 01.04.2019 to 31.03.2020 - TSL Payable TBSL Receivable
B3: Particulars | C3: Balance as on 31.03.2020 | D3: Balance as on 31.03.2019 | E3: Transaction reco for the period
B4: As per RP | E4: ='SOA-TSL Payable'!C26 -> 2.2011657e+08
B6: Reasons for Differences (Add/Less):
B7: Invoice diff in GRIR booked with GST | E7: =D7-C7 -> 0
B8: Material in Transit | C8: =MIT!N13 -> 7737321.6 | E8: =D8-C8 -> -7737321.6
B9: Transaction of last year | C9: ='Last year Items'!K68 -> -21471051 | E9: =D9-C9 -> 21471051
B10: Short provision by TSL | C10: ='Short provi'!O27 -> 3104833 | E10: =D10-C10 -> -3104833
B11: Invoice Difference | C11: ='Invoice Diff'!L159 -> 188485.18 | E11: =D11-C11 -> -188485.18
B12: Invoice Difference in GRIR | C12: ='Invoice diff in GRIR'!L24 -> 15159.63 | E12: =D12-C12 -> -15159.63
B13: Under reco | C13: -290623.58 | E13: =D13-C13 -> 290623.58
B15: Balance after above adjustments | C15: =SUM(C6:C11) -> -10440412 | E15: =SUM(E4:E13) -> 2.3083245e+08
B16: As per Tata Steel Ltd | E16: ='SOA-TSL Payable'!C20*-1 -> 2.3083245e+08
B17: Difference | E17: =E15-E16 -> 0
C38: 72978936
C39: -81433170

Sheet TSL
A1: Company_Code | B1: Company_Name | C1: SAP_Doc_Number | D1: Reference | E1: Document_Type | F1: Business_Area | G1: Fiscal_Year | H1: Posting_Period | I1: Doc/Chq_Date | J1: Posting_Date | K1: Amount_in_Local_Currency | L1: SOA | M1: Local_Currency | N1: Amount_in_Document_Currency | O1: Document_Currency | P1: Discount_Base_Amount | Q1: GST_Amount | R1: Net_Amount | S1: Withholding_Tax_Base_Amount | T1: Withholding_Tax_Amount | U1: Vendor/Customer | V1: Vendor/Customer_Name | W1: Trading_Partner | X1: Text | Y1: HDR_Text | Z1: Inv/SO_Reference | AA1: Plant | AB1: Purchasing_Document | AC1: Delivery_Note | AD1: Account | AE1: Account_Description | AF1: Offsetting_Account | AG1: Offsetting_Acct_Name | AH1: GRIR_Offsetting_Account | AI1: Final_Offsetting_Account | AJ1: Final_Offsetting_Acct_Name | AK1: WBS_Element | AL1: Posting_Key | AM1: Debit/Credit | AN1: Special_G/L_Ind. | AO1: Reversal_Indicator | AP1: Clearing_Doc | AQ1: Clearing_Date | AR1: Entry_date | AS1: Entry_Time | AT1: Notional_GST | AU1: Gross_Amount_In_Local_Currency | AV1: DE_Indicator | AW1: PO_Line | AX1: Entry_Line
A2: 1000 | B2: Tata Steel Limited | C2: 42009213 | D2: DD NO-007452, | E2: KG | F2: 9500 | G2: 2020 | H2: 3 | I2: 43640 | J2: 43640 | K2: 2000 | L2: =K2-Q2+T2 -> 1694.91 | M2: INR | N2: 2000 | O2: INR | P2: 2000 | Q2: 305.09 | R2: 1694.91 | S2: 0 | T2: 0 | U2: T040 | V2: TATA BLUESCOPE STEEL PRIVATE LIMIT | X2: Gate pass penalty, DD no -007452, IDBI | Y2: gatepass penalty | Z2: 42009213 | AD2: 2408402 | AE2: Vendor Reconciliation Account - Domestic | AF2: 3263001 | AG2: Miscellaneous Income Jsr | AI2: 3263001 | AJ2: Miscellaneous Income Jsr | AK2: 0 | AL2: 21 | AM2: S | AP2: 91510334 | AQ2: 24-06-2019 | AR2: 24-06-2019 | AS2: 16:52:22 | AT2: 0 | AU2: 2000 | AX2: 1
A3: 1000 | B3: Tata Steel Limited | C3: 42034968 | D3: GST/TSK/DN/235 | E3: KG | F3: 9600 | G3: 2020 | H3: 5 | I3: 43678 | J3: 43700 | K3: 8673 | L3: =K3-Q3+T3 -> 7350 | M3: INR | N3: 8673 | O3: INR | P3: 8673 | Q3: 1323 | R3: 7350 | S3: 0 | T3: 0 | U3: T040 | V3: TATA BLUESCOPE STEEL PRIVATE LIMIT | X3: Hiring of Equipments | Y3: 3800014331 | Z3: 42034968 | AD3: 2408402 | AE3: Vendor Reconciliation Account - Domestic | AF3: 3263001 | AG3: Miscellaneous Income Jsr | AI3: 3263001 | AJ3: Miscellaneous Income Jsr | AK3: 0 | AL3: 21 | AM3: S | AR3: 23-08-2019 | AS3: 12:43:29 | AT3: 0 | AU3: 8673 | AX3: 1
A4: 1000 | B4: Tata Steel Limited | C4: 42035904 | D4: DD NO -007588 | E4: KG | F4: 9500 | G4: 2020 | H4: 6 | I4: 43719 | J4: 43719 | K4: 800 | L4: =K4-Q4+T4 -> 677.97 | M4: INR | N4: 800 | O4: INR | P4: 800 | Q4: 122.03 | R4: 677.97 | S4: 0 | T4: 0 | U4: T040 | V4: TATA BLUESCOPE STEEL PRIVATE LIMIT | X4: Gate pass penaty , T040 | Y4: Gate pass Penalty | Z4: 42035904 | AD4: 2408402 | AE4: Vendor Reconciliation Account - Domestic | AF4: 3265003 | AG4: MISCELLANEOUS INCOME | AI4: 3265003 | AJ4: MISCELLANEOUS INCOME | AK4: 0 | AL4: 21 | AM4: S | AP4: 92076426 | AQ4: 11-09-2019 | AR4: 11-09-2019 | AS4: 12:53:10 | AT4: 0 | AU4: 800 | AX4: 1
A5: 1000 | B5: Tata Steel Limited | C5: 42035915 | D5: DD 007588 | E5: KG | F5: 9500 | G5: 2020 | H5: 6 | I5: 43719 | J5: 43720 | K5: 800 | L5: =K5-Q5+T5 -> 677.97 | M5: INR | N5: 800 | O5: INR | P5: 800 | Q5: 122.03 | R5: 677.97 | S5: 0 | T5: 0 | U5: T040 | V5: TATA BLUESCOPE STEEL PRIVATE LIMIT | X5: DOC TO DELETE | Y5: Gatepass penalty | Z5: 42035915 | AD5: 2408402 | AE5: Vendor Reconciliation Account - Domestic | AF5: 3265003 | AG5: MISCELLANEOUS INCOME | AI5: 3265003 | AJ5: MISCELLANEOUS INCOME | AK5: 0 | AL5: 21 | AM5: S | AR5: 12-09-2019 | AS5: 09:21:32 | AT5: 0 | AU5: 800 | AX5: 1
A6: 1000 | B6: Tata Steel Limited | C6: 42041185 | D6: GATEPASS/RFID | E6: KG | F6: 9600 | G6: 2020 | H6: 10 | I6: 43860 | J6: 43860 | K6: 1100 | L6: =K6-Q6+T6 -> 932.2 | M6: INR | N6: 1100 | O6: INR | P6: 1100 | Q6: 167.8 | R6: 932.2 | S6: 0 | T6: 0 | U6: T018 | V6: TATA BLUESCOPE STEEL PRIVATE LIMIT | X6: Gatepass/RFID Recovery from Vendor | Y6: Gatepas Penalty | Z6: 42041185 | AD6: 2408402 | AE6: Vendor Reconciliation Account - Domestic | AF6: 3265003 | AG6: MISCELLANEOUS INCOME | AI6: 3265003 | AJ6: MISCELLANEOUS INCOME | AK6: 0 | AL6: 21 | AM6: S | AP6: 92978106 | AQ6: 30-01-2020 | AR6: 30-01-2020 | AS6: 09:15:37 | AT6: 0 | AU6: 1100 | AX6: 1
A7: 1000 | B7: Tata Steel Limited | C7: 42041545 | D7: DD NO-186797 | E7: KG | F7: 9500 | G7: 2020 | H7: 11 | I7: 43868 | J7: 43868 | K7: 400 | L7: =K7-Q7+T7 -> 338.98 | M7: INR | N7: 400 | O7: INR | P7: 400 | Q7: 61.02 | R7: 338.98 | S7: 0 | T7: 0 | U7: T040 | V7: TATA BLUESCOPE STEEL PRIVATE LIMIT | X7: UNION BANK DT 07.02.2019 | Y7: Gate pass Penalty | Z7: 42041545 | AD7: 2408402 | AE7: Vendor Reconciliation Account - Domestic | AF7: 3265003 | AG7: MISCELLANEOUS INCOME | AI7: 3265003 | AJ7: MISCELLANEOUS INCOME | AK7: 0 | AL7: 21 | AM7: S | AP7: 93046164 | AQ7: 07-02-2020 | AR7: 07-02-2020 | AS7: 15:46:49 | AT7: 0 | AU7: 400 | AX7: 1
A8: 1000 | B8: Tata Steel Limited | C8: 42041546 | D8: DD NO-186798 | E8: KG | F8: 9500 | G8: 2020 | H8: 11 | I8: 43868 | J8: 43868 | K8: 200 | L8: =K8-Q8+T8 -> 169.49 | M8: INR | N8: 200 | O8: INR | P8: 200 | Q8: 30.51 | R8: 169.49 | S8: 0 | T8: 0 | U8: T040 | V8: TATA BLUESCOPE STEEL PRIVATE LIMIT | X8: UNION BANK DT 07.02.2019 | Y8: Gate pass Penalty | Z8: 42041546 | AD8: 2408402 | AE8: Vendor Reconciliation Account - Domestic | AF8: 3265003 | AG8: MISCELLANEOUS INCOME | AI8: 3265003 | AJ8: MISCELLANEOUS INCOME | AK8: 0 | AL8: 21 | AM8: S | AP8: 93046166 | AQ8: 07-02-2020 | AR8: 07-02-2020 | AS8: 15:49:59 | AT8: 0 | AU8: 200 | AX8: 1
A9: 1000 | B9: Tata Steel Limited | C9: 44234301 | D9: TDS ON PROVISION | E9: KR | F9: 9000 | G9: 2020 | H9: 12 | I9: 31-03-2020 | J9: 31-03-2020 | K9: 26922 | L9: =K9-Q9+T9 -> 26922 | M9: INR | N9: 26922 | O9: INR | P9: 0 | Q9: 0 | R9: 26922 | S9: 0 | T9: 0 | U9: T018 | V9: TATA BLUESCOPE STEEL PRIVATE LIMIT | X9: TDS on Year End Manual Prov FY 2020 | Y9: TDS on Provisions Manual | Z9: V | AD9: 2408402 | AE9: Vendor Reconciliation Account - Domestic | AF9: T018 | AG9: TATA BLUESCOPE STEEL PRIVATE LIMIT | AI9: 2408402 | AJ9: Vendor Reconciliation Account - Domestic | AK9: 0 | AL9: 21 | AM9: S | AR9: 07-04-2020 | AS9: 16:14:04 | AT9: 0 | AU9: 26922 | AX9: 2
A10: 1000 | B10: Tata Steel Limited | C10: 44234301 | D10: TDS ON PROVISION | E10: KR | F10: 9000 | G10: 2020 | H10: 12 | I10: 31-03-2020 | J10: 31-03-2020 | K10: -26922 | L10: =K10-Q10+T10 -> -26922 | M10: INR | N10: -26922 | O10: INR | P10: 0 | Q10: 0 | R10: -26922 | S10: 0 | T10: 0 | U10: T018 | V10: TATA BLUESCOPE STEEL PRIVATE LIMIT | X10: TDS on Year End Manual Prov FY 2020 | Y10: TDS on Provisions Manual | Z10: 44234301 | AD10: 2408402 | AE10: Vendor Reconciliation Account - Domestic | AF10: 2405215 | AG10: Provisional Liability for TDS on Povision- Manual | AI10: 2405215 | AJ10: Provisional Liability for TDS on Povision- Manual | AK10: 0 | AL10: 31 | AM10: H | AR10: 07-04-2020 | AS10: 16:14:04 | AT10: 0 | AU10: -26922 | AX10: 3
A11: 1000 | B11: Tata Steel Limited | C11: 44234302 | D11: TDS ON PROVISION | E11: KR | F11: 9000 | G11: 2020 | H11: 12 | I11: 31-03-2020 | J11: 31-03-2020 | K11: -64706 | L11: =K11-Q11+T11 -> -64706 | M11: INR | N11: -64706 | O11: INR | P11: 0 | Q11: 0 | R11: -64706 | S11: 0 | T11: 0 | U11: T018 | V11: TATA BLUESCOPE STEEL PRIVATE LIMIT | X11: TDS on Year End Manual Prov FY 2020 | Y11: TDS on Provisions Manual | Z11: 44234302 | AD11: 2408402 | AE11: Vendor Reconciliation Account - Domestic | AF11: 2405215 | AG11: Provisional Liability for TDS on Povision- Manual | AI11: 2405215 | AJ11: Provisional Liability for TDS on Povision- Manual | AK11: 0 | AL11: 31 | AM11: H | AR11: 07-04-2020 | AS11: 16:14:06 | AT11: 0 | AU11: -64706 | AX11: 3
A12: 1000 | B12: Tata Steel Limited | C12: 44234302 | D12: TDS ON PROVISION | E12: KR | F12: 9000 | G12: 2020 | H12: 12 | I12: 31-03-2020 | J12: 31-03-2020 | K12: 64706 | L12: =K12-Q12+T12 -> 64706 | M12: INR | N12: 64706 | O12: INR | P12: 0 | Q12: 0 | R12: 64706 | S12: 0 | T12: 0 | U12: T018 | V12: TATA BLUESCOPE STEEL PRIVATE LIMIT | X12: TDS on Year End Manual Prov FY 2020 | Y12: TDS on Provisions Manual | Z12: V | AD12: 2408402 | AE12: Vendor Reconciliation Account - Domestic | AF12: T018 | AG12: TATA BLUESCOPE STEEL PRIVATE LIMIT | AI12: 2408402 | AJ12: Vendor Reconciliation Account - Domestic | AK12: 0 | AL12: 21 | AM12: S | AR12: 07-04-2020 | AS12: 16:14:06 | AT12: 0 | AU12: 64706 | AX12: 2
A13: 1000 | B13: Tata Steel Limited | C13: 44234305 | D13: TDS ON PROVISION | E13: KR | F13: 9000 | G13: 2020 | H13: 12 | I13: 31-03-2020 | J13: 31-03-2020 | K13: -48508 | L13: =K13-Q13+T13 -> -48508 | M13: INR | N13: -48508 | O13: INR | P13: 0 | Q13: 0 | R13: -48508 | S13: 0 | T13: 0 | U13: T040 | V13: TATA BLUESCOPE STEEL PRIVATE LIMIT | X13: TDS on Year End Manual Prov FY 2020 | Y13: TDS on Provisions Manual | Z13: 44234305 | AD13: 2408402 | AE13: Vendor Reconciliation Account - Domestic | AF13: 2405215 | AG13: Provisional Liability for TDS on Povision- Manual | AI13: 2405215 | AJ13: Provisional Liability for TDS on Povision- Manual | AK13: 0 | AL13: 31 | AM13: H | AR13: 07-04-2020 | AS13: 16:14:09 | AT13: 0 | AU13: -48508 | AX13: 3
A14: 1000 | B14: Tata Steel Limited | C14: 44234305 | D14: TDS ON PROVISION | E14: KR | F14: 9000 | G14: 2020 | H14: 12 | I14: 31-03-2020 | J14: 31-03-2020 | K14: 48508 | L14: =K14-Q14+T14 -> 48508 | M14: INR | N14: 48508 | O14: INR | P14: 0 | Q14: 0 | R14: 48508 | S14: 0 | T14: 0 | U14: T040 | V14: TATA BLUESCOPE STEEL PRIVATE LIMIT | X14: TDS on Year End Manual Prov FY 2020 | Y14: TDS on Provisions Manual | Z14: V | AD14: 2408402 | AE14: Vendor Reconciliation Account - Domestic | AF14: T040 | AG14: TATA BLUESCOPE STEEL PRIVATE LIMIT | AI14: 2408402 | AJ14: Vendor Reconciliation Account - Domestic | AK14: 0 | AL14: 21 | AM14: S | AR14: 07-04-2020 | AS14: 16:14:09 | AT14: 0 | AU14: 48508 | AX14: 2
A15: 1000 | B15: Tata Steel Limited | C15: 44234306 | D15: TDS ON PROVISION | E15: KR | F15: 9000 | G15: 2020 | H15: 12 | I15: 31-03-2020 | J15: 31-03-2020 | K15: -5274 | L15: =K15-Q15+T15 -> -5274 | M15: INR | N15: -5274 | O15: INR | P15: 0 | Q15: 0 | R15: -5274 | S15: 0 | T15: 0 | U15: T040 | V15: TATA BLUESCOPE STEEL PRIVATE LIMIT | X15: TDS on Year End Manual Prov FY 2020 | Y15: TDS on Provisions Manual | Z15: 44234306 | AD15: 2408402 | AE15: Vendor Reconciliation Account - Domestic | AF15: 2405215 | AG15: Provisional Liability for TDS on Povision- Manual | AI15: 2405215 | AJ15: Provisional Liability for TDS on Povision- Manual | AK15: 0 | AL15: 31 | AM15: H | AR15: 07-04-2020 | AS15: 16:14:11 | AT15: 0 | AU15: -5274 | AX15: 3
A16: 1000 | B16: Tata Steel Limited | C16: 44234306 | D16: TDS ON PROVISION | E16: KR | F16: 9000 | G16: 2020 | H16: 12 | I16: 31-03-2020 | J16: 31-03-2020 | K16: 5274 | L16: =K16-Q16+T16 -> 5274 | M16: INR | N16: 5274 | O16: INR | P16: 0 | Q16: 0 | R16: 5274 | S16: 0 | T16: 0 | U16: T040 | V16: TATA BLUESCOPE STEEL PRIVATE LIMIT | X16: TDS on Year End Manual Prov FY 2020 | Y16: TDS on Provisions Manual | Z16: V | AD16: 2408402 | AE16: Vendor Reconciliation Account - Domestic | AF16: T040 | AG16: TATA BLUESCOPE STEEL PRIVATE LIMIT | AI16: 2408402 | AJ16: Vendor Reconciliation Account - Domestic | AK16: 0 | AL16: 21 | AM16: S | AR16: 07-04-2020 | AS16: 16:14:11 | AT16: 0 | AU16: 5274 | AX16: 2
A17: 1000 | B17: Tata Steel Limited | C17: 45001676 | D17: R040272105570 | E17: KZ | F17: 5010 | G17: 2020 | H17: 1 | I17: 01-04-2019 | J17: 01-04-2019 | K17: 1996973 | L17: =K17-Q17+T17 -> 1996973 | M17: INR | N17: 1996973 | O17: INR | P17: 0 | Q17: 0 | R17: 1996973 | S17: 0 | T17: 0 | U17: T018 | V17: TATA BLUESCOPE STEEL PRIVATE LIMIT | Y17: 20190401-SERV2 | Z17: 45001676 | AD17: 2408402 | AE17: Vendor Reconciliation Account - Domestic | AF17: 2200403 | AG17: Cash Credit With HDFC- E -Payments Cleared Balance | AI17: 2200403 | AJ17: Cash Credit With HDFC- E -Payments Cleared Balance | AK17: 0 | AL17: 25 | AM17: S | AP17: 45001676 | AQ17: 01-04-2019 | AR17: 01-04-2019 | AS17: 17:51:48 | AT17: 0 | AU17: 1996973 | AX17: 1
A18: 1000 | B18: Tata Steel Limited | C18: 45004518 | D18: R190793184653 | E18: KZ | F18: 9000 | G18: 2020 | H18: 1 | I18: 03-04-2019 | J18: 03-04-2019 | K18: 137519.56 | L18: =K18-Q18+T18 -> 137519.56 | M18: INR | N18: 137519.56 | O18: INR | P18: 0 | Q18: 0 | R18: 137519.56 | S18: 0 | T18: 0 | U18: T040 | V18: TATA BLUESCOPE STEEL PRIVATE LIMIT | Y18: 20190403-KGLO1 | Z18: 45004518 | AD18: 2408402 | AE18: Vendor Reconciliation Account - Domestic | AF18: 2200403 | AG18: Cash Credit With HDFC- E -Payments Cleared Balance | AI18: 2200403 | AJ18: Cash Credit With HDFC- E -Payments Cleared Balance | AK18: 0 | AL18: 25 | AM18: S | AP18: 45004518 | AQ18: 03-04-2019 | AR18: 03-04-2019 | AS18: 12:33:00 | AT18: 0 | AU18: 137519.56 | AX18: 1
A19: 1000 | B19: Tata Steel Limited | C19: 45005501 | D19: R040472484972 | E19: KZ | F19: 9600 | G19: 2020 | H19: 1 | I19: 03-04-2019 | J19: 03-04-2019 | K19: 722969.75 | L19: =K19-Q19+T19 -> 722969.75 | M19: INR | N19: 722969.75 | O19: INR | P19: 0 | Q19: 0 | R19: 722969.75 | S19: 0 | T19: 0 | U19: T018 | V19: TATA BLUESCOPE STEEL PRIVATE LIMIT | Y19: 20190403-SERV2 | Z19: 45005501 | AD19: 2408402 | AE19: Vendor Reconciliation Account - Domestic | AF19: 2200403 | AG19: Cash Credit With HDFC- E -Payments Cleared Balance | AI19: 2200403 | AJ19: Cash Credit With HDFC- E -Payments Cleared Balance | AK19: 0 | AL19: 25 | AM19: S | AP19: 45005501 | AQ19: 03-04-2019 | AR19: 03-04-2019 | AS19: 18:00:55 | AT19: 0 | AU19: 722969.75 | AX19: 2
A20: 1000 | B20: Tata Steel Limited | C20: 45005501 | D20: R040472484972 | E20: KZ | F20: 9600 | G20: 2020 | H20: 1 | I20: 03-04-2019 | J20: 03-04-2019 | K20: 1713145.5 | L20: =K20-Q20+T20 -> 1713145.5 | M20: INR | N20: 1713145.5 | O20: INR | P20: 0 | Q20: 0 | R20: 1713145.5 | S20: 0 | T20: 0 | U20: T018 | V20: TATA BLUESCOPE STEEL PRIVATE LIMIT | Y20: 20190403-SERV2 | Z20: 45005501 | AD20: 2408402 | AE20: Vendor Reconciliation Account - Domestic | AF20: 2200403 | AG20: Cash Credit With HDFC- E -Payments Cleared Balance | AI20: 2200403 | AJ20: Cash Credit With HDFC- E -Payments Cleared Balance | AK20: 0 | AL20: 25 | AM20: S | AP20: 45005501 | AQ20: 03-04-2019 | AR20: 03-04-2019 | AS20: 18:00:55 | AT20: 0 | AU20: 1713145.5 | AX20: 1
A21: 1000 | B21: Tata Steel Limited | C21: 45005501 | D21: R040472484972 | E21: KZ | F21: 9600 | G21: 2020 | H21: 1 | I21: 03-04-2019 | J21: 03-04-2019 | K21: 782591.43 | L21: =K21-Q21+T21 -> 782591.43 | M21: INR | N21: 782591.43 | O21: INR | P21: 0 | Q21: 0 | R21: 782591.43 | S21: 0 | T21: 0 | U21: T018 | V21: TATA BLUESCOPE STEEL PRIVATE LIMIT | Y21: 20190403-SERV2 | Z21: 45005501 | AD21: 2408402 | AE21: Vendor Reconciliation Account - Domestic | AF21: 2200403 | AG21: Cash Credit With HDFC- E -Payments Cleared Balance | AI21: 2200403 | AJ21: Cash Credit With HDFC- E -Payments Cleared Balance | AK21: 0 | AL21: 25 | AM21: S | AP21: 45005501 | AQ21: 03-04-2019 | AR21: 03-04-2019 | AS21: 18:00:55 | AT21: 0 | AU21: 782591.43 | AX21: 3
A22: 1000 | B22: Tata Steel Limited | C22: 45006919 | D22: R040572726149 | E22: KZ | F22: 9600 | G22: 2020 | H22: 1 | I22: 04-04-2019 | J22: 04-04-2019 | K22: 1117660 | L22: =K22-Q22+T22 -> 1117660 | M22: INR | N22: 1117660 | O22: INR | P22: 0 | Q22: 0 | R22: 1117660 | S22: 0 | T22: 0 | U22: T018 | V22: TATA BLUESCOPE STEEL PRIVATE LIMIT | Y22: 20190404-CAPSH | Z22: 45006919 | AD22: 2408402 | AE22: Vendor Reconciliation Account - Domestic | AF22: 2200403 | AG22: Cash Credit With HDFC- E -Payments Cleared Balance | AI22: 2200403 | AJ22: Cash Credit With HDFC- E -Payments Cleared Balance | AK22: 0 | AL22: 25 | AM22: S | AP22: 45006919 | AQ22: 04-04-2019 | AR22: 04-04-2019 | AS22: 17:17:27 | AT22: 0 | AU22: 1117660 | AX22: 1
A23: 1000 | B23: Tata Steel Limited | C23: 45006920 | D23: R040572737139 | E23: KZ | F23: 9000 | G23: 2020 | H23: 1 | I23: 04-04-2019 | J23: 04-04-2019 | K23: 366824.77 | L23: =K23-Q23+T23 -> 366824.77 | M23: INR | N23: 366824.77 | O23: INR | P23: 0 | Q23: 0 | R23: 366824.77 | S23: 0 | T23: 0 | U23: T040 | V23: TATA BLUESCOPE STEEL PRIVATE LIMIT | Y23: 20190404-CAPSH | Z23: 45006920 | AD23: 2408402 | AE23: Vendor Reconciliation Account - Domestic | AF23: 2200403 | AG23: Cash Credit With HDFC- E -Payments Cleared Balance | AI23: 2200403 | AJ23: Cash Credit With HDFC- E -Payments Cleared Balance | AK23: 0 | AL23: 25 | AM23: S | AP23: 45006920 | AQ23: 04-04-2019 | AR23: 04-04-2019 | AS23: 17:17:27 | AT23: 0 | AU23: 366824.77 | AX23: 1
A24: 1000 | B24: Tata Steel Limited | C24: 45007443 | D24: R040872990802 | E24: KZ | F24: 5010 | G24: 2020 | H24: 1 | I24: 05-04-2019 | J24: 05-04-2019 | K24: 646758 | L24: =K24-Q24+T24 -> 646758 | M24: INR | N24: 646758 | O24: INR | P24: 0 | Q24: 0 | R24: 646758 | S24: 0 | T24: 0 | U24: T018 | V24: TATA BLUESCOPE STEEL PRIVATE LIMIT | Y24: 20190405-SERV2 | Z24: 45007443 | AD24: 2408402 | AE24: Vendor Reconciliation Account - Domestic | AF24: 2200403 | AG24: Cash Credit With HDFC- E -Payments Cleared Balance | AI24: 2200403 | AJ24: Cash Credit With HDFC- E -Payments Cleared Balance | AK24: 0 | AL24: 25 | AM24: S | AP24: 45007443 | AQ24: 05-04-2019 | AR24: 05-04-2019 | AS24: 12:44:05 | AT24: 0 | AU24: 646758 | AX24: 1
A25: 1000 | B25: Tata Steel Limited | C25: 45007445 | D25: R040872990805 | E25: KZ | F25: 9500 | G25: 2020 | H25: 1 | I25: 05-04-2019 | J25: 05-04-2019 | K25: 966445.92 | L25: =K25-Q25+T25 -> 966445.92 | M25: INR | N25: 966445.92 | O25: INR | P25: 0 | Q25: 0 | R25: 966445.92 | S25: 0 | T25: 0 | U25: T040 | V25: TATA BLUESCOPE STEEL PRIVATE LIMIT | Y25: 20190405-SERV2 | Z25: 45007445 | AD25: 2408402 | AE25: Vendor Reconciliation Account - Domestic | AF25: 2200403 | AG25: Cash Credit With HDFC- E -Payments Cleared Balance | AI25: 2200403 | AJ25: Cash Credit With HDFC- E -Payments Cleared Balance | AK25: 0 | AL25: 25 | AM25: S | AP25: 45007445 | AQ25: 05-04-2019 | AR25: 05-04-2019 | AS25: 12:44:05 | AT25: 0 | AU25: 966445.92 | AX25: 1
A26: 1000 | B26: Tata Steel Limited | C26: 45010166 | D26: R041073347232 | E26: KZ | F26: 0920 | G26: 2020 | H26: 1 | I26: 09-04-2019 | J26: 09-04-2019 | K26: 5121003.3 | L26: =K26-Q26+T26 -> 5121003.3 | M26: INR | N26: 5121003.3 | O26: INR | P26: 0 | Q26: 0 | R26: 5121003.3 | S26: 0 | T26: 0 | U26: T018 | V26: TATA BLUESCOPE STEEL PRIVATE LIMIT | Y26: 20190409-COPS3 | Z26: 45010166 | AD26: 2408402 | AE26: Vendor Reconciliation Account - Domestic | AF26: 2200403 | AG26: Cash Credit With HDFC- E -Payments Cleared Balance | AI26: 2200403 | AJ26: Cash Credit With HDFC- E -Payments Cleared Balance | AK26: 0 | AL26: 25 | AM26: S | AP26: 45010166 | AQ26: 09-04-2019 | AR26: 09-04-2019 | AS26: 15:25:25 | AT26: 0 | AU26: 5121003.3 | AX26: 1
A27: 1000 | B27: Tata Steel Limited | C27: 45012116 | D27: R190800737014 | E27: KZ | F27: 9000 | G27: 2020 | H27: 1 | I27: 11-04-2019 | J27: 11-04-2019 | K27: -162273.6 | L27: =K27-Q27+T27 -> -162273.6 | M27: INR | N27: -162273.6 | O27: INR | P27: 0 | Q27: 0 | R27: -162273.6 | S27: 0 | T27: 0 | U27: T040 | V27: TATA BLUESCOPE STEEL PRIVATE LIMIT | Y27: 20190411-SERV3 | Z27: 45012116 | AD27: 2408402 | AE27: Vendor Reconciliation Account - Domestic | AF27: T040 | AG27: TATA BLUESCOPE STEEL PRIVATE LIMIT | AI27: 2408402 | AJ27: Vendor Reconciliation Account - Domestic | AK27: 0 | AL27: 38 | AM27: H | AP27: 45012116 | AQ27: 11-04-2019 | AR27: 11-04-2019 | AS27: 14:26:08 | AT27: 0 | AU27: -162273.6 | AX27: 1
A28: 1000 | B28: Tata Steel Limited | C28: 45012116 | D28: R190800737014 | E28: KZ | F28: 9500 | G28: 2020 | H28: 1 | I28: 11-04-2019 | J28: 11-04-2019 | K28: 189092.68 | L28: =K28-Q28+T28 -> 189092.68 | M28: INR | N28: 189092.68 | O28: INR | P28: 0 | Q28: 0 | R28: 189092.68 | S28: 0 | T28: 0 | U28: T040 | V28: TATA BLUESCOPE STEEL PRIVATE LIMIT | Y28: 20190411-SERV3 | Z28: 45012116 | AD28: 2408402 | AE28: Vendor Reconciliation Account - Domestic | AF28: T040 | AG28: TATA BLUESCOPE STEEL PRIVATE LIMIT | AI28: 2408402 | AJ28: Vendor Reconciliation Account - Domestic | AK28: 0 | AL28: 25 | AM28: S | AP28: 45012116 | AQ28: 11-04-2019 | AR28: 11-04-2019 | AS28: 14:26:08 | AT28: 0 | AU28: 189092.68 | AX28: 2
... A160: 1000 | B160: Tata Steel Limited | C160: 45262199 | D160: R031674248390 | E160: KZ | F160: 9600 | G160: 2020 | H160: 12 | I160: 13-03-2020 | J160: 13-03-2020 | K160: 600451.7 | L160: =K160-Q160+T160 -> 600451.7 | M160: INR | N160: 600451.7 | O160: INR | P160: 0 | Q160: 0 | R160: 600451.7 | S160: 0 | T160: 0 | U160: T040 | V160: TATA BLUESCOPE STEEL PRIVATE LIMIT | Y160: 20200313-CAPSH | Z160: 45262199 | AD160: 2408402 | AE160: Vendor Reconciliation Account - Domestic | AF160: 2200403 | AG160: Cash Credit With HDFC- E -Payments Cleared Balance | AI160: 2200403 | AJ160: Cash Credit With HDFC- E -Payments Cleared Balance | AK160: 0 | AL160: 25 | AM160: S | AP160: 45262199 | AQ160: 13-03-2020 | AR160: 13-03-2020 | AS160: 14:56:16 | AT160: 0 | AU160: 600451.7 | AX160: 1
A161: 1000 | B161: Tata Steel Limited | C161: 51007775 | D161: CI0004108029 | E161: RE | F161: 9600 | G161: 2020 | H161: 1 | I161: 43529 | J161: 43558 | K161: -110831.38 | L161: =K161-Q161+T161 -> -93924.9 | M161: INR | N161: -110831.38 | O161: INR | P161: -110831.38 | Q161: -16906.48 | R161: -93924.9 | S161: 0 | T161: 0 | U161: T018 | V161: TATA BLUESCOPE STEEL PRIVATE LIMIT | Y161: 2300047310 | Z161: 51007775 | AB161: 2300047310 | AD161: 2408402 | AE161: Vendor Reconciliation Account - Domestic | AF161: 2408424 | AG161: GR/IR Account - Capital (Project System) | AH161: 5149121 | AI161: 5149121 | AJ161: Purchase of Capital goods-Project System | AK161: 0 | AL161: 31 | AM161: H | AP161: 45018260 | AQ161: 16-04-2019 | AR161: 03-04-2019 | AS161: 17:10:51 | AT161: 0 | AU161: -110831.38 | AX161: 1
A162: 1000 | B162: Tata Steel Limited | C162: 51015501 | D162: CI0004107732 | E162: RE | F162: 5030 | G162: 2020 | H162: 1 | I162: 43519 | J162: 43563 | K162: -3510796.2 | L162: =K162-Q162+T162 -> -2975250.9 | M162: INR | N162: -3510796.2 | O162: INR | P162: -3510796.2 | Q162: -535545.29 | R162: -2975250.9 | S162: 0 | T162: 0 | U162: T018 | V162: TATA BLUESCOPE STEEL PRIVATE LIMIT | X162: Bill Receipt Date :22.03.2019 | Y162: 3700786376 | Z162: 51015501 | AB162: 3700786376 | AD162: 2408402 | AE162: Vendor Reconciliation Account - Domestic | AF162: 2408409 | AG162: Gr/Ir For Stores And Spares | AH162: 6005101 | AI162: 6005101 | AJ162: Purchase of Stores | AK162: 0 | AL162: 31 | AM162: H | AP162: 45012359 | AQ162: 11-04-2019 | AR162: 08-04-2019 | AS162: 10:39:26 | AT162: 0 | AU162: -3510796.2 | AX162: 1
A163: 1000 | B163: Tata Steel Limited | C163: 51017855 | D163: OM/ARC/14 | E163: RE | F163: 9600 | G163: 2020 | H163: 1 | I163: 43551 | J163: 43564 | K163: -425053.85 | L163: =K163-Q163+T163 -> -366426.01 | M163: INR | N163: -425053.85 | O163: INR | P163: -432382.69 | Q163: -65956.68 | R163: -359097.17 | S163: -366426.01 | T163: -7328.84 | U163: T018 | V163: TATA BLUESCOPE STEEL PRIVATE LIMIT | X163: SUPPLY AND FIXING OF SHEET | Y163: 4404339865 | Z163: 51017855 | AB163: 4404339865 | AD163: 2408402 | AE163: Vendor Reconciliation Account - Domestic | AF163: 2408422 | AG163: GR/IR Account - Services & Capital | AH163: 5149027 | AI163: 5149027 | AJ163: Civil Contract Jobs | AK163: 0 | AL163: 31 | AM163: H | AP163: 45036233 | AQ163: 07-05-2019 | AR163: 09-04-2019 | AS163: 09:31:44 | AT163: 0 | AU163: -425053.85 | AX163: 2
A164: 1000 | B164: Tata Steel Limited | C164: 51017855 | D164: OM/ARC/14 | E164: RE | F164: 9600 | G164: 2020 | H164: 1 | I164: 43551 | J164: 43564 | K164: -215527.83 | L164: =K164-Q164+T164 -> -185799.99 | M164: INR | N164: -215527.83 | O164: INR | P164: -219243.99 | Q164: -33444 | R164: -182083.83 | S164: -185799.99 | T164: -3716.16 | U164: T018 | V164: TATA BLUESCOPE STEEL PRIVATE LIMIT | X164: SUPPLY AND FIXING OF SHEET | Y164: 4404339865 | Z164: 51017855 | AB164: 4404339865 | AD164: 2408402 | AE164: Vendor Reconciliation Account - Domestic | AF164: 2408422 | AG164: GR/IR Account - Services & Capital | AH164: 5149027 | AI164: 5149027 | AJ164: Civil Contract Jobs | AK164: 0 | AL164: 31 | AM164: H | AP164: 45036233 | AQ164: 07-05-2019 | AR164: 09-04-2019 | AS164: 09:31:44 | AT164: 0 | AU164: -215527.83 | AX164: 1
A165: 1000 | B165: Tata Steel Limited | C165: 51017865 | D165: OM/ARC/15 | E165: RE | F165: 9600 | G165: 2020 | H165: 1 | I165: 43551 | J165: 43564 | K165: -208614.2 | L165: =K165-Q165+T165 -> -179840 | M165: INR | N165: -208614.2 | O165: INR | P165: -212211.2 | Q165: -32371.2 | R165: -176243 | S165: -179840 | T165: -3597 | U165: T018 | V165: TATA BLUESCOPE STEEL PRIVATE LIMIT | X165: SUPPLY AND FIXING OF SHEET | Y165: 4404338210 | Z165: 51017865 | AB165: 4404338210 | AD165: 2408402 | AE165: Vendor Reconciliation Account - Domestic | AF165: 2408422 | AG165: GR/IR Account - Services & Capital | AH165: 5149027 | AI165: 5149027 | AJ165: Civil Contract Jobs | AK165: 0 | AL165: 31 | AM165: H | AP165: 45036233 | AQ165: 07-05-2019 | AR165: 09-04-2019 | AS165: 09:35:09 | AT165: 0 | AU165: -208614.2 | AX165: 1
A166: 1000 | B166: Tata Steel Limited | C166: 51017868 | D166: OM/ARC/16 | E166: RE | F166: 9600 | G166: 2020 | H166: 1 | I166: 43551 | J166: 43564 | K166: -106070.26 | L166: =K166-Q166+T166 -> -91440 | M166: INR | N166: -106070.26 | O166: INR | P166: -107899.2 | Q166: -16459.2 | R166: -89611.06 | S166: -91440 | T166: -1828.94 | U166: T018 | V166: TATA BLUESCOPE STEEL PRIVATE LIMIT | X166: SUPPLY AND FIXING OF SHEET | Y166: 4404338208 | Z166: 51017868 | AB166: 4404338208 | AD166: 2408402 | AE166: Vendor Reconciliation Account - Domestic | AF166: 2408422 | AG166: GR/IR Account - Services & Capital | AH166: 5149027 | AI166: 5149027 | AJ166: Civil Contract Jobs | AK166: 0 | AL166: 31 | AM166: H | AP166: 45036233 | AQ166: 07-05-2019 | AR166: 09-04-2019 | AS166: 09:37:32 | AT166: 0 | AU166: -106070.26 | AX166: 3
A167: 1000 | B167: Tata Steel Limited | C167: 51017868 | D167: OM/ARC/16 | E167: RE | F167: 9600 | G167: 2020 | H167: 1 | I167: 43551 | J167: 43564 | K167: -129212.23 | L167: =K167-Q167+T167 -> -111390 | M167: INR | N167: -129212.23 | O167: INR | P167: -131440.2 | Q167: -20050.2 | R167: -109162.03 | S167: -111390 | T167: -2227.97 | U167: T018 | V167: TATA BLUESCOPE STEEL PRIVATE LIMIT | X167: SUPPLY AND FIXING OF SHEET | Y167: 4404338208 | Z167: 51017868 | AB167: 4404338208 | AD167: 2408402 | AE167: Vendor Reconciliation Account - Domestic | AF167: 2408422 | AG167: GR/IR Account - Services & Capital | AH167: 5149027 | AI167: 5149027 | AJ167: Civil Contract Jobs | AK167: 0 | AL167: 31 | AM167: H | AP167: 45036233 | AQ167: 07-05-2019 | AR167: 09-04-2019 | AS167: 09:37:32 | AT167: 0 | AU167: -129212.23 | AX167: 2
A168: 1000 | B168: Tata Steel Limited | C168: 51017868 | D168: OM/ARC/16 | E168: RE | F168: 9600 | G168: 2020 | H168: 1 | I168: 43551 | J168: 43564 | K168: -68903.91 | L168: =K168-Q168+T168 -> -59400 | M168: INR | N168: -68903.91 | O168: INR | P168: -70092 | Q168: -10692 | R168: -58211.91 | S168: -59400 | T168: -1188.09 | U168: T018 | V168: TATA BLUESCOPE STEEL PRIVATE LIMIT | X168: SUPPLY AND FIXING OF SHEET | Y168: 4404338208 | Z168: 51017868 | AB168: 4404338208 | AD168: 2408402 | AE168: Vendor Reconciliation Account - Domestic | AF168: 2408422 | AG168: GR/IR Account - Services & Capital | AH168: 5149027 | AI168: 5149027 | AJ168: Civil Contract Jobs | AK168: 0 | AL168: 31 | AM168: H | AP168: 45036233 | AQ168: 07-05-2019 | AR168: 09-04-2019 | AS168: 09:37:32 | AT168: 0 | AU168: -68903.91 | AX168: 1
A169: 1000 | B169: Tata Steel Limited | C169: 51017875 | D169: OM/ARC/17 | E169: RE | F169: 9600 | G169: 2020 | H169: 1 | I169: 43551 | J169: 43564 | K169: -414990 | L169: =K169-Q169+T169 -> -357750 | M169: INR | N169: -414990 | O169: INR | P169: -422145 | Q169: -64395 | R169: -350595 | S169: -357750 | T169: -7155 | U169: T018 | V169: TATA BLUESCOPE STEEL PRIVATE LIMIT | X169: SUPPLY AND FIXING OF SHEET | Y169: 4404338209 | Z169: 51017875 | AB169: 4404338209 | AD169: 2408402 | AE169: Vendor Reconciliation Account - Domestic | AF169: 2408422 | AG169: GR/IR Account - Services & Capital | AH169: 5149027 | AI169: 5149027 | AJ169: Civil Contract Jobs | AK169: 0 | AL169: 31 | AM169: H | AP169: 45036233 | AQ169: 07-05-2019 | AR169: 09-04-2019 | AS169: 09:40:06 | AT169: 0 | AU169: -414990 | AX169: 1
A170: 1000 | B170: Tata Steel Limited | C170: 51019236 | D170: CI0004108179 | E170: RE | F170: 5030 | G170: 2020 | H170: 1 | I170: 43537 | J170: 43564 | K170: -1844550.3 | L170: =K170-Q170+T170 -> -1563178.4 | M170: INR | N170: -1844550.3 | O170: INR | P170: -1844550.3 | Q170: -281371.99 | R170: -1563178.4 | S170: 0 | T170: 0 | U170: T018 | V170: TATA BLUESCOPE STEEL PRIVATE LIMIT | X170: Bill Receipt Date :22.03.2019 | Y170: 4404040292 | Z170: 51019236 | AB170: 4404040292 | AD170: 2408402 | AE170: Vendor Reconciliation Account - Domestic | AF170: 2408409 | AG170: Gr/Ir For Stores And Spares | AH170: 6005101 | AI170: 6005101 | AJ170: Purchase of Stores | AK170: 0 | AL170: 31 | AM170: H | AP170: 45019034 | AQ170: 16-04-2019 | AR170: 09-04-2019 | AS170: 15:39:51 | AT170: 0 | AU170: -1844550.3 | AX170: 1
A171: 1000 | B171: Tata Steel Limited | C171: 51019944 | D171: CI0004107087 | E171: RE | F171: 9600 | G171: 2020 | H171: 1 | I171: 43492 | J171: 43565 | K171: -309.75 | L171: =K171-Q171+T171 -> -262.5 | M171: INR | N171: -309.75 | O171: INR | P171: -309.75 | Q171: -47.25 | R171: -262.5 | S171: 0 | T171: 0 | U171: T040 | V171: TATA BLUESCOPE STEEL PRIVATE LIMIT | Y171: 2300049475 | Z171: 51019944 | AB171: 2300049475 | AD171: 2408402 | AE171: Vendor Reconciliation Account - Domestic | AF171: 2408424 | AG171: GR/IR Account - Capital (Project System) | AH171: 5149121 | AI171: 5149121 | AJ171: Purchase of Capital goods-Project System | AK171: 0 | AL171: 31 | AM171: H | AP171: 45020062 | AQ171: 17-04-2019 | AR171: 10-04-2019 | AS171: 09:20:14 | AT171: 0 | AU171: -309.75 | AX171: 1
A172: 1000 | B172: Tata Steel Limited | C172: 51019945 | D172: CI0004107088 | E172: RE | F172: 9600 | G172: 2020 | H172: 1 | I172: 43492 | J172: 43565 | K172: -10752.75 | L172: =K172-Q172+T172 -> -9112.5 | M172: INR | N172: -10752.75 | O172: INR | P172: -10752.75 | Q172: -1640.25 | R172: -9112.5 | S172: 0 | T172: 0 | U172: T040 | V172: TATA BLUESCOPE STEEL PRIVATE LIMIT | Y172: 2300049475 | Z172: 51019945 | AB172: 2300049475 | AD172: 2408402 | AE172: Vendor Reconciliation Account - Domestic | AF172: 2408424 | AG172: GR/IR Account - Capital (Project System) | AH172: 5149121 | AI172: 5149121 | AJ172: Purchase of Capital goods-Project System | AK172: 0 | AL172: 31 | AM172: H | AP172: 45020062 | AQ172: 17-04-2019 | AR172: 10-04-2019 | AS172: 09:20:19 | AT172: 0 | AU172: -10752.75 | AX172: 1
A173: 1000 | B173: Tata Steel Limited | C173: 51019946 | D173: CI0004107101 | E173: RE | F173: 9600 | G173: 2020 | H173: 1 | I173: 43492 | J173: 43565 | K173: -1618.96 | L173: =K173-Q173+T173 -> -1372 | M173: INR | N173: -1618.96 | O173: INR | P173: -1618.96 | Q173: -246.96 | R173: -1372 | S173: 0 | T173: 0 | U173: T040 | V173: TATA BLUESCOPE STEEL PRIVATE LIMIT | Y173: 2300049475 | Z173: 51019946 | AB173: 2300049475 | AD173: 2408402 | AE173: Vendor Reconciliation Account - Domestic | AF173: 2408424 | AG173: GR/IR Account - Capital (Project System) | AH173: 5149121 | AI173: 5149121 | AJ173: Purchase of Capital goods-Project System | AK173: 0 | AL173: 31 | AM173: H | AP173: 45020062 | AQ173: 17-04-2019 | AR173: 10-04-2019 | AS173: 09:20:23 | AT173: 0 | AU173: -1618.96 | AX173: 1
A174: 1000 | B174: Tata Steel Limited | C174: 51019947 | D174: CI0004107102 | E174: RE | F174: 9600 | G174: 2020 | H174: 1 | I174: 43492 | J174: 43565 | K174: -5286.4 | L174: =K174-Q174+T174 -> -4480 | M174: INR | N174: -5286.4 | O174: INR | P174: -5286.4 | Q174: -806.4 | R174: -4480 | S174: 0 | T174: 0 | U174: T040 | V174: TATA BLUESCOPE STEEL PRIVATE LIMIT | Y174: 2300049475 | Z174: 51019947 | AB174: 2300049475 | AD174: 2408402 | AE174: Vendor Reconciliation Account - Domestic | AF174: 2408424 | AG174: GR/IR Account - Capital (Project System) | AH174: 5149121 | AI174: 5149121 | AJ174: Purchase of Capital goods-Project System | AK174: 0 | AL174: 31 | AM174: H | AP174: 45020062 | AQ174: 17-04-2019 | AR174: 10-04-2019 | AS174: 09:20:28 | AT174: 0 | AU174: -5286.4 | AX174: 1
A175: 1000 | B175: Tata Steel Limited | C175: 51035916 | D175: OM/CLEAN/06 | E175: RE | F175: 9600 | G175: 2020 | H175: 1 | I175: 43551 | J175: 43572 | K175: -165299.87 | L175: =K175-Q175+T175 -> -142500 | M175: INR | N175: -165299.87 | O175: INR | P175: -168150 | Q175: -25650 | R175: -139649.87 | S175: -142500 | T175: -2850.13 | U175: T018 | V175: TATA BLUESCOPE STEEL PRIVATE LIMIT | X175: CLEANING OF ROOF | Y175: 4404338294 | Z175: 51035916 | AB175: 4404338294 | AD175: 2408402 | AE175: Vendor Reconciliation Account - Domestic | AF175: 2408422 | AG175: GR/IR Account - Services & Capital | AH175: 5020001 | AI175: 5020001 | AJ175: REPAIRS TO BUILDINGS. | AK175: 0 | AL175: 31 | AM175: H | AP175: 45041132 | AQ175: 13-05-2019 | AR175: 17-04-2019 | AS175: 13:31:42 | AT175: 0 | AU175: -165299.87 | AX175: 2
A176: 1000 | B176: Tata Steel Limited | C176: 51035916 | D176: OM/CLEAN/06 | E176: RE | F176: 9600 | G176: 2020 | H176: 1 | I176: 43551 | J176: 43572 | K176: -214989.02 | L176: =K176-Q176+T176 -> -185335.5 | M176: INR | N176: -214989.02 | O176: INR | P176: -218695.89 | Q176: -33360.39 | R176: -181628.63 | S176: -185335.5 | T176: -3706.87 | U176: T018 | V176: TATA BLUESCOPE STEEL PRIVATE LIMIT | X176: CLEANING OF ROOF | Y176: 4404338294 | Z176: 51035916 | AB176: 4404338294 | AD176: 2408402 | AE176: Vendor Reconciliation Account - Domestic | AF176: 2408422 | AG176: GR/IR Account - Services & Capital | AH176: 5020001 | AI176: 5020001 | AJ176: REPAIRS TO BUILDINGS. | AK176: 0 | AL176: 31 | AM176: H | AP176: 45041132 | AQ176: 13-05-2019 | AR176: 17-04-2019 | AS176: 13:31:42 | AT176: 0 | AU176: -214989.02 | AX176: 1
A177: 1000 | B177: Tata Steel Limited | C177: 51038398 | D177: CI0001102734 | E177: RE | F177: 7000 | G177: 2020 | H177: 1 | I177: 43543 | J177: 43573 | K177: -1164518 | L177: =K177-Q177+T177 -> -986879.6 | M177: INR | N177: -1164518 | O177: INR | P177: -1164518 | Q177: -177638.4 | R177: -986879.6 | S177: 0 | T177: 0 | U177: T018 | V177: TATA BLUESCOPE STEEL PRIVATE LIMIT | X177: CONSTRN SHEET;0.50 MM,1072 MM,2.50 RMT, | Y177: 2100554502 | Z177: 51038398 | AB177: 2100554502 | AD177: 2408402 | AE177: Vendor Reconciliation Account - Domestic | AF177: 2408409 | AG177: Gr/Ir For Stores And Spares | AH177: 5000007 | AI177: 5000007 | AJ177: Consumption of Stores | AK177: 0 | AL177: 31 | AM177: H | AP177: 45024071 | AQ177: 22-04-2019 | AR177: 18-04-2019 | AS177: 15:59:16 | AT177: 0 | AU177: -1164518 | AX177: 1
A178: 1000 | B178: Tata Steel Limited | C178: 51038775 | D178: CI0001102733 | E178: RE | F178: 7000 | G178: 2020 | H178: 1 | I178: 43543 | J178: 43573 | K178: -974532 | L178: =K178-Q178+T178 -> -825874.5 | M178: INR | N178: -974532 | O178: INR | P178: -974532 | Q178: -148657.5 | R178: -825874.5 | S178: 0 | T178: 0 | U178: T018 | V178: TATA BLUESCOPE STEEL PRIVATE LIMIT | X178: CONSTRN SHEET;0.50 MM,1072 MM,5.75 RMT, | Y178: 2100553171 | Z178: 51038775 | AB178: 2100553171 | AD178: 2408402 | AE178: Vendor Reconciliation Account - Domestic | AF178: 2408409 | AG178: Gr/Ir For Stores And Spares | AH178: 5000007 | AI178: 5000007 | AJ178: Consumption of Stores | AK178: 0 | AL178: 31 | AM178: H | AP178: 45024071 | AQ178: 22-04-2019 | AR178: 18-04-2019 | AS178: 17:21:59 | AT178: 0 | AU178: -974532 | AX178: 1
A179: 1000 | B179: Tata Steel Limited | C179: 51079211 | D179: 2300039831 | E179: RE | F179: 5030 | G179: 2020 | H179: 2 | I179: 43594 | J179: 43594 | K179: 24.55 | L179: =K179-Q179+T179 -> 24.55 | M179: INR | N179: 24.55 | O179: INR | P179: 24.55 | Q179: 0 | R179: 24.55 | S179: 0 | T179: 0 | U179: T018 | V179: TATA BLUESCOPE STEEL PRIVATE LIMIT | X179: *GR/IR Clearing | Y179: 2300039831 | Z179: 51079211 | AB179: 2300039831 | AD179: 2408402 | AE179: Vendor Reconciliation Account - Domestic | AF179: 2408426 | AG179: Oth chg Clearing For Capital (Project System ) | AH179: 5149121 | AI179: 5149121 | AJ179: Purchase of Capital goods-Project System | AK179: 0 | AL179: 22 | AM179: S | AR179: 09-05-2019 | AS179: 14:59:07 | AT179: 0 | AU179: 24.55 | AX179: 5
A180: 1000 | B180: Tata Steel Limited | C180: 51043071 | D180: CI0004107085 | E180: RE | F180: 9600 | G180: 2020 | H180: 1 | I180: 43492 | J180: 43577 | K180: -832.49 | L180: =K180-Q180+T180 -> -705.5 | M180: INR | N180: -832.49 | O180: INR | P180: -832.49 | Q180: -126.99 | R180: -705.5 | S180: 0 | T180: 0 | U180: T040 | V180: TATA BLUESCOPE STEEL PRIVATE LIMIT | X180: Mail from Abhinandan Ojha on dtd 24.04.2019 | Y180: 2300049475 | Z180: 51043071 | AB180: 2300049475 | AD180: 2408402 | AE180: Vendor Reconciliation Account - Domestic | AF180: 2408424 | AG180: GR/IR Account - Capital (Project System) | AH180: 5149121 | AI180: 5149121 | AJ180: Purchase of Capital goods-Project System | AK180: 0 | AL180: 31 | AM180: H | AP180: 45082766 | AQ180: 04-07-2019 | AR180: 22-04-2019 | AS180: 10:20:38 | AT180: 0 | AU180: -832.49 | AX180: 1
A181: 1000 | B181: Tata Steel Limited | C181: 51043072 | D181: CI0004107086 | E181: RE | F181: 9600 | G181: 2020 | H181: 1 | I181: 43492 | J181: 43577 | K181: -27251.51 | L181: =K181-Q181+T181 -> -23094.5 | M181: INR | N181: -27251.51 | O181: INR | P181: -27251.51 | Q181: -4157.01 | R181: -23094.5 | S181: 0 | T181: 0 | U181: T040 | V181: TATA BLUESCOPE STEEL PRIVATE LIMIT | X181: Mail from Abhinandan Ojha on dtd 24.04.2019 | Y181: 2300049475 | Z181: 51043072 | AB181: 2300049475 | AD181: 2408402 | AE181: Vendor Reconciliation Account - Domestic | AF181: 2408424 | AG181: GR/IR Account - Capital (Project System) | AH181: 5149121 | AI181: 5149121 | AJ181: Purchase of Capital goods-Project System | AK181: 0 | AL181: 31 | AM181: H | AP181: 45082766 | AQ181: 04-07-2019 | AR181: 22-04-2019 | AS181: 10:20:43 | AT181: 0 | AU181: -27251.51 | AX181: 1
A182: 1000 | B182: Tata Steel Limited | C182: 51043074 | D182: CI0004107099 | E182: RE | F182: 9600 | G182: 2020 | H182: 1 | I182: 43492 | J182: 43577 | K182: -4956 | L182: =K182-Q182+T182 -> -4200 | M182: INR | N182: -4956 | O182: INR | P182: -4956 | Q182: -756 | R182: -4200 | S182: 0 | T182: 0 | U182: T040 | V182: TATA BLUESCOPE STEEL PRIVATE LIMIT | X182: Mail from Abhinandan Ojha on dtd 24.04.2019 | Y182: 2300049475 | Z182: 51043074 | AB182: 2300049475 | AD182: 2408402 | AE182: Vendor Reconciliation Account - Domestic | AF182: 2408424 | AG182: GR/IR Account - Capital (Project System) | AH182: 5149121 | AI182: 5149121 | AJ182: Purchase of Capital goods-Project System | AK182: 0 | AL182: 31 | AM182: H | AP182: 45082766 | AQ182: 04-07-2019 | AR182: 22-04-2019 | AS182: 10:20:47 | AT182: 0 | AU182: -4956 | AX182: 1
A183: 1000 | B183: Tata Steel Limited | C183: 51043076 | D183: CI0004107100 | E183: RE | F183: 9600 | G183: 2020 | H183: 1 | I183: 43492 | J183: 43577 | K183: -8673 | L183: =K183-Q183+T183 -> -7350 | M183: INR | N183: -8673 | O183: INR | P183: -8673 | Q183: -1323 | R183: -7350 | S183: 0 | T183: 0 | U183: T040 | V183: TATA BLUESCOPE STEEL PRIVATE LIMIT | X183: Mail from Abhinandan Ojha on dtd 24.04.2019 | Y183: 2300049475 | Z183: 51043076 | AB183: 2300049475 | AD183: 2408402 | AE183: Vendor Reconciliation Account - Domestic | AF183: 2408424 | AG183: GR/IR Account - Capital (Project System) | AH183: 5149121 | AI183: 5149121 | AJ183: Purchase of Capital goods-Project System | AK183: 0 | AL183: 31 | AM183: H | AP183: 45082766 | AQ183: 04-07-2019 | AR183: 22-04-2019 | AS183: 10:20:53 | AT183: 0 | AU183: -8673 | AX183: 1
A184: 1000 | B184: Tata Steel Limited | C184: 51047406 | D184: CI0004107078 | E184: RE | F184: 9600 | G184: 2020 | H184: 1 | I184: 43492 | J184: 43578 | K184: -21655.36 | L184: =K184-Q184+T184 -> -18352 | M184: INR | N184: -21655.36 | O184: INR | P184: -21655.36 | Q184: -3303.36 | R184: -18352 | S184: 0 | T184: 0 | U184: T040 | V184: TATA BLUESCOPE STEEL PRIVATE LIMIT | X184: Mail from Abhinandan Ojha on dtd 24.04.2019 | Y184: 2300049475 | Z184: 51047406 | AB184: 2300049475 | AD184: 2408402 | AE184: Vendor Reconciliation Account - Domestic | AF184: 2408424 | AG184: GR/IR Account - Capital (Project System) | AH184: 5149121 | AI184: 5149121 | AJ184: Purchase of Capital goods-Project System | AK184: 0 | AL184: 31 | AM184: H | AP184: 45070150 | AQ184: 19-06-2019 | AR184: 23-04-2019 | AS184: 17:58:59 | AT184: 0 | AU184: -21655.36 | AX184: 1
A185: 1000 | B185: Tata Steel Limited | C185: 51047407 | D185: CI0004107079 | E185: RE | F185: 9600 | G185: 2020 | H185: 1 | I185: 43492 | J185: 43578 | K185: -21655.36 | L185: =K185-Q185+T185 -> -18352 | M185: INR | N185: -21655.36 | O185: INR | P185: -21655.36 | Q185: -3303.36 | R185: -18352 | S185: 0 | T185: 0 | U185: T040 | V185: TATA BLUESCOPE STEEL PRIVATE LIMIT | X185: Mail from Abhinandan Ojha on dtd 24.04.2019 | Y185: 2300049475 | Z185: 51047407 | AB185: 2300049475 | AD185: 2408402 | AE185: Vendor Reconciliation Account - Domestic | AF185: 2408424 | AG185: GR/IR Account - Capital (Project System) | AH185: 5149121 | AI185: 5149121 | AJ185: Purchase of Capital goods-Project System | AK185: 0 | AL185: 31 | AM185: H | AP185: 45070150 | AQ185: 19-06-2019 | AR185: 23-04-2019 | AS185: 17:59:04 | AT185: 0 | AU185: -21655.36 | AX185: 1
A186: 1000 | B186: Tata Steel Limited | C186: 51047408 | D186: CI0004107080 | E186: RE | F186: 9600 | G186: 2020 | H186: 1 | I186: 43492 | J186: 43578 | K186: -7858.8 | L186: =K186-Q186+T186 -> -6660 | M186: INR | N186: -7858.8 | O186: INR | P186: -7858.8 | Q186: -1198.8 | R186: -6660 | S186: 0 | T186: 0 | U186: T040 | V186: TATA BLUESCOPE STEEL PRIVATE LIMIT | X186: Mail from Abhinandan Ojha on dtd 24.04.2019 | Y186: 2300049475 | Z186: 51047408 | AB186: 2300049475 | AD186: 2408402 | AE186: Vendor Reconciliation Account - Domestic | AF186: 2408424 | AG186: GR/IR Account - Capital (Project System) | AH186: 5149121 | AI186: 5149121 | AJ186: Purchase of Capital goods-Project System | AK186: 0 | AL186: 31 | AM186: H | AP186: 45070150 | AQ186: 19-06-2019 | AR186: 23-04-2019 | AS186: 17:59:08 | AT186: 0 | AU186: -7858.8 | AX186: 1
A187: 1000 | B187: Tata Steel Limited | C187: 51047409 | D187: CI0004107081 | E187: RE | F187: 9600 | G187: 2020 | H187: 1 | I187: 43492 | J187: 43578 | K187: -2124 | L187: =K187-Q187+T187 -> -1800 | M187: INR | N187: -2124 | O187: INR | P187: -2124 | Q187: -324 | R187: -1800 | S187: 0 | T187: 0 | U187: T040 | V187: TATA BLUESCOPE STEEL PRIVATE LIMIT | X187: Mail from Abhinandan Ojha on dtd 24.04.2019 | Y187: 2300049475 | Z187: 51047409 | AB187: 2300049475 | AD187: 2408402 | AE187: Vendor Reconciliation Account - Domestic | AF187: 2408424 | AG187: GR/IR Account - Capital (Project System) | AH187: 5149121 | AI187: 5149121 | AJ187: Purchase of Capital goods-Project System | AK187: 0 | AL187: 31 | AM187: H | AP187: 45070150 | AQ187: 19-06-2019 | AR187: 23-04-2019 | AS187: 17:59:13 | AT187: 0 | AU187: -2124 | AX187: 1
A188: 1000 | B188: Tata Steel Limited | C188: 51047410 | D188: CI0004107082 | E188: RE | F188: 9600 | G188: 2020 | H188: 1 | I188: 43492 | J188: 43578 | K188: -511128.8 | L188: =K188-Q188+T188 -> -433160 | M188: INR | N188: -511128.8 | O188: INR | P188: -511128.8 | Q188: -77968.8 | R188: -433160 | S188: 0 | T188: 0 | U188: T040 | V188: TATA BLUESCOPE STEEL PRIVATE LIMIT | X188: Mail from Abhinandan Ojha on dtd 24.04.2019 | Y188: 2300049475 | Z188: 51047410 | AB188: 2300049475 | AD188: 2408402 | AE188: Vendor Reconciliation Account - Domestic | AF188: 2408424 | AG188: GR/IR Account - Capital (Project System) | AH188: 5149121 | AI188: 5149121 | AJ188: Purchase of Capital goods-Project System | AK188: 0 | AL188: 31 | AM188: H | AP188: 45070150 | AQ188: 19-06-2019 | AR188: 23-04-2019 | AS188: 17:59:17 | AT188: 0 | AU188: -511128.8 | AX188: 1
A189: 1000 | B189: Tata Steel Limited | C189: 51047411 | D189: CI0004107091 | E189: RE | F189: 9600 | G189: 2020 | H189: 1 | I189: 43492 | J189: 43578 | K189: -4956 | L189: =K189-Q189+T189 -> -4200 | M189: INR | N189: -4956 | O189: INR | P189: -4956 | Q189: -756 | R189: -4200 | S189: 0 | T189: 0 | U189: T040 | V189: TATA BLUESCOPE STEEL PRIVATE LIMIT | X189: Mail from Abhinandan Ojha on dtd 24.04.2019 | Y189: 2300049475 | Z189: 51047411 | AB189: 2300049475 | AD189: 2408402 | AE189: Vendor Reconciliation Account - Domestic | AF189: 2408424 | AG189: GR/IR Account - Capital (Project System) | AH189: 5149121 | AI189: 5149121 | AJ189: Purchase of Capital goods-Project System | AK189: 0 | AL189: 31 | AM189: H | AP189: 45070150 | AQ189: 19-06-2019 | AR189: 23-04-2019 | AS189: 17:59:22 | AT189: 0 | AU189: -4956 | AX189: 1
A190: 1000 | B190: Tata Steel Limited | C190: 51047412 | D190: CI0004107092 | E190: RE | F190: 9600 | G190: 2020 | H190: 1 | I190: 43492 | J190: 43578 | K190: -61914.6 | L190: =K190-Q190+T190 -> -52470 | M190: INR | N190: -61914.6 | O190: INR | P190: -61914.6 | Q190: -9444.6 | R190: -52470 | S190: 0 | T190: 0 | U190: T040 | V190: TATA BLUESCOPE STEEL PRIVATE LIMIT | X190: Mail from Abhinandan Ojha on dtd 24.04.2019 | Y190: 2300049475 | Z190: 51047412 | AB190: 2300049475 | AD190: 2408402 | AE190: Vendor Reconciliation Account - Domestic | AF190: 2408424 | AG190: GR/IR Account - Capital (Project System) | AH190: 5149121 | AI190: 5149121 | AJ190: Purchase of Capital goods-Project System | AK190: 0 | AL190: 31 | AM190: H | AP190: 45070150 | AQ190: 19-06-2019 | AR190: 23-04-2019 | AS190: 17:59:27 | AT190: 0 | AU190: -61914.6 | AX190: 1
A191: 1000 | B191: Tata Steel Limited | C191: 51047413 | D191: CI0004107093 | E191: RE | F191: 9600 | G191: 2020 | H191: 1 | I191: 43492 | J191: 43578 | K191: -61914.6 | L191: =K191-Q191+T191 -> -52470 | M191: INR | N191: -61914.6 | O191: INR | P191: -61914.6 | Q191: -9444.6 | R191: -52470 | S191: 0 | T191: 0 | U191: T040 | V191: TATA BLUESCOPE STEEL PRIVATE LIMIT | X191: Mail from Abhinandan Ojha on dtd 24.04.2019 | Y191: 2300049475 | Z191: 51047413 | AB191: 2300049475 | AD191: 2408402 | AE191: Vendor Reconciliation Account - Domestic | AF191: 2408424 | AG191: GR/IR Account - Capital (Project System) | AH191: 5149121 | AI191: 5149121 | AJ191: Purchase of Capital goods-Project System | AK191: 0 | AL191: 31 | AM191: H | AP191: 45070150 | AQ191: 19-06-2019 | AR191: 23-04-2019 | AS191: 17:59:31 | AT191: 0 | AU191: -61914.6 | AX191: 1
... A196: 1000 | B196: Tata Steel Limited | C196: 51760823 | D196: 2 | E196: RE | F196: 5010 | G196: 2020 | H196: 12 | I196: 40382 | J196: 43908 | K196: -7802.46 | L196: =K196-Q196+T196 -> -7802.46 | M196: INR | N196: -7802.46 | O196: INR | P196: -7802.46 | Q196: 0 | R196: -7802.46 | S196: 0 | T196: 0 | U196: T018 | V196: TATA BLUESCOPE STEEL PRIVATE LIMIT | X196: GRIR CLEARING >3 YRS | Y196: GRIR Clearing > 3 yr | Z196: 51760823 | AB196: 2100204812 | AD196: 2408402 | AE196: Vendor Reconciliation Account - Domestic | AF196: 2408413 | AG196: Freight Clearing For Stores | AH196: 6005102 | AI196: 6005102 | AJ196: Freight - Purchase of Stores | AK196: 0 | AL196: 31 | AM196: H | AP196: 93385931 | AQ196: 28-03-2020 | AR196: 18-03-2020 | AS196: 11:47:29 | AT196: 0 | AU196: -7802.46 | AX196: 1
A197: 1000 | B197: Tata Steel Limited | C197: 51786309 | D197: 1C DT.130910 | E197: RE | F197: 5030 | G197: 2020 | H197: 12 | I197: 40448 | J197: 43921 | K197: -12970.19 | L197: =K197-Q197+T197 -> -12970.19 | M197: INR | N197: -12970.19 | O197: INR | P197: -12970.19 | Q197: 0 | R197: -12970.19 | S197: 0 | T197: 0 | U197: T018 | V197: TATA BLUESCOPE STEEL PRIVATE LIMIT | X197: GRIR Clearing > 3 years | Y197: GRIR Clearing > 3 Years | Z197: 51786309 | AB197: 3700479949 | AD197: 2408402 | AE197: Vendor Reconciliation Account - Domestic | AF197: 2408413 | AG197: Freight Clearing For Stores | AH197: 6005102 | AI197: 6005102 | AJ197: Freight - Purchase of Stores | AK197: 0 | AL197: 31 | AM197: H | AR197: 01-04-2020 | AS197: 17:32:54 | AT197: 0 | AU197: -12970.19 | AX197: 1
A198: 1000 | B198: Tata Steel Limited | C198: 51062273 | D198: CI0004107075 | E198: RE | F198: 9600 | G198: 2020 | H198: 1 | I198: 43492 | J198: 43585 | K198: -43091.71 | L198: =K198-Q198+T198 -> -36518.4 | M198: INR | N198: -43091.71 | O198: INR | P198: -43091.71 | Q198: -6573.31 | R198: -36518.4 | S198: 0 | T198: 0 | U198: T040 | V198: TATA BLUESCOPE STEEL PRIVATE LIMIT | Y198: 2300049475 | Z198: 51062273 | AB198: 2300049475 | AD198: 2408402 | AE198: Vendor Reconciliation Account - Domestic | AF198: 2408424 | AG198: GR/IR Account - Capital (Project System) | AH198: 5149121 | AI198: 5149121 | AJ198: Purchase of Capital goods-Project System | AK198: 0 | AL198: 31 | AM198: H | AP198: 45039858 | AQ198: 10-05-2019 | AR198: 30-04-2019 | AS198: 10:42:08 | AT198: 0 | AU198: -43091.71 | AX198: 1
A199: 1000 | B199: Tata Steel Limited | C199: 51062274 | D199: CI0004107076 | E199: RE | F199: 9600 | G199: 2020 | H199: 1 | I199: 43492 | J199: 43585 | K199: -121118.98 | L199: =K199-Q199+T199 -> -102643.2 | M199: INR | N199: -121118.98 | O199: INR | P199: -121118.98 | Q199: -18475.78 | R199: -102643.2 | S199: 0 | T199: 0 | U199: T040 | V199: TATA BLUESCOPE STEEL PRIVATE LIMIT | Y199: 2300049475 | Z199: 51062274 | AB199: 2300049475 | AD199: 2408402 | AE199: Vendor Reconciliation Account - Domestic | AF199: 2408424 | AG199: GR/IR Account - Capital (Project System) | AH199: 5149121 | AI199: 5149121 | AJ199: Purchase of Capital goods-Project System | AK199: 0 | AL199: 31 | AM199: H | AP199: 45046601 | AQ199: 20-05-2019 | AR199: 30-04-2019 | AS199: 10:42:13 | AT199: 0 | AU199: -121118.98 | AX199: 1
A200: 1000 | B200: Tata Steel Limited | C200: 51062276 | D200: CI0004107077 | E200: RE | F200: 9600 | G200: 2020 | H200: 1 | I200: 43492 | J200: 43585 | K200: -13345.8 | L200: =K200-Q200+T200 -> -11310 | M200: INR | N200: -13345.8 | O200: INR | P200: -13345.8 | Q200: -2035.8 | R200: -11310 | S200: 0 | T200: 0 | U200: T040 | V200: TATA BLUESCOPE STEEL PRIVATE LIMIT | Y200: 2300049475 | Z200: 51062276 | AB200: 2300049475 | AD200: 2408402 | AE200: Vendor Reconciliation Account - Domestic | AF200: 2408424 | AG200: GR/IR Account - Capital (Project System) | AH200: 5149121 | AI200: 5149121 | AJ200: Purchase of Capital goods-Project System | AK200: 0 | AL200: 31 | AM200: H | AP200: 45039858 | AQ200: 10-05-2019 | AR200: 30-04-2019 | AS200: 10:42:17 | AT200: 0 | AU200: -13345.8 | AX200: 1
A201: 1000 | B201: Tata Steel Limited | C201: 51062277 | D201: CI0004107089 | E201: RE | F201: 9600 | G201: 2020 | H201: 1 | I201: 43492 | J201: 43585 | K201: -2950 | L201: =K201-Q201+T201 -> -2500 | M201: INR | N201: -2950 | O201: INR | P201: -2950 | Q201: -450 | R201: -2500 | S201: 0 | T201: 0 | U201: T040 | V201: TATA BLUESCOPE STEEL PRIVATE LIMIT | Y201: 2300049475 | Z201: 51062277 | AB201: 2300049475 | AD201: 2408402 | AE201: Vendor Reconciliation Account - Domestic | AF201: 2408424 | AG201: GR/IR Account - Capital (Project System) | AH201: 5149121 | AI201: 5149121 | AJ201: Purchase of Capital goods-Project System | AK201: 0 | AL201: 31 | AM201: H | AP201: 45039858 | AQ201: 10-05-2019 | AR201: 30-04-2019 | AS201: 10:42:22 | AT201: 0 | AU201: -2950 | AX201: 1
A202: 1000 | B202: Tata Steel Limited | C202: 51062278 | D202: CI0004107090 | E202: RE | F202: 9600 | G202: 2020 | H202: 1 | I202: 43492 | J202: 43585 | K202: -4425 | L202: =K202-Q202+T202 -> -3750 | M202: INR | N202: -4425 | O202: INR | P202: -4425 | Q202: -675 | R202: -3750 | S202: 0 | T202: 0 | U202: T040 | V202: TATA BLUESCOPE STEEL PRIVATE LIMIT | Y202: 2300049475 | Z202: 51062278 | AB202: 2300049475 | AD202: 2408402 | AE202: Vendor Reconciliation Account - Domestic | AF202: 2408424 | AG202: GR/IR Account - Capital (Project System) | AH202: 5149121 | AI202: 5149121 | AJ202: Purchase of Capital goods-Project System | AK202: 0 | AL202: 31 | AM202: H | AP202: 45039858 | AQ202: 10-05-2019 | AR202: 30-04-2019 | AS202: 10:42:27 | AT202: 0 | AU202: -4425 | AX202: 1
A203: 1000 | B203: Tata Steel Limited | C203: 51062279 | D203: CI0004107097 | E203: RE | F203: 9600 | G203: 2020 | H203: 1 | I203: 43492 | J203: 43585 | K203: -3186 | L203: =K203-Q203+T203 -> -2700 | M203: INR | N203: -3186 | O203: INR | P203: -3186 | Q203: -486 | R203: -2700 | S203: 0 | T203: 0 | U203: T040 | V203: TATA BLUESCOPE STEEL PRIVATE LIMIT | Y203: 2300049475 | Z203: 51062279 | AB203: 2300049475 | AD203: 2408402 | AE203: Vendor Reconciliation Account - Domestic | AF203: 2408424 | AG203: GR/IR Account - Capital (Project System) | AH203: 5149121 | AI203: 5149121 | AJ203: Purchase of Capital goods-Project System | AK203: 0 | AL203: 31 | AM203: H | AP203: 45039858 | AQ203: 10-05-2019 | AR203: 30-04-2019 | AS203: 10:42:32 | AT203: 0 | AU203: -3186 | AX203: 1
A204: 1000 | B204: Tata Steel Limited | C204: 51062280 | D204: CI0004107098 | E204: RE | F204: 9600 | G204: 2020 | H204: 1 | I204: 43492 | J204: 43585 | K204: -660.8 | L204: =K204-Q204+T204 -> -560 | M204: INR | N204: -660.8 | O204: INR | P204: -660.8 | Q204: -100.8 | R204: -560 | S204: 0 | T204: 0 | U204: T040 | V204: TATA BLUESCOPE STEEL PRIVATE LIMIT | Y204: 2300049475 | Z204: 51062280 | AB204: 2300049475 | AD204: 2408402 | AE204: Vendor Reconciliation Account - Domestic | AF204: 2408424 | AG204: GR/IR Account - Capital (Project System) | AH204: 5149121 | AI204: 5149121 | AJ204: Purchase of Capital goods-Project System | AK204: 0 | AL204: 31 | AM204: H | AP204: 45039858 | AQ204: 10-05-2019 | AR204: 30-04-2019 | AS204: 10:42:36 | AT204: 0 | AU204: -660.8 | AX204: 1
A205: 1000 | B205: Tata Steel Limited | C205: 51079211 | D205: 2300039831 | E205: RE | F205: 9000 | G205: 2020 | H205: 2 | I205: 43594 | J205: 43594 | K205: -24.56 | L205: =K205-Q205+T205 -> -24.56 | M205: INR | N205: -24.56 | O205: INR | P205: -24.56 | Q205: 0 | R205: -24.56 | S205: 0 | T205: 0 | U205: T018 | V205: TATA BLUESCOPE STEEL PRIVATE LIMIT | X205: *GR/IR Clearing | Y205: 2300039831 | Z205: 51079211 | AB205: 2300039831 | AD205: 2408402 | AE205: Vendor Reconciliation Account - Domestic | AF205: 2408426 | AG205: Oth chg Clearing For Capital (Project System ) | AH205: 5149121 | AI205: 5149121 | AJ205: Purchase of Capital goods-Project System | AK205: 0 | AL205: 31 | AM205: H | AR205: 09-05-2019 | AS205: 14:59:07 | AT205: 0 | AU205: -24.56 | AX205: 6
A206: 1000 | B206: Tata Steel Limited | C206: 51041862 | D206: SI1904100003 | E206: RE | F206: 9500 | G206: 2020 | H206: 1 | I206: 43574 | J206: 43575 | K206: -236918.2 | L206: =K206-Q206+T206 -> -204240 | M206: INR | N206: -236918.2 | O206: INR | P206: -241003.2 | Q206: -36763.2 | R206: -200155 | S206: -204240 | T206: -4085 | U206: T040 | V206: TATA BLUESCOPE STEEL PRIVATE LIMIT | X206: CIVIL | Y206: 4404421415 | Z206: 51041862 | AB206: 4404421415 | AD206: 2408402 | AE206: Vendor Reconciliation Account - Domestic | AF206: 2408422 | AG206: GR/IR Account - Services & Capital | AH206: 5149028 | AI206: 5149028 | AJ206: Mechanical Contract Jobs | AK206: 0 | AL206: 31 | AM206: H | AP206: 45047801 | AQ206: 21-05-2019 | AR206: 20-04-2019 | AS206: 12:20:32 | AT206: 0 | AU206: -236918.2 | AX206: 1
A207: 1000 | B207: Tata Steel Limited | C207: 51253749 | D207: OM/ARC/31 | E207: RE | F207: 9600 | G207: 2020 | H207: 4 | I207: 43669 | J207: 43671 | K207: -529366 | L207: =K207-Q207+T207 -> -456350 | M207: INR | N207: -529366 | O207: INR | P207: -538493 | Q207: -82143 | R207: -447223 | S207: -456350 | T207: -9127 | U207: T018 | V207: TATA BLUESCOPE STEEL PRIVATE LIMIT | X207: SUPPLY AND FIXING OF SHEET | Y207: 4404791817 | Z207: 51253749 | AB207: 4404791817 | AD207: 2408402 | AE207: Vendor Reconciliation Account - Domestic | AF207: 2408422 | AG207: GR/IR Account - Services & Capital | AH207: 5149027 | AI207: 5149027 | AJ207: Civil Contract Jobs | AK207: 0 | AL207: 31 | AM207: H | AP207: 45117965 | AQ207: 21-08-2019 | AR207: 25-07-2019 | AS207: 16:53:52 | AT207: 0 | AU207: -529366 | AX207: 1
A208: 1000 | B208: Tata Steel Limited | C208: 51253765 | D208: OM/ARC/32 | E208: RE | F208: 9600 | G208: 2020 | H208: 4 | I208: 43669 | J208: 43671 | K208: -114840 | L208: =K208-Q208+T208 -> -99000 | M208: INR | N208: -114840 | O208: INR | P208: -116820 | Q208: -17820 | R208: -97020 | S208: -99000 | T208: -1980 | U208: T018 | V208: TATA BLUESCOPE STEEL PRIVATE LIMIT | X208: SUPPLY AND FIXING OF SHEET | Y208: 4404791828 | Z208: 51253765 | AB208: 4404791828 | AD208: 2408402 | AE208: Vendor Reconciliation Account - Domestic | AF208: 2408422 | AG208: GR/IR Account - Services & Capital | AH208: 5149027 | AI208: 5149027 | AJ208: Civil Contract Jobs | AK208: 0 | AL208: 31 | AM208: H | AP208: 45117965 | AQ208: 21-08-2019 | AR208: 25-07-2019 | AS208: 16:57:56 | AT208: 0 | AU208: -114840 | AX208: 1
A209: 1000 | B209: Tata Steel Limited | C209: 51253765 | D209: OM/ARC/32 | E209: RE | F209: 9600 | G209: 2020 | H209: 4 | I209: 43669 | J209: 43671 | K209: -447876 | L209: =K209-Q209+T209 -> -386100 | M209: INR | N209: -447876 | O209: INR | P209: -455598 | Q209: -69498 | R209: -378378 | S209: -386100 | T209: -7722 | U209: T018 | V209: TATA BLUESCOPE STEEL PRIVATE LIMIT | X209: SUPPLY AND FIXING OF SHEET | Y209: 4404791828 | Z209: 51253765 | AB209: 4404791828 | AD209: 2408402 | AE209: Vendor Reconciliation Account - Domestic | AF209: 2408422 | AG209: GR/IR Account - Services & Capital | AH209: 5149027 | AI209: 5149027 | AJ209: Civil Contract Jobs | AK209: 0 | AL209: 31 | AM209: H | AP209: 45117965 | AQ209: 21-08-2019 | AR209: 25-07-2019 | AS209: 16:57:56 | AT209: 0 | AU209: -447876 | AX209: 2
A210: 1000 | B210: Tata Steel Limited | C210: 51253775 | D210: OM/ARC/33 | E210: RE | F210: 9600 | G210: 2020 | H210: 4 | I210: 43669 | J210: 43671 | K210: -10412.14 | L210: =K210-Q210+T210 -> -8975.99 | M210: INR | N210: -10412.14 | O210: INR | P210: -10591.67 | Q210: -1615.68 | R210: -8796.46 | S210: -8975.99 | T210: -179.53 | U210: T018 | V210: TATA BLUESCOPE STEEL PRIVATE LIMIT | X210: SUPPLY AND FIXING OF SHEET | Y210: 4404791822 | Z210: 51253775 | AB210: 4404791822 | AD210: 2408402 | AE210: Vendor Reconciliation Account - Domestic | AF210: 2408422 | AG210: GR/IR Account - Services & Capital | AH210: 5149027 | AI210: 5149027 | AJ210: Civil Contract Jobs | AK210: 0 | AL210: 31 | AM210: H | AP210: 45117965 | AQ210: 21-08-2019 | AR210: 25-07-2019 | AS210: 17:01:01 | AT210: 0 | AU210: -10412.14 | AX210: 1
A211: 1000 | B211: Tata Steel Limited | C211: 51253775 | D211: OM/ARC/33 | E211: RE | F211: 9600 | G211: 2020 | H211: 4 | I211: 43669 | J211: 43671 | K211: -412678.98 | L211: =K211-Q211+T211 -> -355758.01 | M211: INR | N211: -412678.98 | O211: INR | P211: -419794.45 | Q211: -64036.44 | R211: -348642.54 | S211: -355758.01 | T211: -7115.47 | U211: T018 | V211: TATA BLUESCOPE STEEL PRIVATE LIMIT | X211: SUPPLY AND FIXING OF SHEET | Y211: 4404791822 | Z211: 51253775 | AB211: 4404791822 | AD211: 2408402 | AE211: Vendor Reconciliation Account - Domestic | AF211: 2408422 | AG211: GR/IR Account - Services & Capital | AH211: 5149027 | AI211: 5149027 | AJ211: Civil Contract Jobs | AK211: 0 | AL211: 31 | AM211: H | AP211: 45117965 | AQ211: 21-08-2019 | AR211: 25-07-2019 | AS211: 17:01:01 | AT211: 0 | AU211: -412678.98 | AX211: 2
A212: 1000 | B212: Tata Steel Limited | C212: 51786311 | D212: 1B DT.130910 | E212: RE | F212: 5030 | G212: 2020 | H212: 12 | I212: 40448 | J212: 43921 | K212: -9016.07 | L212: =K212-Q212+T212 -> -9016.07 | M212: INR | N212: -9016.07 | O212: INR | P212: -9016.07 | Q212: 0 | R212: -9016.07 | S212: 0 | T212: 0 | U212: T018 | V212: TATA BLUESCOPE STEEL PRIVATE LIMIT | X212: GRIR Clearing > 3 years | Y212: GRIR Clearing > 3 Years | Z212: 51786311 | AB212: 3700479961 | AD212: 2408402 | AE212: Vendor Reconciliation Account - Domestic | AF212: 2408413 | AG212: Freight Clearing For Stores | AH212: 6005102 | AI212: 6005102 | AJ212: Freight - Purchase of Stores | AK212: 0 | AL212: 31 | AM212: H | AR212: 01-04-2020 | AS212: 17:39:25 | AT212: 0 | AU212: -9016.07 | AX212: 1
A213: 1000 | B213: Tata Steel Limited | C213: 51786380 | D213: 1A DT.130910 | E213: RE | F213: 5030 | G213: 2020 | H213: 12 | I213: 40448 | J213: 43921 | K213: -33456.06 | L213: =K213-Q213+T213 -> -33456.06 | M213: INR | N213: -33456.06 | O213: INR | P213: -33456.06 | Q213: 0 | R213: -33456.06 | S213: 0 | T213: 0 | U213: T018 | V213: TATA BLUESCOPE STEEL PRIVATE LIMIT | X213: GRIR Clearing > 3 years | Y213: GRIR Clearing > 3 Years | Z213: 51786380 | AB213: 3700479963 | AD213: 2408402 | AE213: Vendor Reconciliation Account - Domestic | AF213: 2408413 | AG213: Freight Clearing For Stores | AH213: 6005102 | AI213: 6005102 | AJ213: Freight - Purchase of Stores | AK213: 0 | AL213: 31 | AM213: H | AR213: 02-04-2020 | AS213: 09:37:47 | AT213: 0 | AU213: -33456.06 | AX213: 1
A214: 1000 | B214: Tata Steel Limited | C214: 51214149 | D214: OM/ARC/29 | E214: RE | F214: 9600 | G214: 2020 | H214: 4 | I214: 43651 | J214: 43654 | K214: -429616.8 | L214: =K214-Q214+T214 -> -370360 | M214: INR | N214: -429616.8 | O214: INR | P214: -437024.8 | Q214: -66664.8 | R214: -362952 | S214: -370360 | T214: -7408 | U214: T018 | V214: TATA BLUESCOPE STEEL PRIVATE LIMIT | X214: SUPPLY AND FIXING OF SHEET | Y214: 4404719297 | Z214: 51214149 | AB214: 4404719297 | AD214: 2408402 | AE214: Vendor Reconciliation Account - Domestic | AF214: 2408422 | AG214: GR/IR Account - Services & Capital | AH214: 5149027 | AI214: 5149027 | AJ214: Civil Contract Jobs | AK214: 0 | AL214: 31 | AM214: H | AP214: 45108277 | AQ214: 05-08-2019 | AR214: 08-07-2019 | AS214: 11:30:58 | AT214: 0 | AU214: -429616.8 | AX214: 1
A215: 1000 | B215: Tata Steel Limited | C215: 51214169 | D215: OM/ARC/30 | E215: RE | F215: 9600 | G215: 2020 | H215: 4 | I215: 43651 | J215: 43654 | K215: -355956.8 | L215: =K215-Q215+T215 -> -306860 | M215: INR | N215: -355956.8 | O215: INR | P215: -362094.8 | Q215: -55234.8 | R215: -300722 | S215: -306860 | T215: -6138 | U215: T018 | V215: TATA BLUESCOPE STEEL PRIVATE LIMIT | X215: SUPPLY AND FIXING OF SHEET | Y215: 4404719310 | Z215: 51214169 | AB215: 4404719310 | AD215: 2408402 | AE215: Vendor Reconciliation Account - Domestic | AF215: 2408422 | AG215: GR/IR Account - Services & Capital | AH215: 5149027 | AI215: 5149027 | AJ215: Civil Contract Jobs | AK215: 0 | AL215: 31 | AM215: H | AP215: 45108277 | AQ215: 05-08-2019 | AR215: 08-07-2019 | AS215: 11:34:29 | AT215: 0 | AU215: -355956.8 | AX215: 1
A216: 1000 | B216: Tata Steel Limited | C216: 51214184 | D216: OM/CLEAN/10 | E216: RE | F216: 9600 | G216: 2020 | H216: 4 | I216: 43651 | J216: 43654 | K216: -206507.32 | L216: =K216-Q216+T216 -> -178024 | M216: INR | N216: -206507.32 | O216: INR | P216: -210068.32 | Q216: -32044.32 | R216: -174463 | S216: -178024 | T216: -3561 | U216: T018 | V216: TATA BLUESCOPE STEEL PRIVATE LIMIT | X216: CLEANING OF ROOF | Y216: 4404719301 | Z216: 51214184 | AB216: 4404719301 | AD216: 2408402 | AE216: Vendor Reconciliation Account - Domestic | AF216: 2408422 | AG216: GR/IR Account - Services & Capital | AH216: 5020001 | AI216: 5020001 | AJ216: REPAIRS TO BUILDINGS. | AK216: 0 | AL216: 31 | AM216: H | AP216: 45108277 | AQ216: 05-08-2019 | AR216: 08-07-2019 | AS216: 11:38:13 | AT216: 0 | AU216: -206507.32 | AX216: 1
A217: 1000 | B217: Tata Steel Limited | C217: 51342555 | D217: SI1904100032 | E217: RE | F217: 9500 | G217: 2020 | H217: 6 | I217: 43705 | J217: 43710 | K217: -118470.88 | L217: =K217-Q217+T217 -> -102130.4 | M217: INR | N217: -118470.88 | O217: INR | P217: -120513.88 | Q217: -18383.48 | R217: -100087.4 | S217: -102130.4 | T217: -2043 | U217: T040 | V217: TATA BLUESCOPE STEEL PRIVATE LIMIT | X217: Bill Receipt Date :29.08.2019 | Y217: 4404904823 | Z217: 51342555 | AB217: 4404904823 | AD217: 2408402 | AE217: Vendor Reconciliation Account - Domestic | AF217: 2408422 | AG217: GR/IR Account - Services & Capital | AH217: 5149028 | AI217: 5149028 | AJ217: Mechanical Contract Jobs | AK217: 0 | AL217: 31 | AM217: H | AP217: 45148134 | AQ217: 01-10-2019 | AR217: 02-09-2019 | AS217: 17:04:51 | AT217: 0 | AU217: -118470.88 | AX217: 1
A218: 1000 | B218: Tata Steel Limited | C218: 51093980 | D218: CI0004105707 | E218: RE | F218: 9600 | G218: 2020 | H218: 2 | I218: 43433 | J218: 43600 | K218: -619500 | L218: =K218-Q218+T218 -> -525000 | M218: INR | N218: -619500 | O218: INR | P218: -619500 | Q218: -94500 | R218: -619500 | S218: 0 | T218: 0 | U218: T018 | V218: TATA BLUESCOPE STEEL PRIVATE LIMIT | Y218: 2300049646 | Z218: 51093980 | AB218: 2300049646 | AD218: 2408402 | AE218: Vendor Reconciliation Account - Domestic | AF218: 2408424 | AG218: GR/IR Account - Capital (Project System) | AH218: 5149121 | AI218: 5149121 | AJ218: Purchase of Capital goods-Project System | AK218: 0 | AL218: 31 | AM218: H | AP218: 45049791 | AQ218: 23-05-2019 | AR218: 15-05-2019 | AS218: 18:10:12 | AT218: 0 | AU218: -619500 | AX218: 1
A219: 1000 | B219: Tata Steel Limited | C219: 51087756 | D219: CI0004105747 | E219: RE | F219: 9600 | G219: 2020 | H219: 2 | I219: 43434 | J219: 43599 | K219: -1937796 | L219: =K219-Q219+T219 -> -1642200 | M219: INR | N219: -1937796 | O219: INR | P219: -1937796 | Q219: -295596 | R219: -1937796 | S219: 0 | T219: 0 | U219: T018 | V219: TATA BLUESCOPE STEEL PRIVATE LIMIT | Y219: 2300049646 | Z219: 51087756 | AB219: 2300049646 | AD219: 2408402 | AE219: Vendor Reconciliation Account - Domestic | AF219: 2408424 | AG219: GR/IR Account - Capital (Project System) | AH219: 5149121 | AI219: 5149121 | AJ219: Purchase of Capital goods-Project System | AK219: 0 | AL219: 31 | AM219: H | AP219: 45046600 | AQ219: 20-05-2019 | AR219: 14-05-2019 | AS219: 11:06:56 | AT219: 0 | AU219: -1937796 | AX219: 1
A220: 1000 | B220: Tata Steel Limited | C220: 51087758 | D220: CI0004105748 | E220: RE | F220: 9600 | G220: 2020 | H220: 2 | I220: 43434 | J220: 43599 | K220: -1937796 | L220: =K220-Q220+T220 -> -1642200 | M220: INR | N220: -1937796 | O220: INR | P220: -1937796 | Q220: -295596 | R220: -1937796 | S220: 0 | T220: 0 | U220: T018 | V220: TATA BLUESCOPE STEEL PRIVATE LIMIT | Y220: 2300049646 | Z220: 51087758 | AB220: 2300049646 | AD220: 2408402 | AE220: Vendor Reconciliation Account - Domestic | AF220: 2408424 | AG220: GR/IR Account - Capital (Project System) | AH220: 5149121 | AI220: 5149121 | AJ220: Purchase of Capital goods-Project System | AK220: 0 | AL220: 31 | AM220: H | AP220: 45046600 | AQ220: 20-05-2019 | AR220: 14-05-2019 | AS220: 11:07:01 | AT220: 0 | AU220: -1937796 | AX220: 1
A221: 1000 | B221: Tata Steel Limited | C221: 51093981 | D221: CI0004105749 | E221: RE | F221: 9600 | G221: 2020 | H221: 2 | I221: 43434 | J221: 43600 | K221: -1850240 | L221: =K221-Q221+T221 -> -1568000 | M221: INR | N221: -1850240 | O221: INR | P221: -1850240 | Q221: -282240 | R221: -1850240 | S221: 0 | T221: 0 | U221: T018 | V221: TATA BLUESCOPE STEEL PRIVATE LIMIT | Y221: 2300049646 | Z221: 51093981 | AB221: 2300049646 | AD221: 2408402 | AE221: Vendor Reconciliation Account - Domestic | AF221: 2408424 | AG221: GR/IR Account - Capital (Project System) | AH221: 5149121 | AI221: 5149121 | AJ221: Purchase of Capital goods-Project System | AK221: 0 | AL221: 31 | AM221: H | AP221: 45049791 | AQ221: 23-05-2019 | AR221: 15-05-2019 | AS221: 18:10:16 | AT221: 0 | AU221: -1850240 | AX221: 1
A222: 1000 | B222: Tata Steel Limited | C222: 51093982 | D222: CI0004105750 | E222: RE | F222: 9600 | G222: 2020 | H222: 2 | I222: 43434 | J222: 43600 | K222: -1639610 | L222: =K222-Q222+T222 -> -1389500 | M222: INR | N222: -1639610 | O222: INR | P222: -1639610 | Q222: -250110 | R222: -1639610 | S222: 0 | T222: 0 | U222: T018 | V222: TATA BLUESCOPE STEEL PRIVATE LIMIT | Y222: 2300049646 | Z222: 51093982 | AB222: 2300049646 | AD222: 2408402 | AE222: Vendor Reconciliation Account - Domestic | AF222: 2408424 | AG222: GR/IR Account - Capital (Project System) | AH222: 5149121 | AI222: 5149121 | AJ222: Purchase of Capital goods-Project System | AK222: 0 | AL222: 31 | AM222: H | AP222: 45049791 | AQ222: 23-05-2019 | AR222: 15-05-2019 | AS222: 18:10:20 | AT222: 0 | AU222: -1639610 | AX222: 1
A223: 1000 | B223: Tata Steel Limited | C223: 51050682 | D223: GSEZ/ERE-RAB-03 | E223: RE | F223: 9650 | G223: 2020 | H223: 1 | I223: 43462 | J223: 43580 | K223: -11906.85 | L223: =K223-Q223+T223 -> 24842.32 | M223: INR | N223: -11906.85 | O223: INR | P223: -12112.85 | Q223: -36954.56 | R223: -11906.85 | S223: -9751.37 | T223: -205.39 | U223: T040 | V223: TATA BLUESCOPE STEEL PRIVATE LIMIT | Y223: 3800014331 | Z223: 51050682 | AB223: 3800014331 | AD223: 2408402 | AE223: Vendor Reconciliation Account - Domestic | AF223: 2408422 | AG223: GR/IR Account - Services & Capital | AH223: 5149106 | AI223: 5149106 | AJ223: CAPITAL EXPENSES | AK223: 0 | AL223: 31 | AM223: H | AR223: 25-04-2019 | AS223: 12:12:59 | AT223: 0 | AU223: -11906.85 | AX223: 8
A224: 1000 | B224: Tata Steel Limited | C224: 51050682 | D224: GSEZ/ERE-RAB-03 | E224: RE | F224: 9650 | G224: 2020 | H224: 1 | I224: 43462 | J224: 43580 | K224: -214335.34 | L224: =K224-Q224+T224 -> -218032.56 | M224: INR | N224: -214335.34 | O224: INR | P224: -218031.34 | Q224: 0 | R224: -214335.34 | S224: -175534.61 | T224: -3697.22 | U224: T040 | V224: TATA BLUESCOPE STEEL PRIVATE LIMIT | Y224: 3800014331 | Z224: 51050682 | AB224: 3800014331 | AD224: 2408402 | AE224: Vendor Reconciliation Account - Domestic | AF224: 2408422 | AG224: GR/IR Account - Services & Capital | AH224: 5149106 | AI224: 5149106 | AJ224: CAPITAL EXPENSES | AK224: 0 | AL224: 31 | AM224: H | AP224: 45028294 | AQ224: 26-04-2019 | AR224: 25-04-2019 | AS224: 12:12:59 | AT224: 0 | AU224: -214335.34 | AX224: 6
A225: 1000 | B225: Tata Steel Limited | C225: 51050682 | D225: GSEZ/ERE-RAB-03 | E225: RE | F225: 9650 | G225: 2020 | H225: 1 | I225: 43462 | J225: 43580 | K225: -11906.85 | L225: =K225-Q225+T225 -> -12112.24 | M225: INR | N225: -11906.85 | O225: INR | P225: -12112.85 | Q225: 0 | R225: -11906.85 | S225: -9751.37 | T225: -205.39 | U225: T040 | V225: TATA BLUESCOPE STEEL PRIVATE LIMIT | Y225: 3800014331 | Z225: 51050682 | AB225: 3800014331 | AD225: 2408402 | AE225: Vendor Reconciliation Account - Domestic | AF225: 2408422 | AG225: GR/IR Account - Services & Capital | AH225: 5149106 | AI225: 5149106 | AJ225: CAPITAL EXPENSES | AK225: 0 | AL225: 31 | AM225: H | AR225: 25-04-2019 | AS225: 12:12:59 | AT225: 0 | AU225: -11906.85 | AX225: 7
A226: 1000 | B226: Tata Steel Limited | C226: 51087753 | D226: CI0004106485 | E226: RE | F226: 9600 | G226: 2020 | H226: 2 | I226: 43464 | J226: 43599 | K226: -696683.8 | L226: =K226-Q226+T226 -> -590410 | M226: INR | N226: -696683.8 | O226: INR | P226: -696683.8 | Q226: -106273.8 | R226: -696683.8 | S226: 0 | T226: 0 | U226: T018 | V226: TATA BLUESCOPE STEEL PRIVATE LIMIT | Y226: 2300049646 | Z226: 51087753 | AB226: 2300049646 | AD226: 2408402 | AE226: Vendor Reconciliation Account - Domestic | AF226: 2408424 | AG226: GR/IR Account - Capital (Project System) | AH226: 5149121 | AI226: 5149121 | AJ226: Purchase of Capital goods-Project System | AK226: 0 | AL226: 31 | AM226: H | AP226: 45046600 | AQ226: 20-05-2019 | AR226: 14-05-2019 | AS226: 11:06:47 | AT226: 0 | AU226: -696683.8 | AX226: 1
A227: 1000 | B227: Tata Steel Limited | C227: 51087754 | D227: CI0004106486 | E227: RE | F227: 9600 | G227: 2020 | H227: 2 | I227: 43464 | J227: 43599 | K227: -2045947.2 | L227: =K227-Q227+T227 -> -1733853.6 | M227: INR | N227: -2045947.2 | O227: INR | P227: -2045947.2 | Q227: -312093.65 | R227: -2045947.2 | S227: 0 | T227: 0 | U227: T018 | V227: TATA BLUESCOPE STEEL PRIVATE LIMIT | Y227: 2300049646 | Z227: 51087754 | AB227: 2300049646 | AD227: 2408402 | AE227: Vendor Reconciliation Account - Domestic | AF227: 2408424 | AG227: GR/IR Account - Capital (Project System) | AH227: 5149121 | AI227: 5149121 | AJ227: Purchase of Capital goods-Project System | AK227: 0 | AL227: 31 | AM227: H | AP227: 45046600 | AQ227: 20-05-2019 | AR227: 14-05-2019 | AS227: 11:06:52 | AT227: 0 | AU227: -2045947.2 | AX227: 1
A228: 1000 | B228: Tata Steel Limited | C228: 51093219 | D228: CI0001102514 | E228: RE | F228: 0700 | G228: 2020 | H228: 2 | I228: 43522 | J228: 43600 | K228: -595900 | L228: =K228-Q228+T228 -> -505000 | M228: INR | N228: -595900 | O228: INR | P228: -595900 | Q228: -90900 | R228: -505000 | S228: 0 | T228: 0 | U228: T018 | V228: TATA BLUESCOPE STEEL PRIVATE LIMIT | Y228: 2300049939 | Z228: 51093219 | AB228: 2300049939 | AD228: 2408402 | AE228: Vendor Reconciliation Account - Domestic | AF228: 2408409 | AG228: Gr/Ir For Stores And Spares | AH228: 6005101 | AI228: 6005101 | AJ228: Purchase of Stores | AK228: 0 | AL228: 31 | AM228: H | AP228: 45046600 | AQ228: 20-05-2019 | AR228: 15-05-2019 | AS228: 14:56:07 | AT228: 0 | AU228: -595900 | AX228: 1
A229: 1000 | B229: Tata Steel Limited | C229: 51093319 | D229: CI0001102515 | E229: RE | F229: 0700 | G229: 2020 | H229: 2 | I229: 43522 | J229: 43600 | K229: -909780 | L229: =K229-Q229+T229 -> -771000 | M229: INR | N229: -909780 | O229: INR | P229: -909780 | Q229: -138780 | R229: -771000 | S229: 0 | T229: 0 | U229: T018 | V229: TATA BLUESCOPE STEEL PRIVATE LIMIT | Y229: 2300049939 | Z229: 51093319 | AB229: 2300049939 | AD229: 2408402 | AE229: Vendor Reconciliation Account - Domestic | AF229: 2408409 | AG229: Gr/Ir For Stores And Spares | AH229: 6005101 | AI229: 6005101 | AJ229: Purchase of Stores | AK229: 0 | AL229: 31 | AM229: H | AP229: 45046600 | AQ229: 20-05-2019 | AR229: 15-05-2019 | AS229: 15:13:58 | AT229: 0 | AU229: -909780 | AX229: 1
A230: 1000 | B230: Tata Steel Limited | C230: 51525079 | D230: SI1904100045 | E230: RE | F230: 9600 | G230: 2020 | H230: 9 | I230: 43798 | J230: 43803 | K230: -6495.99 | L230: =K230-Q230+T230 -> -5600 | M230: INR | N230: -6495.99 | O230: INR | P230: -6608 | Q230: -1008 | R230: -5487.99 | S230: -5600 | T230: -112.01 | U230: T018 | V230: TATA BLUESCOPE STEEL PRIVATE LIMIT | X230: SUPPLY AND FIXING OF SHEET | Y230: 4405162996 | Z230: 51525079 | AB230: 4405162996 | AD230: 2408402 | AE230: Vendor Reconciliation Account - Domestic | AF230: 2408422 | AG230: GR/IR Account - Services & Capital | AH230: 5149027 | AI230: 5149027 | AJ230: Civil Contract Jobs | AK230: 0 | AL230: 31 | AM230: H | AP230: 45207813 | AQ230: 30-12-2019 | AR230: 04-12-2019 | AS230: 14:21:55 | AT230: 0 | AU230: -6495.99 | AX230: 1
A231: 1000 | B231: Tata Steel Limited | C231: 51525079 | D231: SI1904100045 | E231: RE | F231: 9600 | G231: 2020 | H231: 9 | I231: 43798 | J231: 43803 | K231: -26447.97 | L231: =K231-Q231+T231 -> -22800.01 | M231: INR | N231: -26447.97 | O231: INR | P231: -26904.01 | Q231: -4104 | R231: -22343.97 | S231: -22800.01 | T231: -456.04 | U231: T018 | V231: TATA BLUESCOPE STEEL PRIVATE LIMIT | X231: SUPPLY AND FIXING OF SHEET | Y231: 4405162996 | Z231: 51525079 | AB231: 4405162996 | AD231: 2408402 | AE231: Vendor Reconciliation Account - Domestic | AF231: 2408422 | AG231: GR/IR Account - Services & Capital | AH231: 5149027 | AI231: 5149027 | AJ231: Civil Contract Jobs | AK231: 0 | AL231: 31 | AM231: H | AP231: 45207813 | AQ231: 30-12-2019 | AR231: 04-12-2019 | AS231: 14:21:55 | AT231: 0 | AU231: -26447.97 | AX231: 3
A232: 1000 | B232: Tata Steel Limited | C232: 51091615 | D232: GSEZ/ERE-RAB-04 | E232: RE | F232: 9650 | G232: 2020 | H232: 2 | I232: 43525 | J232: 43600 | K232: -14267.87 | L232: =K232-Q232+T232 -> 29768.64 | M232: INR | N232: -14267.87 | O232: INR | P232: -14514.87 | Q232: -44282.65 | R232: -14267.87 | S232: -12300 | T232: -246.14 | U232: T040 | V232: TATA BLUESCOPE STEEL PRIVATE LIMIT | Y232: 3800014331 | Z232: 51091615 | AB232: 3800014331 | AD232: 2408402 | AE232: Vendor Reconciliation Account - Domestic | AF232: 2408422 | AG232: GR/IR Account - Services & Capital | AH232: 5149106 | AI232: 5149106 | AJ232: CAPITAL EXPENSES | AK232: 0 | AL232: 31 | AM232: H | AR232: 15-05-2019 | AS232: 11:36:36 | AT232: 0 | AU232: -14267.87 | AX232: 7
A233: 1000 | B233: Tata Steel Limited | C233: 51091615 | D233: GSEZ/ERE-RAB-04 | E233: RE | F233: 9650 | G233: 2020 | H233: 2 | I233: 43525 | J233: 43600 | K233: -256838.6 | L233: =K233-Q233+T233 -> -261269.33 | M233: INR | N233: -256838.6 | O233: INR | P233: -261267.6 | Q233: 0 | R233: -256838.6 | S233: -221414.68 | T233: -4430.73 | U233: T040 | V233: TATA BLUESCOPE STEEL PRIVATE LIMIT | Y233: 3800014331 | Z233: 51091615 | AB233: 3800014331 | AD233: 2408402 | AE233: Vendor Reconciliation Account - Domestic | AF233: 2408422 | AG233: GR/IR Account - Services & Capital | AH233: 5149106 | AI233: 5149106 | AJ233: CAPITAL EXPENSES | AK233: 0 | AL233: 31 | AM233: H | AP233: 45050489 | AQ233: 24-05-2019 | AR233: 15-05-2019 | AS233: 11:36:36 | AT233: 0 | AU233: -256838.6 | AX233: 6
A234: 1000 | B234: Tata Steel Limited | C234: 51091615 | D234: GSEZ/ERE-RAB-04 | E234: RE | F234: 9650 | G234: 2020 | H234: 2 | I234: 43525 | J234: 43600 | K234: -14267.86 | L234: =K234-Q234+T234 -> -14514 | M234: INR | N234: -14267.86 | O234: INR | P234: -14514.86 | Q234: 0 | R234: -14267.86 | S234: -12300 | T234: -246.14 | U234: T040 | V234: TATA BLUESCOPE STEEL PRIVATE LIMIT | Y234: 3800014331 | Z234: 51091615 | AB234: 3800014331 | AD234: 2408402 | AE234: Vendor Reconciliation Account - Domestic | AF234: 2408422 | AG234: GR/IR Account - Services & Capital | AH234: 5149106 | AI234: 5149106 | AJ234: CAPITAL EXPENSES | AK234: 0 | AL234: 31 | AM234: H | AR234: 15-05-2019 | AS234: 11:36:36 | AT234: 0 | AU234: -14267.86 | AX234: 8
A235: 1000 | B235: Tata Steel Limited | C235: 51099503 | D235: CI0004106487 | E235: RE | F235: 9600 | G235: 2020 | H235: 2 | I235: 43464 | J235: 43602 | K235: -59253.32 | L235: =K235-Q235+T235 -> -50214.68 | M235: INR | N235: -59253.32 | O235: INR | P235: -59253.32 | Q235: -9038.64 | R235: -50214.68 | S235: 0 | T235: 0 | U235: T040 | V235: TATA BLUESCOPE STEEL PRIVATE LIMIT | Y235: 2300049475 | Z235: 51099503 | AB235: 2300049475 | AD235: 2408402 | AE235: Vendor Reconciliation Account - Domestic | AF235: 2408424 | AG235: GR/IR Account - Capital (Project System) | AH235: 5149121 | AI235: 5149121 | AJ235: Purchase of Capital goods-Project System | AK235: 0 | AL235: 31 | AM235: H | AP235: 45053840 | AQ235: 28-05-2019 | AR235: 17-05-2019 | AS235: 18:08:53 | AT235: 0 | AU235: -59253.32 | AX235: 1
...

Sheet TBSL
A1: Company_Code | B1: Company_Name | C1: SAP_Doc_Number | D1: Reference | E1: Document_Type | F1: Business_Area | G1: Fiscal_Year | H1: Posting_Period | I1: DocChq_Date | J1: Posting_Date | K1: Amount_in_Local_Currency | L1: SOA | M1: Local_Currency | N1: Amount_in_Document_Currency | O1: Document_Currency | P1: Discount_Base_Amount | Q1: GST_Amount | R1: Net_Amount | S1: Withholding_Tax_Base_Amount | T1: Withholding_Tax_Amount | U1: VendorCustomer | V1: VendorCustomer_Name | W1: Trading_Partner | X1: Text_ | Y1: HDR_Text | Z1: InvSO_Reference | AA1: Plant | AB1: Purchasing_Document | AC1: Delivery_Note | AD1: Account | AE1: Account_Description | AF1: Offsetting_Account | AG1: Offsetting_Acct_Name | AH1: GRIR_Offsetting_Account | AI1: Final_Offsetting_Account | AJ1: Final_Offsetting_Acct_Name | AK1: WBS_Element | AL1: Posting_Key | AM1: DebitCredit | AN1: Special_GL_Ind | AO1: Reversal_Indicator | AP1: Clearing_Doc | AQ1: Clearing_Date | AR1: Entry_date | AS1: Entry_Time | AT1: Notional_GST | AU1: Gross_Amount_In_Local_Currency | AV1: DE_Indicator | AW1: PO_Line | AX1: Entry_Line
A2: 1000 | B2: Tata BlueScope Steel Ltd | C2: 100058209 | E2: AB | F2: 1109 | G2: 2019 | H2: 4 | I2: 43677 | J2: 43677 | K2: 463358.86 | L2: =K2-Q2+T2 -> 463358.86 | M2: INR | N2: 463358.86 | O2: INR | P2: 0 | Q2: 0 | R2: 463358.86 | S2: 0 | T2: 0 | U2: 312193 | V2: Tata Steel Limited ( Kalinganagar) | X2: SI1904100019 | Z2: 2316 | AB2: 4700069343/172 | AD2: 110000 | AE2: Customer - Domestic | AF2: 110000 | AG2: Customer - Domestic | AI2: 110000 | AJ2: Customer - Domestic | AK2: 0 | AL2: 4 | AM2: S | AP2: 100058463 | AQ2: 43677 | AR2: 43678 | AS2: 0.19703704 | AT2: 0 | AU2: 0 | AX2: 2
A3: 1000 | B3: Tata BlueScope Steel Ltd | C3: 100082045 | E3: AB | F3: 1101 | G3: 2019 | H3: 5 | I3: 43708 | J3: 43708 | K3: 74051 | L3: =K3-Q3+T3 -> 74051 | M3: INR | N3: 74051 | O3: INR | P3: 0 | Q3: 0 | R3: 74051 | S3: 0 | T3: 0 | U3: 318999 | V3: Tata Steel Limited | X3: Short Payment Aug 19 | Z3: 100082045 | AD3: 110000 | AE3: Customer - Domestic | AF3: 110000 | AG3: Customer - Domestic | AI3: 110000 | AJ3: Customer - Domestic | AK3: 0 | AL3: 4 | AM3: S | AR3: 43710 | AS3: 0.35267361 | AT3: 0 | AU3: 0 | AX3: 3
A4: 1000 | B4: Tata BlueScope Steel Ltd | C4: 100075998 | E4: AB | F4: 1101 | G4: 2019 | H4: 5 | I4: 43703 | J4: 43703 | K4: -6259900 | L4: =K4-Q4+T4 -> -6259900 | M4: INR | N4: -6259900 | O4: INR | P4: 0 | Q4: 0 | R4: -6259900 | S4: 0 | T4: 0 | U4: 309728 | V4: Tata Steel Ltd - Growth Shop | Z4: 100075998 | AD4: 110000 | AE4: Customer - Domestic | AF4: 310300 | AG4: Customer - Advance against Sale | AI4: 310300 | AJ4: Customer - Advance against Sale | AK4: 0 | AL4: 17 | AM4: H | AP4: 100075998 | AQ4: 43703 | AR4: 43703 | AS4: 0.73967593 | AT4: 0 | AU4: 0 | AX4: 1
A5: 1000 | B5: Tata BlueScope Steel Ltd | C5: 113598 | D5: 95004888 | E5: RV | F5: 1109 | G5: 2019 | H5: 12 | I5: 43893 | J5: 43893 | K5: 444919 | L5: =K5-Q5+T5 -> 377050 | M5: INR | N5: 444919 | O5: INR | P5: 0 | Q5: 67869 | R5: 377050 | S5: 0 | T5: 0 | U5: 312193 | V5: Tata Steel Limited ( Kalinganagar) | Z5: 2525 | AB5: SI1904100055 | AD5: 110000 | AE5: Customer - Domestic | AF5: 501020 | AG5: Revenue DS - Sale of Services Domestic | AI5: 501020 | AJ5: Revenue DS - Sale of Services Domestic | AK5: 0 | AL5: 1 | AM5: S | AR5: 43893 | AS5: 0.59444444 | AT5: 0 | AU5: 0 | AW5: 0 | AX5: 1
A6: 1000 | B6: Tata BlueScope Steel Ltd | C6: 113643 | D6: 95004889 | E6: RV | F6: 1109 | G6: 2019 | H6: 12 | I6: 43895 | J6: 43895 | K6: 570730.6 | L6: =K6-Q6+T6 -> 483670 | M6: INR | N6: 570730.6 | O6: INR | P6: 0 | Q6: 87060.6 | R6: 483670 | S6: 0 | T6: 0 | U6: 312193 | V6: Tata Steel Limited ( Kalinganagar) | Z6: 2525 | AB6: SI1904100056 | AD6: 110000 | AE6: Customer - Domestic | AF6: 501020 | AG6: Revenue DS - Sale of Services Domestic | AI6: 501020 | AJ6: Revenue DS - Sale of Services Domestic | AK6: 0 | AL6: 1 | AM6: S | AR6: 43895 | AS6: 0.77569444 | AT6: 0 | AU6: 0 | AW6: 0 | AX6: 1
A7: 1000 | B7: Tata BlueScope Steel Ltd | C7: 1400006405 | E7: DZ | F7: 1106 | G7: 2019 | H7: 6 | I7: 43738 | J7: 43738 | K7: -5496781.8 | L7: =K7-Q7+T7 -> -5496781.8 | M7: INR | N7: -5496781.8 | O7: INR | P7: 0 | Q7: 0 | R7: -5496781.8 | S7: 0 | T7: 0 | U7: 305576 | V7: Tata Steel Ltd. | X7: IL36701909309640|HDFCR52019093 | Y7: IL36701909309640|HDFCR520 | Z7: 1400006405 | AC7: Receipt | AD7: 310300 | AE7: Customer - Advance against Sale | AF7: 101105 | AG7: Stanchart- Clearing Pune | AI7: 101105 | AJ7: Stanchart- Clearing Pune | AK7: 0 | AL7: 19 | AM7: H | AN7: A | AP7: 100122444 | AQ7: 43738 | AR7: 43739 | AS7: 0.4278125 | AT7: 0 | AU7: 0 | AX7: 2
A8: 1000 | B8: Tata BlueScope Steel Ltd | C8: 100882 | D8: SI1904100005 | E8: RV | F8: 1109 | G8: 2019 | H8: 1 | I8: 43581 | J8: 43581 | K8: 651626.68 | L8: =K8-Q8+T8 -> 552226 | M8: INR | N8: 651626.68 | O8: INR | P8: 0 | Q8: 99400.68 | R8: 552226 | S8: 0 | T8: 0 | U8: 312193 | V8: Tata Steel Limited ( Kalinganagar) | Z8: 2316 | AB8: 4700069343/172 | AD8: 110000 | AE8: Customer - Domestic | AF8: 501020 | AG8: Revenue DS - Sale of Services Domestic | AI8: 501020 | AJ8: Revenue DS - Sale of Services Domestic | AK8: 0 | AL8: 1 | AM8: S | AP8: 100005107 | AQ8: 43585 | AR8: 43581 | AS8: 0.77087963 | AT8: 0 | AU8: 0 | AX8: 1
A9: 1000 | B9: Tata BlueScope Steel Ltd | C9: 100057890 | E9: AB | F9: 1109 | G9: 2019 | H9: 4 | I9: 43677 | J9: 43677 | K9: 7696 | L9: =K9-Q9+T9 -> 7696 | M9: INR | N9: 7696 | O9: INR | P9: 0 | Q9: 0 | R9: 7696 | S9: 0 | T9: 0 | U9: 312193 | V9: Tata Steel Limited ( Kalinganagar) | X9: TDS SI1904100016 | Z9: 2316 | AB9: 4700069343/172 | AD9: 110000 | AE9: Customer - Domestic | AF9: 110000 | AG9: Customer - Domestic | AI9: 110000 | AJ9: Customer - Domestic | AK9: 0 | AL9: 4 | AM9: S | AP9: 100173563 | AQ9: 43799 | AR9: 43677 | AS9: 0.62208333 | AT9: 0 | AU9: 0 | AX9: 4
A10: 1000 | B10: Tata BlueScope Steel Ltd | C10: 100078765 | E10: AB | F10: 1108 | G10: 2019 | H10: 5 | I10: 43706 | J10: 43706 | K10: -210068.32 | L10: =K10-Q10+T10 -> -210068.32 | M10: INR | N10: -210068.32 | O10: INR | P10: 0 | Q10: 0 | R10: -210068.32 | S10: 0 | T10: 0 | U10: 312193 | V10: Tata Steel Limited ( Kalinganagar) | Z10: 100078765 | AD10: 110000 | AE10: Customer - Domestic | AF10: 110000 | AG10: Customer - Domestic | AI10: 110000 | AJ10: Customer - Domestic | AK10: 0 | AL10: 17 | AM10: H | AP10: 100078765 | AQ10: 43706 | AR10: 43706 | AS10: 0.70283565 | AT10: 0 | AU10: 0 | AX10: 8
A11: 1000 | B11: Tata BlueScope Steel Ltd | C11: 1400003713 | E11: DZ | F11: 1106 | G11: 2019 | H11: 4 | I11: 43654 | J11: 43654 | K11: -844942.76 | L11: =K11-Q11+T11 -> -844942.76 | M11: INR | N11: -844942.76 | O11: INR | P11: 0 | Q11: 0 | R11: -844942.76 | S11: 0 | T11: 0 | U11: 305576 | V11: Tata Steel Ltd. | X11: IL36701907081828|HDFCR52019070 | Y11: IL36701907081828|HDFCR520 | Z11: 1400003713 | AC11: Receipt | AD11: 310300 | AE11: Customer - Advance against Sale | AF11: 101105 | AG11: Stanchart- Clearing Pune | AI11: 101105 | AJ11: Stanchart- Clearing Pune | AK11: 0 | AL11: 19 | AM11: H | AN11: A | AP11: 100057905 | AQ11: 43677 | AR11: 43656 | AS11: 0.27262731 | AT11: 0 | AU11: 0 | AX11: 2
A12: 1000 | B12: Tata BlueScope Steel Ltd | C12: 100057905 | E12: AB | F12: 1106 | G12: 2019 | H12: 4 | I12: 43677 | J12: 43677 | K12: 3199939.6 | L12: =K12-Q12+T12 -> 3199939.6 | M12: INR | N12: 3199939.6 | O12: INR | P12: 0 | Q12: 0 | R12: 3199939.6 | S12: 0 | T12: 0 | U12: 305576 | V12: Tata Steel Ltd. | Z12: 100057905 | AD12: 310300 | AE12: Customer - Advance against Sale | AF12: 310300 | AG12: Customer - Advance against Sale | AI12: 310300 | AJ12: Customer - Advance against Sale | AK12: 0 | AL12: 9 | AM12: S | AN12: A | AP12: 100057905 | AQ12: 43677 | AR12: 43677 | AS12: 0.661875 | AT12: 0 | AU12: 0 | AX12: 3
A13: 1000 | B13: Tata BlueScope Steel Ltd | C13: 100058185 | E13: AB | F13: 1106 | G13: 2019 | H13: 4 | I13: 43677 | J13: 43677 | K13: 774670 | L13: =K13-Q13+T13 -> 774670 | M13: INR | N13: 774670 | O13: INR | P13: 0 | Q13: 0 | R13: 774670 | S13: 0 | T13: 0 | U13: 305576 | V13: Tata Steel Ltd. | Z13: 100058185 | AD13: 310300 | AE13: Customer - Advance against Sale | AF13: 110000 | AG13: Customer - Domestic | AI13: 110000 | AJ13: Customer - Domestic | AK13: 0 | AL13: 9 | AM13: S | AN13: A | AP13: 100058185 | AQ13: 43677 | AR13: 43678 | AS13: 0.17371528 | AT13: 0 | AU13: 0 | AX13: 2
A14: 1000 | B14: Tata BlueScope Steel Ltd | C14: 113741 | D14: 95004891 | E14: RV | F14: 1109 | G14: 2019 | H14: 12 | I14: 43899 | J14: 43899 | K14: 533737.6 | L14: =K14-Q14+T14 -> 452320 | M14: INR | N14: 533737.6 | O14: INR | P14: 0 | Q14: 81417.6 | R14: 452320 | S14: 0 | T14: 0 | U14: 312193 | V14: Tata Steel Limited ( Kalinganagar) | Z14: 2525 | AB14: SI1904100058 | AD14: 110000 | AE14: Customer - Domestic | AF14: 501020 | AG14: Revenue DS - Sale of Services Domestic | AI14: 501020 | AJ14: Revenue DS - Sale of Services Domestic | AK14: 0 | AL14: 1 | AM14: S | AR14: 43899 | AS14: 0.68680556 | AT14: 0 | AU14: 0 | AW14: 0 | AX14: 1
A15: 1000 | B15: Tata BlueScope Steel Ltd | C15: 105301 | D15: CN1901100024 | E15: RV | F15: 1108 | G15: 2019 | H15: 4 | I15: 43677 | J15: 43677 | K15: -10620 | L15: =K15-Q15+T15 -> -9000 | M15: INR | N15: -10620 | O15: INR | P15: 0 | Q15: -1620 | R15: -9000 | S15: 0 | T15: 0 | U15: 312948 | V15: Tata Steel Limited, �Wire Division | Z15: 60002464 | AD15: 110000 | AE15: Customer - Domestic | AF15: 901000 | AG15: Freight DS - Domestic | AI15: 901000 | AJ15: Freight DS - Domestic | AK15: 0 | AL15: 11 | AM15: H | AP15: 100058213 | AQ15: 43677 | AR15: 43677 | AS15: 0.53966435 | AT15: 0 | AU15: 0 | AX15: 1
A16: 1000 | B16: Tata BlueScope Steel Ltd | C16: 100116355 | E16: AB | F16: 1108 | G16: 2019 | H16: 6 | I16: 43738 | J16: 43738 | K16: -735858.32 | L16: =K16-Q16+T16 -> -735858.32 | M16: INR | N16: -735858.32 | O16: INR | P16: 0 | Q16: 0 | R16: -735858.32 | S16: 0 | T16: 0 | U16: 312193 | V16: Tata Steel Limited ( Kalinganagar) | Z16: 100116355 | AD16: 110000 | AE16: Customer - Domestic | AF16: 110000 | AG16: Customer - Domestic | AI16: 110000 | AJ16: Customer - Domestic | AK16: 0 | AL16: 17 | AM16: H | AP16: 100116355 | AQ16: 43738 | AR16: 43738 | AS16: 0.22452546 | AT16: 0 | AU16: 0 | AX16: 6
A17: 1000 | B17: Tata BlueScope Steel Ltd | C17: 100081981 | E17: AB | F17: 1101 | G17: 2019 | H17: 5 | I17: 43708 | J17: 43708 | K17: -2478000 | L17: =K17-Q17+T17 -> -2478000 | M17: INR | N17: -2478000 | O17: INR | P17: 0 | Q17: 0 | R17: -2478000 | S17: 0 | T17: 0 | U17: 309728 | V17: Tata Steel Ltd - Growth Shop | Z17: 100081981 | AD17: 110000 | AE17: Customer - Domestic | AF17: 310300 | AG17: Customer - Advance against Sale | AI17: 310300 | AJ17: Customer - Advance against Sale | AK17: 0 | AL17: 17 | AM17: H | AP17: 100081981 | AQ17: 43708 | AR17: 43710 | AS17: 0.28978009 | AT17: 0 | AU17: 0 | AX17: 1
A18: 1000 | B18: Tata BlueScope Steel Ltd | C18: 100058228 | E18: AB | F18: 1102 | G18: 2019 | H18: 4 | I18: 43677 | J18: 43677 | K18: -24754.04 | L18: =K18-Q18+T18 -> -24754.04 | M18: INR | N18: -24754.04 | O18: INR | P18: 0 | Q18: 0 | R18: -24754.04 | S18: 0 | T18: 0 | U18: 315113 | V18: Tata Steel Limited | Z18: 100058228 | AD18: 110000 | AE18: Customer - Domestic | AF18: 310300 | AG18: Customer - Advance against Sale | AI18: 310300 | AJ18: Customer - Advance against Sale | AK18: 0 | AL18: 17 | AM18: H | AP18: 100058228 | AQ18: 43677 | AR18: 43678 | AS18: 0.20967593 | AT18: 0 | AU18: 0 | AX18: 1
A19: 1000 | B19: Tata BlueScope Steel Ltd | C19: 1600000142 | D19: GST CREDIT ENTRY | E19: DA | F19: 1106 | G19: 2019 | H19: 4 | I19: 43676 | J19: 43676 | K19: -24754.04 | L19: =K19-Q19+T19 -> -24754.04 | M19: INR | N19: -24754.04 | O19: INR | P19: -24754.04 | Q19: 0 | R19: -24754.04 | S19: 0 | T19: 0 | U19: 315113 | V19: Tata Steel Limited | X19: IGST on LD Tata Steel | Y19: GST Credit TSL LD | Z19: 1600000142 | AD19: 310300 | AE19: Customer - Advance against Sale | AF19: 198044 | AG19: IGST Input Cr : Serv Proc: (1190) Kolkata | AI19: 198044 | AJ19: IGST Input Cr : Serv Proc: (1190) Kolkata | AK19: 0 | AL19: 19 | AM19: H | AN19: A | AP19: 100058228 | AQ19: 43677 | AR19: 43676 | AS19: 0.55850694 | AT19: 0 | AU19: 0 | AX19: 2
A20: 1000 | B20: Tata BlueScope Steel Ltd | C20: 113809 | D20: 95004892 | E20: RV | F20: 1109 | G20: 2019 | H20: 12 | I20: 43901 | J20: 43901 | K20: 302032.8 | L20: =K20-Q20+T20 -> 255960 | M20: INR | N20: 302032.8 | O20: INR | P20: 0 | Q20: 46072.8 | R20: 255960 | S20: 0 | T20: 0 | U20: 312193 | V20: Tata Steel Limited ( Kalinganagar) | Z20: 2525 | AB20: SI1904100059 | AD20: 110000 | AE20: Customer - Domestic | AF20: 501020 | AG20: Revenue DS - Sale of Services Domestic | AI20: 501020 | AJ20: Revenue DS - Sale of Services Domestic | AK20: 0 | AL20: 1 | AM20: S | AR20: 43901 | AS20: 0.70486111 | AT20: 0 | AU20: 0 | AW20: 0 | AX20: 1
A21: 1000 | B21: Tata BlueScope Steel Ltd | C21: 100057906 | E21: AB | F21: 1109 | G21: 2019 | H21: 4 | I21: 43677 | J21: 43677 | K21: -380140.76 | L21: =K21-Q21+T21 -> -380140.76 | M21: INR | N21: -380140.76 | O21: INR | P21: 0 | Q21: 0 | R21: -380140.76 | S21: 0 | T21: 0 | U21: 307259 | V21: Tata Steel Limited | Z21: 100057906 | AD21: 110000 | AE21: Customer - Domestic | AF21: 310300 | AG21: Customer - Advance against Sale | AI21: 310300 | AJ21: Customer - Advance against Sale | AK21: 0 | AL21: 17 | AM21: H | AP21: 100057906 | AQ21: 43677 | AR21: 43677 | AS21: 0.66454861 | AT21: 0 | AU21: 0 | AX21: 1
A22: 1000 | B22: Tata BlueScope Steel Ltd | C22: 1600000147 | D22: TRF ENTRY | E22: DA | F22: 1106 | G22: 2019 | H22: 4 | I22: 43677 | J22: 43677 | K22: 380140.76 | L22: =K22-Q22+T22 -> 380140.76 | M22: INR | N22: 380140.76 | O22: INR | P22: 380140.76 | Q22: 0 | R22: 380140.76 | S22: 0 | T22: 0 | U22: 305576 | V22: Tata Steel Ltd. | X22: Trf to 307259 IL36701907081828 | Y22: Trf entry | Z22: 1600000147 | AD22: 110000 | AE22: Customer - Domestic | AF22: 307259 | AG22: Tata Steel Limited | AI22: 307259 | AJ22: Tata Steel Limited | AK22: 0 | AL22: 4 | AM22: S | AP22: 100057907 | AQ22: 43677 | AR22: 43677 | AS22: 0.6640162 | AT22: 0 | AU22: 0 | AX22: 1
A23: 1000 | B23: Tata BlueScope Steel Ltd | C23: 100078765 | E23: AB | F23: 1101 | G23: 2019 | H23: 5 | I23: 43706 | J23: 43706 | K23: 992081 | L23: =K23-Q23+T23 -> 992081 | M23: INR | N23: 992081 | O23: INR | P23: 0 | Q23: 0 | R23: 992081 | S23: 0 | T23: 0 | U23: 312193 | V23: Tata Steel Limited ( Kalinganagar) | Z23: 100078765 | AD23: 310300 | AE23: Customer - Advance against Sale | AF23: 110000 | AG23: Customer - Domestic | AI23: 110000 | AJ23: Customer - Domestic | AK23: 0 | AL23: 9 | AM23: S | AN23: A | AP23: 100078765 | AQ23: 43706 | AR23: 43706 | AS23: 0.70283565 | AT23: 0 | AU23: 0 | AX23: 10
A24: 1000 | B24: Tata BlueScope Steel Ltd | C24: 100081970 | E24: AB | F24: 1109 | G24: 2019 | H24: 5 | I24: 43708 | J24: 43708 | K24: -254204.56 | L24: =K24-Q24+T24 -> -254204.56 | M24: INR | N24: -254204.56 | O24: INR | P24: 0 | Q24: 0 | R24: -254204.56 | S24: 0 | T24: 0 | U24: 307259 | V24: Tata Steel Limited | Z24: 100081970 | AD24: 110000 | AE24: Customer - Domestic | AF24: 310300 | AG24: Customer - Advance against Sale | AI24: 310300 | AJ24: Customer - Advance against Sale | AK24: 0 | AL24: 17 | AM24: H | AP24: 100081970 | AQ24: 43708 | AR24: 43710 | AS24: 0.28239583 | AT24: 0 | AU24: 0 | AX24: 1
A25: 1000 | B25: Tata BlueScope Steel Ltd | C25: 100082479 | E25: AB | F25: 1101 | G25: 2019 | H25: 5 | I25: 43708 | J25: 43708 | K25: -365469.45 | L25: =K25-Q25+T25 -> -365469.45 | M25: INR | N25: -365469.45 | O25: INR | P25: 0 | Q25: 0 | R25: -365469.45 | S25: 0 | T25: 0 | U25: 318999 | V25: Tata Steel Limited | Z25: 100082479 | AD25: 111105 | AE25: Customer - Retention | AF25: 110000 | AG25: Customer - Domestic | AI25: 110000 | AJ25: Customer - Domestic | AK25: 0 | AL25: 19 | AM25: H | AN25: Y | AP25: 100082479 | AQ25: 43708 | AR25: 43711 | AS25: 0.23831019 | AT25: 0 | AU25: 0 | AX25: 4
A26: 1000 | B26: Tata BlueScope Steel Ltd | C26: 100058249 | E26: AB | F26: 1109 | G26: 2019 | H26: 4 | I26: 43677 | J26: 43677 | K26: -3614555.8 | L26: =K26-Q26+T26 -> -3614555.8 | M26: INR | N26: -3614555.8 | O26: INR | P26: 0 | Q26: 0 | R26: -3614555.8 | S26: 0 | T26: 0 | U26: 318179 | V26: Tata Steel Limited | Z26: 100058249 | AD26: 110000 | AE26: Customer - Domestic | AF26: 110000 | AG26: Customer - Domestic | AI26: 110000 | AJ26: Customer - Domestic | AK26: 0 | AL26: 17 | AM26: H | AP26: 100058249 | AQ26: 43677 | AR26: 43678 | AS26: 0.22288194 | AT26: 0 | AU26: 0 | AX26: 3
A27: 1000 | B27: Tata BlueScope Steel Ltd | C27: 100082479 | E27: AB | F27: 1101 | G27: 2019 | H27: 5 | I27: 43708 | J27: 43708 | K27: 509193.39 | L27: =K27-Q27+T27 -> 509193.39 | M27: INR | N27: 509193.39 | O27: INR | P27: 509193.39 | Q27: 0 | R27: 509193.39 | S27: 0 | T27: 0 | U27: 318999 | V27: Tata Steel Limited | X27: Retention Erection | Z27: 100082479 | AD27: 111105 | AE27: Customer - Retention | AF27: 110000 | AG27: Customer - Domestic | AI27: 110000 | AJ27: Customer - Domestic | AK27: 0 | AL27: 9 | AM27: S | AN27: Y | AP27: 100173604 | AQ27: 43799 | AR27: 43711 | AS27: 0.23831019 | AT27: 0 | AU27: 0 | AX27: 2
A28: 1000 | B28: Tata BlueScope Steel Ltd | C28: 1400003592 | E28: DZ | F28: 1106 | G28: 2019 | H28: 4 | I28: 43650 | J28: 43650 | K28: -3143638 | L28: =K28-Q28+T28 -> -3143638 | M28: INR | N28: -3143638 | O28: INR | P28: 0 | Q28: 0 | R28: -3143638 | S28: 0 | T28: 0 | U28: 305576 | V28: Tata Steel Ltd. | X28: IL36701907045618|HDFCR52019070 | Y28: IL36701907045618|HDFCR520 | Z28: 1400003592 | AC28: Receipt | AD28: 310300 | AE28: Customer - Advance against Sale | AF28: 101105 | AG28: Stanchart- Clearing Pune | AI28: 101105 | AJ28: Stanchart- Clearing Pune | AK28: 0 | AL28: 19 | AM28: H | AN28: A | AP28: 100055938 | AQ28: 43671 | AR28: 43651 | AS28: 0.75216435 | AT28: 0 | AU28: 0 | AX28: 2
A29: 1000 | B29: Tata BlueScope Steel Ltd | C29: 100075998 | E29: AB | F29: 1106 | G29: 2019 | H29: 5 | I29: 43703 | J29: 43703 | K29: 6259900 | L29: =K29-Q29+T29 -> 6259900 | M29: INR | N29: 6259900 | O29: INR | P29: 0 | Q29: 0 | R29: 6259900 | S29: 0 | T29: 0 | U29: 309728 | V29: Tata Steel Ltd - Growth Shop | Z29: 100075998 | AD29: 310300 | AE29: Customer - Advance against Sale | AF29: 110000 | AG29: Customer - Domestic | AI29: 110000 | AJ29: Customer - Domestic | AK29: 0 | AL29: 9 | AM29: S | AN29: A | AP29: 100075998 | AQ29: 43703 | AR29: 43703 | AS29: 0.73967593 | AT29: 0 | AU29: 0 | AX29: 2
A30: 1000 | B30: Tata BlueScope Steel Ltd | C30: 1600000180 | D30: TRF ENTRY | E30: DA | F30: 1106 | G30: 2019 | H30: 5 | I30: 43706 | J30: 43706 | K30: -303810.6 | L30: =K30-Q30+T30 -> -303810.6 | M30: INR | N30: -303810.6 | O30: INR | P30: -303810.6 | Q30: 0 | R30: -303810.6 | S30: 0 | T30: 0 | U30: 312193 | V30: Tata Steel Limited ( Kalinganagar) | X30: Trf Fm 309085 | Y30: Trf Entry | Z30: 1600000180 | AD30: 310300 | AE30: Customer - Advance against Sale | AF30: 309085 | AG30: TATA STEEL LIMITED | AI30: 309085 | AJ30: TATA STEEL LIMITED | AK30: 0 | AL30: 19 | AM30: H | AN30: A | AP30: 100078765 | AQ30: 43706 | AR30: 43706 | AS30: 0.46318287 | AT30: 0 | AU30: 0 | AX30: 2
A31: 1000 | B31: Tata BlueScope Steel Ltd | C31: 101042 | D31: SI1904100006 | E31: RV | F31: 1109 | G31: 2019 | H31: 1 | I31: 43584 | J31: 43584 | K31: 212211.2 | L31: =K31-Q31+T31 -> 179840 | M31: INR | N31: 212211.2 | O31: INR | P31: 0 | Q31: 32371.2 | R31: 179840 | S31: 0 | T31: 0 | U31: 312193 | V31: Tata Steel Limited ( Kalinganagar) | Z31: 2316 | AB31: 4700069343/172 | AD31: 110000 | AE31: Customer - Domestic | AF31: 501020 | AG31: Revenue DS - Sale of Services Domestic | AI31: 501020 | AJ31: Revenue DS - Sale of Services Domestic | AK31: 0 | AL31: 1 | AM31: S | AP31: 100005107 | AQ31: 43585 | AR31: 43584 | AS31: 0.60512731 | AT31: 0 | AU31: 0 | AX31: 1
A32: 1000 | B32: Tata BlueScope Steel Ltd | C32: 100116355 | E32: AB | F32: 1109 | G32: 2019 | H32: 6 | I32: 43738 | J32: 43738 | K32: 308876.8 | L32: =K32-Q32+T32 -> 308876.8 | M32: INR | N32: 308876.8 | O32: INR | P32: 0 | Q32: 0 | R32: 308876.8 | S32: 0 | T32: 0 | U32: 312193 | V32: Tata Steel Limited ( Kalinganagar) | X32: SI1904100034 | Z32: 2316 | AB32: 4700069343/172 | AD32: 110000 | AE32: Customer - Domestic | AF32: 110000 | AG32: Customer - Domestic | AI32: 110000 | AJ32: Customer - Domestic | AK32: 0 | AL32: 4 | AM32: S | AP32: 100123318 | AQ32: 43738 | AR32: 43738 | AS32: 0.22452546 | AT32: 0 | AU32: 0 | AX32: 2
A33: 1000 | B33: Tata BlueScope Steel Ltd | C33: 100081967 | E33: AB | F33: 1109 | G33: 2019 | H33: 5 | I33: 43708 | J33: 43708 | K33: 1833661 | L33: =K33-Q33+T33 -> 1833661 | M33: INR | N33: 1833661 | O33: INR | P33: 0 | Q33: 0 | R33: 1833661 | S33: 0 | T33: 0 | U33: 305576 | V33: Tata Steel Ltd. | X33: CI1904103045 | Z33: 60427 | AB33: 4404899885/901 | AD33: 110000 | AE33: Customer - Domestic | AF33: 110000 | AG33: Customer - Domestic | AI33: 110000 | AJ33: Customer - Domestic | AK33: 0 | AL33: 4 | AM33: S | AP33: 100122444 | AQ33: 43738 | AR33: 43710 | AS33: 0.27603009 | AT33: 0 | AU33: 0 | AX33: 2
A34: 1000 | B34: Tata BlueScope Steel Ltd | C34: 100113124 | D34: R OFF | E34: SA | F34: 1108 | G34: 2019 | H34: 6 | I34: 43732 | J34: 43732 | K34: -0.43 | L34: =K34-Q34+T34 -> -0.43 | M34: INR | N34: -0.43 | O34: INR | P34: 0 | Q34: 0 | R34: -0.43 | S34: 0 | T34: 0 | U34: 306263 | V34: Tata Steel limited ( CRC ) | X34: R off-Small Balance306263 | Y34: R off | Z34: 100113124 | AD34: 110000 | AE34: Customer - Domestic | AF34: 891305 | AG34: Rounding differences | AI34: 891305 | AJ34: Rounding differences | AK34: 0 | AL34: 17 | AM34: H | AP34: 100113124 | AQ34: 43732 | AR34: 43733 | AS34: 0.69230324 | AT34: 0 | AU34: 0 | AX34: 2
A35: 1000 | B35: Tata BlueScope Steel Ltd | C35: 101052 | D35: SI1904100007 | E35: RV | F35: 1109 | G35: 2019 | H35: 1 | I35: 43584 | J35: 43584 | K35: 309431.4 | L35: =K35-Q35+T35 -> 262230 | M35: INR | N35: 309431.4 | O35: INR | P35: 0 | Q35: 47201.4 | R35: 262230 | S35: 0 | T35: 0 | U35: 312193 | V35: Tata Steel Limited ( Kalinganagar) | Z35: 2316 | AB35: 4700069343/172 | AD35: 110000 | AE35: Customer - Domestic | AF35: 501020 | AG35: Revenue DS - Sale of Services Domestic | AI35: 501020 | AJ35: Revenue DS - Sale of Services Domestic | AK35: 0 | AL35: 1 | AM35: S | AP35: 100005107 | AQ35: 43585 | AR35: 43584 | AS35: 0.69956019 | AT35: 0 | AU35: 0 | AX35: 1
A36: 1000 | B36: Tata BlueScope Steel Ltd | C36: 1400004796 | E36: DZ | F36: 1101 | G36: 2019 | H36: 5 | I36: 43682 | J36: 43682 | K36: -1743896 | L36: =K36-Q36+T36 -> -1743896 | M36: INR | N36: -1743896 | O36: INR | P36: 0 | Q36: 0 | R36: -1743896 | S36: 0 | T36: 0 | U36: 318999 | V36: Tata Steel Limited | X36: IL36701908052447|HDFCR52019080 | Y36: IL36701908052447|HDFCR520 | Z36: 1400004796 | AC36: Receipt | AD36: 310300 | AE36: Customer - Advance against Sale | AF36: 101105 | AG36: Stanchart- Clearing Pune | AI36: 101105 | AJ36: Stanchart- Clearing Pune | AK36: 0 | AL36: 19 | AM36: H | AN36: A | AP36: 100076146 | AQ36: 43703 | AR36: 43685 | AS36: 0.48803241 | AT36: 0 | AU36: 0 | AX36: 2
A37: 1000 | B37: Tata BlueScope Steel Ltd | C37: 1400005437 | E37: DZ | F37: 1101 | G37: 2019 | H37: 5 | I37: 43706 | J37: 43706 | K37: -3431713.4 | L37: =K37-Q37+T37 -> -3431713.4 | M37: INR | N37: -3431713.4 | O37: INR | P37: 0 | Q37: 0 | R37: -3431713.4 | S37: 0 | T37: 0 | U37: 312948 | V37: Tata Steel Limited, �Wire Division | X37: IL36701908294865|HDFCR52019082 | Y37: IL36701908294865|HDFCR520 | Z37: 1400005437 | AC37: Receipt | AD37: 310300 | AE37: Customer - Advance against Sale | AF37: 101105 | AG37: Stanchart- Clearing Pune | AI37: 101105 | AJ37: Stanchart- Clearing Pune | AK37: 0 | AL37: 19 | AM37: H | AN37: A | AP37: 100081995 | AQ37: 43708 | AR37: 43707 | AS37: 0.49556713 | AT37: 0 | AU37: 0 | AX37: 2
A38: 1000 | B38: Tata BlueScope Steel Ltd | C38: 100058463 | E38: AB | F38: 1109 | G38: 2019 | H38: 4 | I38: 43677 | J38: 43677 | K38: 6579 | L38: =K38-Q38+T38 -> 6579 | M38: INR | N38: 6579 | O38: INR | P38: 0 | Q38: 0 | R38: 6579 | S38: 0 | T38: 0 | U38: 312193 | V38: Tata Steel Limited ( Kalinganagar) | X38: TDS SI1904100022 | Z38: 2316 | AB38: 4700069343/172 | AD38: 110000 | AE38: Customer - Domestic | AF38: 110000 | AG38: Customer - Domestic | AI38: 110000 | AJ38: Customer - Domestic | AK38: 0 | AL38: 4 | AM38: S | AP38: 100173563 | AQ38: 43799 | AR38: 43678 | AS38: 0.57675926 | AT38: 0 | AU38: 0 | AX38: 4
A39: 1000 | B39: Tata BlueScope Steel Ltd | C39: 100055956 | E39: AB | F39: 1109 | G39: 2019 | H39: 4 | I39: 43671 | J39: 43671 | K39: -672600 | L39: =K39-Q39+T39 -> -672600 | M39: INR | N39: -672600 | O39: INR | P39: 0 | Q39: 0 | R39: -672600 | S39: 0 | T39: 0 | U39: 313029 | V39: Tata Steel Limited | Z39: 100055956 | AD39: 110000 | AE39: Customer - Domestic | AF39: 310300 | AG39: Customer - Advance against Sale | AI39: 310300 | AJ39: Customer - Advance against Sale | AK39: 0 | AL39: 17 | AM39: H | AP39: 100055956 | AQ39: 43671 | AR39: 43671 | AS39: 0.65671296 | AT39: 0 | AU39: 0 | AX39: 1
A40: 1000 | B40: Tata BlueScope Steel Ltd | C40: 100074926 | E40: AB | F40: 1109 | G40: 2019 | H40: 5 | I40: 43701 | J40: 43701 | K40: -396480 | L40: =K40-Q40+T40 -> -396480 | M40: INR | N40: -396480 | O40: INR | P40: 0 | Q40: 0 | R40: -396480 | S40: 0 | T40: 0 | U40: 304431 | V40: Tata Steel Limited (Tubes Division) | Z40: 100074926 | AD40: 110000 | AE40: Customer - Domestic | AF40: 110000 | AG40: Customer - Domestic | AI40: 110000 | AJ40: Customer - Domestic | AK40: 0 | AL40: 17 | AM40: H | AP40: 100074926 | AQ40: 43701 | AR40: 43701 | AS40: 0.55780093 | AT40: 0 | AU40: 0 | AX40: 3
A41: 1000 | B41: Tata BlueScope Steel Ltd | C41: 100058209 | E41: AB | F41: 1109 | G41: 2019 | H41: 4 | I41: 43677 | J41: 43677 | K41: 388161 | L41: =K41-Q41+T41 -> 388161 | M41: INR | N41: 388161 | O41: INR | P41: 0 | Q41: 0 | R41: 388161 | S41: 0 | T41: 0 | U41: 312193 | V41: Tata Steel Limited ( Kalinganagar) | X41: SI1904100022 | Z41: 2316 | AB41: 4700069343/172 | AD41: 110000 | AE41: Customer - Domestic | AF41: 110000 | AG41: Customer - Domestic | AI41: 110000 | AJ41: Customer - Domestic | AK41: 0 | AL41: 4 | AM41: S | AP41: 100058463 | AQ41: 43677 | AR41: 43678 | AS41: 0.19703704 | AT41: 0 | AU41: 0 | AX41: 5
A42: 1000 | B42: Tata BlueScope Steel Ltd | C42: 100081967 | E42: AB | F42: 1109 | G42: 2019 | H42: 5 | I42: 43708 | J42: 43708 | K42: 2416168 | L42: =K42-Q42+T42 -> 2416168 | M42: INR | N42: 2416168 | O42: INR | P42: 0 | Q42: 0 | R42: 2416168 | S42: 0 | T42: 0 | U42: 305576 | V42: Tata Steel Ltd. | X42: CI1904102755 | Z42: 60204 | AB42: 4404806804/901 | AD42: 110000 | AE42: Customer - Domestic | AF42: 110000 | AG42: Customer - Domestic | AI42: 110000 | AJ42: Customer - Domestic | AK42: 0 | AL42: 4 | AM42: S | AP42: 100122444 | AQ42: 43738 | AR42: 43710 | AS42: 0.27603009 | AT42: 0 | AU42: 0 | AX42: 1
A43: 1000 | B43: Tata BlueScope Steel Ltd | C43: 100122987 | E43: AB | F43: 1109 | G43: 2019 | H43: 6 | I43: 43738 | J43: 43738 | K43: -2394019.4 | L43: =K43-Q43+T43 -> -2394019.4 | M43: INR | N43: -2394019.4 | O43: INR | P43: 0 | Q43: 0 | R43: -2394019.4 | S43: 0 | T43: 0 | U43: 312193 | V43: Tata Steel Limited ( Kalinganagar) | Z43: 100122987 | AD43: 110000 | AE43: Customer - Domestic | AF43: 110000 | AG43: Customer - Domestic | AI43: 110000 | AJ43: Customer - Domestic | AK43: 0 | AL43: 17 | AM43: H | AP43: 100122987 | AQ43: 43738 | AR43: 43739 | AS43: 0.48152778 | AT43: 0 | AU43: 0 | AX43: 8
A44: 1000 | B44: Tata BlueScope Steel Ltd | C44: 100055939 | E44: AB | F44: 1108 | G44: 2019 | H44: 4 | I44: 43671 | J44: 43671 | K44: -2769100 | L44: =K44-Q44+T44 -> -2769100 | M44: INR | N44: -2769100 | O44: INR | P44: 0 | Q44: 0 | R44: -2769100 | S44: 0 | T44: 0 | U44: 306263 | V44: Tata Steel limited ( CRC ) | Z44: 100055939 | AD44: 110000 | AE44: Customer - Domestic | AF44: 310300 | AG44: Customer - Advance against Sale | AI44: 310300 | AJ44: Customer - Advance against Sale | AK44: 0 | AL44: 17 | AM44: H | AP44: 100055939 | AQ44: 43671 | AR44: 43671 | AS44: 0.63871528 | AT44: 0 | AU44: 0 | AX44: 1
A45: 1000 | B45: Tata BlueScope Steel Ltd | C45: 106080 | D45: SI1901100029 | E45: RV | F45: 1101 | G45: 2019 | H45: 5 | I45: 43703 | J45: 43703 | K45: 1437239.4 | L45: =K45-Q45+T45 -> 1217999.5 | M45: INR | N45: 1437239.4 | O45: INR | P45: 0 | Q45: 219239.9 | R45: 1217999.5 | S45: 0 | T45: 0 | U45: 318999 | V45: Tata Steel Limited | Z45: 2388 | AB45: 3000125388/806 | AD45: 110000 | AE45: Customer - Domestic | AF45: 501020 | AG45: Revenue DS - Sale of Services Domestic | AI45: 501020 | AJ45: Revenue DS - Sale of Services Domestic | AK45: 0 | AL45: 1 | AM45: S | AP45: 100082045 | AQ45: 43708 | AR45: 43703 | AS45: 0.60416667 | AT45: 0 | AU45: 0 | AX45: 1
A46: 1000 | B46: Tata BlueScope Steel Ltd | C46: 100123319 | E46: AB | F46: 1106 | G46: 2019 | H46: 6 | I46: 43738 | J46: 43738 | K46: 1246952.8 | L46: =K46-Q46+T46 -> 1246952.8 | M46: INR | N46: 1246952.8 | O46: INR | P46: 0 | Q46: 0 | R46: 1246952.8 | S46: 0 | T46: 0 | U46: 305576 | V46: Tata Steel Ltd. | Z46: 100123319 | AD46: 310300 | AE46: Customer - Advance against Sale | AF46: 110000 | AG46: Customer - Domestic | AI46: 110000 | AJ46: Customer - Domestic | AK46: 0 | AL46: 9 | AM46: S | AN46: A | AP46: 100123319 | AQ46: 43738 | AR46: 43739 | AS46: 0.5869213 | AT46: 0 | AU46: 0 | AX46: 2
A47: 1000 | B47: Tata BlueScope Steel Ltd | C47: 100058463 | E47: AB | F47: 1109 | G47: 2019 | H47: 4 | I47: 43677 | J47: 43677 | K47: 7643.4 | L47: =K47-Q47+T47 -> 7643.4 | M47: INR | N47: 7643.4 | O47: INR | P47: 0 | Q47: 0 | R47: 7643.4 | S47: 0 | T47: 0 | U47: 312193 | V47: Tata Steel Limited ( Kalinganagar) | X47: TDS SI1904100020 | Z47: 2316 | AB47: 4700069343/172 | AD47: 110000 | AE47: Customer - Domestic | AF47: 110000 | AG47: Customer - Domestic | AI47: 110000 | AJ47: Customer - Domestic | AK47: 0 | AL47: 4 | AM47: S | AP47: 100173563 | AQ47: 43799 | AR47: 43678 | AS47: 0.57675926 | AT47: 0 | AU47: 0 | AX47: 2
A48: 1000 | B48: Tata BlueScope Steel Ltd | C48: 100122987 | E48: AB | F48: 1109 | G48: 2019 | H48: 6 | I48: 43738 | J48: 43738 | K48: 499730 | L48: =K48-Q48+T48 -> 499730 | M48: INR | N48: 499730 | O48: INR | P48: 0 | Q48: 0 | R48: 499730 | S48: 0 | T48: 0 | U48: 312193 | V48: Tata Steel Limited ( Kalinganagar) | X48: SI1904100038 | Z48: 2316 | AB48: 4700069343/172 | AD48: 110000 | AE48: Customer - Domestic | AF48: 110000 | AG48: Customer - Domestic | AI48: 110000 | AJ48: Customer - Domestic | AK48: 0 | AL48: 4 | AM48: S | AP48: 100173530 | AQ48: 43799 | AR48: 43739 | AS48: 0.48152778 | AT48: 0 | AU48: 0 | AX48: 4
A49: 1000 | B49: Tata BlueScope Steel Ltd | C49: 100082045 | E49: AB | F49: 1101 | G49: 2019 | H49: 5 | I49: 43708 | J49: 43708 | K49: 1437239.4 | L49: =K49-Q49+T49 -> 1437239.4 | M49: INR | N49: 1437239.4 | O49: INR | P49: 0 | Q49: 0 | R49: 1437239.4 | S49: 0 | T49: 0 | U49: 318999 | V49: Tata Steel Limited | X49: SI1901100029 | Z49: 2388 | AB49: 3000125388/806 | AD49: 110000 | AE49: Customer - Domestic | AF49: 110000 | AG49: Customer - Domestic | AI49: 110000 | AJ49: Customer - Domestic | AK49: 0 | AL49: 4 | AM49: S | AP49: 100082479 | AQ49: 43708 | AR49: 43710 | AS49: 0.35267361 | AT49: 0 | AU49: 0 | AX49: 1
A50: 1000 | B50: Tata BlueScope Steel Ltd | C50: 100057912 | E50: AB | F50: 1101 | G50: 2019 | H50: 4 | I50: 43677 | J50: 43677 | K50: 527318.91 | L50: =K50-Q50+T50 -> 527318.91 | M50: INR | N50: 527318.91 | O50: INR | P50: 0 | Q50: 0 | R50: 527318.91 | S50: 0 | T50: 0 | U50: 318999 | V50: Tata Steel Limited | X50: CI1901101069 | Z50: 100057912 | AD50: 110000 | AE50: Customer - Domestic | AF50: 110000 | AG50: Customer - Domestic | AI50: 110000 | AJ50: Customer - Domestic | AK50: 0 | AL50: 4 | AM50: S | AP50: 100082045 | AQ50: 43708 | AR50: 43677 | AS50: 0.69949074 | AT50: 0 | AU50: 0 | AX50: 4
A51: 1000 | B51: Tata BlueScope Steel Ltd | C51: 100081987 | E51: AB | F51: 1109 | G51: 2019 | H51: 5 | I51: 43708 | J51: 43708 | K51: 3942514.1 | L51: =K51-Q51+T51 -> 3942514.1 | M51: INR | N51: 3942514.1 | O51: INR | P51: 0 | Q51: 0 | R51: 3942514.1 | S51: 0 | T51: 0 | U51: 311155 | V51: Tata steel (Engineering Services) | X51: CI1904103099 | Z51: 60431 | AB51: 4404900489/133 | AD51: 110000 | AE51: Customer - Domestic | AF51: 110000 | AG51: Customer - Domestic | AI51: 110000 | AJ51: Customer - Domestic | AK51: 0 | AL51: 4 | AM51: S | AP51: 100143931 | AQ51: 43769 | AR51: 43710 | AS51: 0.29409722 | AT51: 0 | AU51: 0 | AX51: 1
A52: 1000 | B52: Tata BlueScope Steel Ltd | C52: 100057535 | D52: LD DEBIT | E52: AB | F52: 1101 | G52: 2019 | H52: 4 | I52: 43676 | J52: 43676 | K52: 24753.6 | L52: =K52-Q52+T52 -> 24753.6 | M52: INR | N52: 24753.6 | O52: INR | P52: 0 | Q52: 0 | R52: 24753.6 | S52: 0 | T52: 0 | U52: 315113 | V52: Tata Steel Limited | X52: LD Debit as per mail Attchment ( GST ) | Y52: LD Debit | Z52: 100057535 | AD52: 110000 | AE52: Customer - Domestic | AF52: M0262 | AG52: MUKTA ENGINEERS | AI52: M0262 | AJ52: MUKTA ENGINEERS | AK52: 0 | AL52: 4 | AM52: S | AO52: 100057533 | AP52: 100057535 | AQ52: 43676 | AR52: 43676 | AS52: 0.63332176 | AT52: 0 | AU52: 0 | AX52: 2
A53: 1000 | B53: Tata BlueScope Steel Ltd | C53: 100057908 | E53: AB | F53: 1109 | G53: 2019 | H53: 4 | I53: 43677 | J53: 43677 | K53: 3351327.7 | L53: =K53-Q53+T53 -> 3351327.7 | M53: INR | N53: 3351327.7 | O53: INR | P53: 0 | Q53: 0 | R53: 3351327.7 | S53: 0 | T53: 0 | U53: 311155 | V53: Tata steel (Engineering Services) | X53: CI1904102414 | Z53: 59854 | AB53: 4404744126/133 | AD53: 110000 | AE53: Customer - Domestic | AF53: 110000 | AG53: Customer - Domestic | AI53: 110000 | AJ53: Customer - Domestic | AK53: 0 | AL53: 4 | AM53: S | AP53: 100122462 | AQ53: 43738 | AR53: 43677 | AS53: 0.68739583 | AT53: 0 | AU53: 0 | AX53: 1
A54: 1000 | B54: Tata BlueScope Steel Ltd | C54: 100058209 | E54: AB | F54: 1108 | G54: 2019 | H54: 4 | I54: 43677 | J54: 43677 | K54: 210068.32 | L54: =K54-Q54+T54 -> 210068.32 | M54: INR | N54: 210068.32 | O54: INR | P54: 0 | Q54: 0 | R54: 210068.32 | S54: 0 | T54: 0 | U54: 312193 | V54: Tata Steel Limited ( Kalinganagar) | X54: SI1901100021 | Z54: 2346 | AB54: 4700070596/172 | AD54: 110000 | AE54: Customer - Domestic | AF54: 110000 | AG54: Customer - Domestic | AI54: 110000 | AJ54: Customer - Domestic | AK54: 0 | AL54: 4 | AM54: S | AP54: 100078765 | AQ54: 43706 | AR54: 43678 | AS54: 0.19703704 | AT54: 0 | AU54: 0 | AX54: 1
A55: 1000 | B55: Tata BlueScope Steel Ltd | C55: 100123327 | E55: AB | F55: 1109 | G55: 2019 | H55: 6 | I55: 43738 | J55: 43738 | K55: -396480 | L55: =K55-Q55+T55 -> -396480 | M55: INR | N55: -396480 | O55: INR | P55: 0 | Q55: 0 | R55: -396480 | S55: 0 | T55: 0 | U55: 304431 | V55: Tata Steel Limited (Tubes Division) | Z55: 100123327 | AD55: 110000 | AE55: Customer - Domestic | AF55: 110000 | AG55: Customer - Domestic | AI55: 110000 | AJ55: Customer - Domestic | AK55: 0 | AL55: 17 | AM55: H | AP55: 100123327 | AQ55: 43738 | AR55: 43739 | AS55: 0.61493056 | AT55: 0 | AU55: 0 | AX55: 3
A56: 1000 | B56: Tata BlueScope Steel Ltd | C56: 113895 | D56: 95004895 | E56: RV | F56: 1109 | G56: 2019 | H56: 12 | I56: 43903 | J56: 43903 | K56: 542115.6 | L56: =K56-Q56+T56 -> 459420 | M56: INR | N56: 542115.6 | O56: INR | P56: 0 | Q56: 82695.6 | R56: 459420 | S56: 0 | T56: 0 | U56: 312193 | V56: Tata Steel Limited ( Kalinganagar) | Z56: 2525 | AB56: SI1904100061 | AD56: 110000 | AE56: Customer - Domestic | AF56: 501020 | AG56: Revenue DS - Sale of Services Domestic | AI56: 501020 | AJ56: Revenue DS - Sale of Services Domestic | AK56: 0 | AL56: 1 | AM56: S | AR56: 43903 | AS56: 0.63819444 | AT56: 0 | AU56: 0 | AW56: 0 | AX56: 1
A57: 1000 | B57: Tata BlueScope Steel Ltd | C57: 106330 | D57: CI1901101406 | E57: RV | F57: 1108 | G57: 2019 | H57: 5 | I57: 43707 | J57: 43707 | K57: 230723.4 | L57: =K57-Q57+T57 -> 195528.3 | M57: INR | N57: 230723.4 | O57: INR | P57: 0 | Q57: 35195.1 | R57: 195528.3 | S57: 0 | T57: 0 | U57: 312948 | V57: Tata Steel Limited, �Wire Division | Z57: 60206 | AB57: 2100569670/807 | AD57: 110000 | AE57: Customer - Domestic | AF57: 501005 | AG57: Revenue DS - Domestic Sales | AI57: 501005 | AJ57: Revenue DS - Domestic Sales | AK57: 0 | AL57: 1 | AM57: S | AP57: 100081995 | AQ57: 43708 | AR57: 43707 | AS57: 0.63336806 | AT57: 0 | AU57: 0 | AX57: 1
A58: 1000 | B58: Tata BlueScope Steel Ltd | C58: 100078765 | E58: AB | F58: 1108 | G58: 2019 | H58: 5 | I58: 43706 | J58: 43706 | K58: 3560.48 | L58: =K58-Q58+T58 -> 3560.48 | M58: INR | N58: 3560.48 | O58: INR | P58: 0 | Q58: 0 | R58: 3560.48 | S58: 0 | T58: 0 | U58: 312193 | V58: Tata Steel Limited ( Kalinganagar) | X58: TDS SI1901100021 | Z58: 2346 | AB58: 4700070596/172 | AD58: 110000 | AE58: Customer - Domestic | AF58: 110000 | AG58: Customer - Domestic | AI58: 110000 | AJ58: Customer - Domestic | AK58: 0 | AL58: 4 | AM58: S | AP58: 100173563 | AQ58: 43799 | AR58: 43706 | AS58: 0.70283565 | AT58: 0 | AU58: 0 | AX58: 4
A59: 1000 | B59: Tata BlueScope Steel Ltd | C59: 104207 | D59: CI1901101068 | E59: RV | F59: 1101 | G59: 2019 | H59: 4 | I59: 43650 | J59: 43650 | K59: 371198.09 | L59: =K59-Q59+T59 -> 314574.65 | M59: INR | N59: 371198.09 | O59: INR | P59: 0 | Q59: 56623.44 | R59: 314574.65 | S59: 0 | T59: 0 | U59: 318999 | V59: Tata Steel Limited | Z59: 104207 | AD59: 110000 | AE59: Customer - Domestic | AF59: 501040 | AG59: Project Revenue - Domestic | AI59: 501040 | AJ59: Project Revenue - Domestic | AK59: 0 | AL59: 1 | AM59: S | AP59: 100057912 | AQ59: 43677 | AR59: 43650 | AS59: 0.53107639 | AT59: 0 | AU59: 0 | AX59: 1
A60: 1000 | B60: Tata BlueScope Steel Ltd | C60: 100058209 | E60: AB | F60: 1109 | G60: 2019 | H60: 4 | I60: 43677 | J60: 43677 | K60: -2445983.1 | L60: =K60-Q60+T60 -> -2445983.1 | M60: INR | N60: -2445983.1 | O60: INR | P60: 0 | Q60: 0 | R60: -2445983.1 | S60: 0 | T60: 0 | U60: 312193 | V60: Tata Steel Limited ( Kalinganagar) | Z60: 100058209 | AD60: 110000 | AE60: Customer - Domestic | AF60: 110000 | AG60: Customer - Domestic | AI60: 110000 | AJ60: Customer - Domestic | AK60: 0 | AL60: 17 | AM60: H | AP60: 100058209 | AQ60: 43677 | AR60: 43678 | AS60: 0.19703704 | AT60: 0 | AU60: 0 | AX60: 9
A61: 1000 | B61: Tata BlueScope Steel Ltd | C61: 100078765 | E61: AB | F61: 1109 | G61: 2019 | H61: 5 | I61: 43706 | J61: 43706 | K61: 7407.2 | L61: =K61-Q61+T61 -> 7407.2 | M61: INR | N61: 7407.2 | O61: INR | P61: 0 | Q61: 0 | R61: 7407.2 | S61: 0 | T61: 0 | U61: 312193 | V61: Tata Steel Limited ( Kalinganagar) | X61: TDS SI1904100023 | Z61: 2316 | AB61: 4700069343/172 | AD61: 110000 | AE61: Customer - Domestic | AF61: 110000 | AG61: Customer - Domestic | AI61: 110000 | AJ61: Customer - Domestic | AK61: 0 | AL61: 4 | AM61: S | AP61: 100173563 | AQ61: 43799 | AR61: 43706 | AS61: 0.70283565 | AT61: 0 | AU61: 0 | AX61: 5
A62: 1000 | B62: Tata BlueScope Steel Ltd | C62: 100123318 | E62: AB | F62: 1109 | G62: 2019 | H62: 6 | I62: 43738 | J62: 43738 | K62: -1268452.8 | L62: =K62-Q62+T62 -> -1268452.8 | M62: INR | N62: -1268452.8 | O62: INR | P62: 0 | Q62: 0 | R62: -1268452.8 | S62: 0 | T62: 0 | U62: 312193 | V62: Tata Steel Limited ( Kalinganagar) | Z62: 100123318 | AD62: 110000 | AE62: Customer - Domestic | AF62: 110000 | AG62: Customer - Domestic | AI62: 110000 | AJ62: Customer - Domestic | AK62: 0 | AL62: 17 | AM62: H | AP62: 100123318 | AQ62: 43738 | AR62: 43739 | AS62: 0.5847338 | AT62: 0 | AU62: 0 | AX62: 7
A63: 1000 | B63: Tata BlueScope Steel Ltd | C63: 100123319 | E63: AB | F63: 1106 | G63: 2019 | H63: 6 | I63: 43738 | J63: 43738 | K63: -1246952.8 | L63: =K63-Q63+T63 -> -1246952.8 | M63: INR | N63: -1246952.8 | O63: INR | P63: 0 | Q63: 0 | R63: -1246952.8 | S63: 0 | T63: 0 | U63: 305576 | V63: Tata Steel Ltd. | Z63: 100123319 | AD63: 110000 | AE63: Customer - Domestic | AF63: 310300 | AG63: Customer - Advance against Sale | AI63: 310300 | AJ63: Customer - Advance against Sale | AK63: 0 | AL63: 17 | AM63: H | AP63: 100123319 | AQ63: 43738 | AR63: 43739 | AS63: 0.5869213 | AT63: 0 | AU63: 0 | AX63: 1
A64: 1000 | B64: Tata BlueScope Steel Ltd | C64: 100058209 | E64: AB | F64: 1109 | G64: 2019 | H64: 4 | I64: 43677 | J64: 43677 | K64: 344383 | L64: =K64-Q64+T64 -> 344383 | M64: INR | N64: 344383 | O64: INR | P64: 0 | Q64: 0 | R64: 344383 | S64: 0 | T64: 0 | U64: 312193 | V64: Tata Steel Limited ( Kalinganagar) | X64: SI1904100021 | Z64: 2316 | AB64: 4700069343/172 | AD64: 110000 | AE64: Customer - Domestic | AF64: 110000 | AG64: Customer - Domestic | AI64: 110000 | AJ64: Customer - Domestic | AK64: 0 | AL64: 4 | AM64: S | AP64: 100058463 | AQ64: 43677 | AR64: 43678 | AS64: 0.19703704 | AT64: 0 | AU64: 0 | AX64: 4
A65: 1000 | B65: Tata BlueScope Steel Ltd | C65: 100082045 | E65: AB | F65: 1101 | G65: 2019 | H65: 5 | I65: 43708 | J65: 43708 | K65: 18773845 | L65: =K65-Q65+T65 -> 18773845 | M65: INR | N65: 18773845 | O65: INR | P65: 0 | Q65: 0 | R65: 18773845 | S65: 0 | T65: 0 | U65: 318999 | V65: Tata Steel Limited | Z65: 100082045 | AD65: 310300 | AE65: Customer - Advance against Sale | AF65: 110000 | AG65: Customer - Domestic | AI65: 110000 | AJ65: Customer - Domestic | AK65: 0 | AL65: 9 | AM65: S | AN65: A | AP65: 100082045 | AQ65: 43708 | AR65: 43710 | AS65: 0.35267361 | AT65: 0 | AU65: 0 | AX65: 6
A66: 1000 | B66: Tata BlueScope Steel Ltd | C66: 1400003914 | E66: DZ | F66: 1106 | G66: 2019 | H66: 4 | I66: 43658 | J66: 43658 | K66: -672600 | L66: =K66-Q66+T66 -> -672600 | M66: INR | N66: -672600 | O66: INR | P66: 0 | Q66: 0 | R66: -672600 | S66: 0 | T66: 0 | U66: 313029 | V66: Tata Steel Limited | X66: IL36701907126076|HDFCR52019071 | Y66: IL36701907126076|HDFCR520 | Z66: 1400003914 | AC66: Receipt | AD66: 310300 | AE66: Customer - Advance against Sale | AF66: 101105 | AG66: Stanchart- Clearing Pune | AI66: 101105 | AJ66: Stanchart- Clearing Pune | AK66: 0 | AL66: 19 | AM66: H | AN66: A | AP66: 100055956 | AQ66: 43671 | AR66: 43662 | AS66: 0.51194444 | AT66: 0 | AU66: 0 | AX66: 2
A67: 1000 | B67: Tata BlueScope Steel Ltd | C67: 100058186 | E67: AB | F67: 1101 | G67: 2019 | H67: 4 | I67: 43677 | J67: 43677 | K67: 941711 | L67: =K67-Q67+T67 -> 941711 | M67: INR | N67: 941711 | O67: INR | P67: 0 | Q67: 0 | R67: 941711 | S67: 0 | T67: 0 | U67: 306263 | V67: Tata Steel limited ( CRC ) | Z67: 100058186 | AD67: 310300 | AE67: Customer - Advance against Sale | AF67: 110000 | AG67: Customer - Domestic | AI67: 110000 | AJ67: Customer - Domestic | AK67: 0 | AL67: 9 | AM67: S | AN67: A | AP67: 100058186 | AQ67: 43677 | AR67: 43678 | AS67: 0.174375 | AT67: 0 | AU67: 0 | AX67: 3
A68: 1000 | B68: Tata BlueScope Steel Ltd | C68: 100057912 | E68: AB | F68: 1101 | G68: 2019 | H68: 4 | I68: 43677 | J68: 43677 | K68: 1515261 | L68: =K68-Q68+T68 -> 1515261 | M68: INR | N68: 1515261 | O68: INR | P68: 0 | Q68: 0 | R68: 1515261 | S68: 0 | T68: 0 | U68: 318999 | V68: Tata Steel Limited | X68: SI1901100018 | Z68: 2388 | AB68: 3000125388/806 | AD68: 110000 | AE68: Customer - Domestic | AF68: 110000 | AG68: Customer - Domestic | AI68: 110000 | AJ68: Customer - Domestic | AK68: 0 | AL68: 4 | AM68: S | AP68: 100082045 | AQ68: 43708 | AR68: 43677 | AS68: 0.69949074 | AT68: 0 | AU68: 0 | AX68: 7
A69: 1000 | B69: Tata BlueScope Steel Ltd | C69: 100057890 | E69: AB | F69: 1108 | G69: 2019 | H69: 4 | I69: 43677 | J69: 43677 | K69: 9193 | L69: =K69-Q69+T69 -> 9193 | M69: INR | N69: 9193 | O69: INR | P69: 0 | Q69: 0 | R69: 9193 | S69: 0 | T69: 0 | U69: 312193 | V69: Tata Steel Limited ( Kalinganagar) | X69: TDS SI1901100012 | Z69: 2346 | AB69: 4700070596/172 | AD69: 110000 | AE69: Customer - Domestic | AF69: 110000 | AG69: Customer - Domestic | AI69: 110000 | AJ69: Customer - Domestic | AK69: 0 | AL69: 4 | AM69: S | AP69: 100173563 | AQ69: 43799 | AR69: 43677 | AS69: 0.62208333 | AT69: 0 | AU69: 0 | AX69: 1
A70: 1000 | B70: Tata BlueScope Steel Ltd | C70: 100057912 | E70: AB | F70: 1101 | G70: 2019 | H70: 4 | I70: 43677 | J70: 43677 | K70: 7634994.6 | L70: =K70-Q70+T70 -> 7634994.6 | M70: INR | N70: 7634994.6 | O70: INR | P70: 0 | Q70: 0 | R70: 7634994.6 | S70: 0 | T70: 0 | U70: 318999 | V70: Tata Steel Limited | Z70: 100057912 | AD70: 310300 | AE70: Customer - Advance against Sale | AF70: 110000 | AG70: Customer - Domestic | AI70: 110000 | AJ70: Customer - Domestic | AK70: 0 | AL70: 9 | AM70: S | AN70: A | AP70: 100057912 | AQ70: 43677 | AR70: 43677 | AS70: 0.69949074 | AT70: 0 | AU70: 0 | AX70: 14
A71: 1000 | B71: Tata BlueScope Steel Ltd | C71: 100123318 | E71: AB | F71: 1106 | G71: 2019 | H71: 6 | I71: 43738 | J71: 43738 | K71: 1246952.8 | L71: =K71-Q71+T71 -> 1246952.8 | M71: INR | N71: 1246952.8 | O71: INR | P71: 0 | Q71: 0 | R71: 1246952.8 | S71: 0 | T71: 0 | U71: 312193 | V71: Tata Steel Limited ( Kalinganagar) | Z71: 100123318 | AD71: 310300 | AE71: Customer - Advance against Sale | AF71: 110000 | AG71: Customer - Domestic | AI71: 110000 | AJ71: Customer - Domestic | AK71: 0 | AL71: 9 | AM71: S | AN71: A | AP71: 100123318 | AQ71: 43738 | AR71: 43739 | AS71: 0.5847338 | AT71: 0 | AU71: 0 | AX71: 8
A72: 1000 | B72: Tata BlueScope Steel Ltd | C72: 100081965 | E72: AB | F72: 1109 | G72: 2019 | H72: 5 | I72: 43708 | J72: 43708 | K72: 5393 | L72: =K72-Q72+T72 -> 5393 | M72: INR | N72: 5393 | O72: INR | P72: 0 | Q72: 0 | R72: 5393 | S72: 0 | T72: 0 | U72: 304431 | V72: Tata Steel Limited (Tubes Division) | X72: TDS SI1904100012 | Z72: 2247 | AB72: 4700066177/554 | AD72: 110000 | AE72: Customer - Domestic | AF72: 110000 | AG72: Customer - Domestic | AI72: 110000 | AJ72: Customer - Domestic | AK72: 0 | AL72: 4 | AM72: S | AP72: 100172891 | AQ72: 43799 | AR72: 43710 | AS72: 0.27255787 | AT72: 0 | AU72: 0 | AX72: 3
A73: 1000 | B73: Tata BlueScope Steel Ltd | C73: 1400003823 | E73: DZ | F73: 1101 | G73: 2019 | H73: 4 | I73: 43656 | J73: 43656 | K73: -2222150.6 | L73: =K73-Q73+T73 -> -2222150.6 | M73: INR | N73: -2222150.6 | O73: INR | P73: 0 | Q73: 0 | R73: -2222150.6 | S73: 0 | T73: 0 | U73: 312193 | V73: Tata Steel Limited ( Kalinganagar) | X73: IL36701907106472|HDFCR52019071 | Y73: IL36701907106472|HDFCR520 | Z73: 1400003823 | AC73: Receipt | AD73: 310300 | AE73: Customer - Advance against Sale | AF73: 101105 | AG73: Stanchart- Clearing Pune | AI73: 101105 | AJ73: Stanchart- Clearing Pune | AK73: 0 | AL73: 19 | AM73: H | AN73: A | AP73: 100057890 | AQ73: 43677 | AR73: 43658 | AS73: 0.6880787 | AT73: 0 | AU73: 0 | AX73: 2
A74: 1000 | B74: Tata BlueScope Steel Ltd | C74: 100057907 | E74: AB | F74: 1106 | G74: 2019 | H74: 4 | I74: 43677 | J74: 43677 | K74: 380140.76 | L74: =K74-Q74+T74 -> 380140.76 | M74: INR | N74: 380140.76 | O74: INR | P74: 0 | Q74: 0 | R74: 380140.76 | S74: 0 | T74: 0 | U74: 305576 | V74: Tata Steel Ltd. | Z74: 100057907 | AD74: 310300 | AE74: Customer - Advance against Sale | AF74: 110000 | AG74: Customer - Domestic | AI74: 110000 | AJ74: Customer - Domestic | AK74: 0 | AL74: 9 | AM74: S | AN74: A | AP74: 100057907 | AQ74: 43677 | AR74: 43677 | AS74: 0.66481481 | AT74: 0 | AU74: 0 | AX74: 2
A75: 1000 | B75: Tata BlueScope Steel Ltd | C75: 100122987 | E75: AB | F75: 1109 | G75: 2019 | H75: 6 | I75: 43738 | J75: 43738 | K75: 446040 | L75: =K75-Q75+T75 -> 446040 | M75: INR | N75: 446040 | O75: INR | P75: 0 | Q75: 0 | R75: 446040 | S75: 0 | T75: 0 | U75: 312193 | V75: Tata Steel Limited ( Kalinganagar) | X75: SI1904100040 | Z75: 2316 | AB75: 4700069343/172 | AD75: 110000 | AE75: Customer - Domestic | AF75: 110000 | AG75: Customer - Domestic | AI75: 110000 | AJ75: Customer - Domestic | AK75: 0 | AL75: 4 | AM75: S | AP75: 100173530 | AQ75: 43799 | AR75: 43739 | AS75: 0.48152778 | AT75: 0 | AU75: 0 | AX75: 6
A76: 1000 | B76: Tata BlueScope Steel Ltd | C76: 100058209 | E76: AB | F76: 1109 | G76: 2019 | H76: 4 | I76: 43677 | J76: 43677 | K76: 362094.8 | L76: =K76-Q76+T76 -> 362094.8 | M76: INR | N76: 362094.8 | O76: INR | P76: 0 | Q76: 0 | R76: 362094.8 | S76: 0 | T76: 0 | U76: 312193 | V76: Tata Steel Limited ( Kalinganagar) | X76: SI1904100024 | Z76: 2316 | AB76: 4700069343/172 | AD76: 110000 | AE76: Customer - Domestic | AF76: 110000 | AG76: Customer - Domestic | AI76: 110000 | AJ76: Customer - Domestic | AK76: 0 | AL76: 4 | AM76: S | AP76: 100078765 | AQ76: 43706 | AR76: 43678 | AS76: 0.19703704 | AT76: 0 | AU76: 0 | AX76: 7
A77: 1000 | B77: Tata BlueScope Steel Ltd | C77: 104424 | D77: CI1901101130 | E77: RV | F77: 1101 | G77: 2019 | H77: 4 | I77: 43657 | J77: 43657 | K77: 567641.19 | L77: =K77-Q77+T77 -> 481051.83 | M77: INR | N77: 567641.19 | O77: INR | P77: 0 | Q77: 86589.36 | R77: 481051.83 | S77: 0 | T77: 0 | U77: 318999 | V77: Tata Steel Limited | Z77: 104424 | AD77: 110000 | AE77: Customer - Domestic | AF77: 501040 | AG77: Project Revenue - Domestic | AI77: 501040 | AJ77: Project Revenue - Domestic | AK77: 0 | AL77: 1 | AM77: S | AP77: 100057912 | AQ77: 43677 | AR77: 43657 | AS77: 0.50612269 | AT77: 0 | AU77: 0 | AX77: 1
A78: 1000 | B78: Tata BlueScope Steel Ltd | C78: 100081978 | E78: AB | F78: 1106 | G78: 2019 | H78: 5 | I78: 43708 | J78: 43708 | K78: -112395.64 | L78: =K78-Q78+T78 -> -112395.64 | M78: INR | N78: -112395.64 | O78: INR | P78: -112395.64 | Q78: 0 | R78: -112395.64 | S78: 0 | T78: 0 | U78: 309085 | V78: TATA STEEL LIMITED | X78: HDFCR52015093006260723 dt 30.09.2015 FREIGHT | Z78: 100081978 | AD78: 310300 | AE78: Customer - Advance against Sale | AF78: 310300 | AG78: Customer - Advance against Sale | AI78: 310300 | AJ78: Customer - Advance against Sale | AK78: 0 | AL78: 19 | AM78: H | AN78: A | AR78: 43710 | AS78: 0.28693287 | AT78: 0 | AU78: 0 | AX78: 1
A79: 1000 | B79: Tata BlueScope Steel Ltd | C79: 114012 | D79: 95004897 | E79: RV | F79: 1109 | G79: 2019 | H79: 12 | I79: 43906 | J79: 43906 | K79: 361257 | L79: =K79-Q79+T79 -> 306150 | M79: INR | N79: 361257 | O79: INR | P79: 0 | Q79: 55107 | R79: 306150 | S79: 0 | T79: 0 | U79: 312193 | V79: Tata Steel Limited ( Kalinganagar) | Z79: 2525 | AB79: SI1904100062 | AD79: 110000 | AE79: Customer - Domestic | AF79: 501020 | AG79: Revenue DS - Sale of Services Domestic | AI79: 501020 | AJ79: Revenue DS - Sale of Services Domestic | AK79: 0 | AL79: 1 | AM79: S | AR79: 43906 | AS79: 0.55069444 | AT79: 0 | AU79: 0 | AW79: 0 | AX79: 1
A80: 1000 | B80: Tata BlueScope Steel Ltd | C80: 104182 | D80: CI1901101063 | E80: RV | F80: 1101 | G80: 2019 | H80: 4 | I80: 43649 | J80: 43649 | K80: 287552.85 | L80: =K80-Q80+T80 -> 243688.87 | M80: INR | N80: 287552.85 | O80: INR | P80: 0 | Q80: 43863.98 | R80: 243688.87 | S80: 0 | T80: 0 | U80: 318999 | V80: Tata Steel Limited | Z80: 104182 | AD80: 110000 | AE80: Customer - Domestic | AF80: 501040 | AG80: Project Revenue - Domestic | AI80: 501040 | AJ80: Project Revenue - Domestic | AK80: 0 | AL80: 1 | AM80: S | AP80: 100057912 | AQ80: 43677 | AR80: 43649 | AS80: 0.6177662 | AT80: 0 | AU80: 0 | AX80: 1
A81: 1000 | B81: Tata BlueScope Steel Ltd | C81: 1600000229 | D81: TRF ENTRY | E81: DA | F81: 1106 | G81: 2019 | H81: 6 | I81: 43738 | J81: 43738 | K81: 1246952.8 | L81: =K81-Q81+T81 -> 1246952.8 | M81: INR | N81: 1246952.8 | O81: INR | P81: 1246952.8 | Q81: 0 | R81: 1246952.8 | S81: 0 | T81: 0 | U81: 305576 | V81: Tata Steel Ltd. | X81: Trf to 312193 | Y81: Trf Entry | Z81: 1600000229 | AD81: 110000 | AE81: Customer - Domestic | AF81: 312193 | AG81: Tata Steel Limited ( Kalinganagar) | AI81: 312193 | AJ81: Tata Steel Limited ( Kalinganagar) | AK81: 0 | AL81: 4 | AM81: S | AP81: 100123319 | AQ81: 43738 | AR81: 43739 | AS81: 0.56887731 | AT81: 0 | AU81: 0 | AX81: 1
A82: 1000 | B82: Tata BlueScope Steel Ltd | C82: 100081965 | E82: AB | F82: 1109 | G82: 2019 | H82: 5 | I82: 43708 | J82: 43708 | K82: 167714.46 | L82: =K82-Q82+T82 -> 167714.46 | M82: INR | N82: 167714.46 | O82: INR | P82: 0 | Q82: 0 | R82: 167714.46 | S82: 0 | T82: 0 | U82: 304431 | V82: Tata Steel Limited (Tubes Division) | X82: SI1904100031 | Z82: 2447 | AB82: 4700074501/554 | AD82: 110000 | AE82: Customer - Domestic | AF82: 110000 | AG82: Customer - Domestic | AI82: 110000 | AJ82: Customer - Domestic | AK82: 0 | AL82: 4 | AM82: S | AP82: 100141416 | AQ82: 43766 | AR82: 43710 | AS82: 0.27255787 | AT82: 0 | AU82: 0 | AX82: 1
A83: 1000 | B83: Tata BlueScope Steel Ltd | C83: 100078340 | D83: IL36701908223353 | E83: SA | F83: 1106 | G83: 2019 | H83: 5 | I83: 43699 | J83: 43699 | K83: -2478000 | L83: =K83-Q83+T83 -> -2478000 | M83: INR | N83: -2478000 | O83: INR | P83: -2478000 | Q83: 0 | R83: -2478000 | S83: 0 | T83: 0 | U83: 309728 | V83: Tata Steel Ltd - Growth Shop | X83: IL36701908223353|HDFCR52019082292309313 | Y83: IL36701908223353|HDFCR520 | Z83: 100078340 | AD83: 310300 | AE83: Customer - Advance against Sale | AF83: 101105 | AG83: Stanchart- Clearing Pune | AI83: 101105 | AJ83: Stanchart- Clearing Pune | AK83: 0 | AL83: 19 | AM83: H | AN83: A | AP83: 100081981 | AQ83: 43708 | AR83: 43706 | AS83: 0.43344907 | AT83: 0 | AU83: 0 | AX83: 3
A84: 1000 | B84: Tata BlueScope Steel Ltd | C84: 100081995 | E84: AB | F84: 1108 | G84: 2019 | H84: 5 | I84: 43708 | J84: 43708 | K84: -4288700.4 | L84: =K84-Q84+T84 -> -4288700.4 | M84: INR | N84: -4288700.4 | O84: INR | P84: 0 | Q84: 0 | R84: -4288700.4 | S84: 0 | T84: 0 | U84: 312948 | V84: Tata Steel Limited, �Wire Division | Z84: 100081995 | AD84: 110000 | AE84: Customer - Domestic | AF84: 110000 | AG84: Customer - Domestic | AI84: 110000 | AJ84: Customer - Domestic | AK84: 0 | AL84: 17 | AM84: H | AP84: 100081995 | AQ84: 43708 | AR84: 43710 | AS84: 0.30090278 | AT84: 0 | AU84: 0 | AX84: 4
A85: 1000 | B85: Tata BlueScope Steel Ltd | C85: 100511 | D85: CI1904100261 | E85: RV | F85: 1109 | G85: 2019 | H85: 1 | I85: 43572 | J85: 43572 | K85: 2354996.8 | L85: =K85-Q85+T85 -> 1995760 | M85: INR | N85: 2354996.8 | O85: INR | P85: 0 | Q85: 359236.8 | R85: 1995760 | S85: 0 | T85: 0 | U85: 305576 | V85: Tata Steel Ltd. | Z85: 57637 | AB85: 4404331996 | AD85: 110000 | AE85: Customer - Domestic | AF85: 501005 | AG85: Revenue DS - Domestic Sales | AI85: 501005 | AJ85: Revenue DS - Domestic Sales | AK85: 0 | AL85: 1 | AM85: S | AP85: 100004317 | AQ85: 43583 | AR85: 43572 | AS85: 0.75424769 | AT85: 0 | AU85: 0 | AX85: 1
A86: 1000 | B86: Tata BlueScope Steel Ltd | C86: 100057912 | E86: AB | F86: 1108 | G86: 2019 | H86: 4 | I86: 43677 | J86: 43677 | K86: -1783508.4 | L86: =K86-Q86+T86 -> -1783508.4 | M86: INR | N86: -1783508.4 | O86: INR | P86: 0 | Q86: 0 | R86: -1783508.4 | S86: 0 | T86: 0 | U86: 318999 | V86: Tata Steel Limited | Z86: 100057912 | AD86: 110000 | AE86: Customer - Domestic | AF86: 110000 | AG86: Customer - Domestic | AI86: 110000 | AJ86: Customer - Domestic | AK86: 0 | AL86: 17 | AM86: H | AP86: 100057912 | AQ86: 43677 | AR86: 43677 | AS86: 0.69949074 | AT86: 0 | AU86: 0 | AX86: 12
A87: 1000 | B87: Tata BlueScope Steel Ltd | C87: 100078340 | D87: IL36701908223353 | E87: SA | F87: 1106 | G87: 2019 | H87: 5 | I87: 43699 | J87: 43699 | K87: -1515173.1 | L87: =K87-Q87+T87 -> -1515173.1 | M87: INR | N87: -1515173.1 | O87: INR | P87: -1515173.1 | Q87: 0 | R87: -1515173.1 | S87: 0 | T87: 0 | U87: 312193 | V87: Tata Steel Limited ( Kalinganagar) | X87: IL36701908223353|HDFCR52019082292309313 | Y87: IL36701908223353|HDFCR520 | Z87: 100078340 | AD87: 310300 | AE87: Customer - Advance against Sale | AF87: 101105 | AG87: Stanchart- Clearing Pune | AI87: 101105 | AJ87: Stanchart- Clearing Pune | AK87: 0 | AL87: 19 | AM87: H | AN87: A | AP87: 100078765 | AQ87: 43706 | AR87: 43706 | AS87: 0.43344907 | AT87: 0 | AU87: 0 | AX87: 4
A88: 1000 | B88: Tata BlueScope Steel Ltd | C88: 100919 | D88: CI1904100505 | E88: RV | F88: 1109 | G88: 2019 | H88: 1 | I88: 43582 | J88: 43582 | K88: 1301599 | L88: =K88-Q88+T88 -> 1103050 | M88: INR | N88: 1301599 | O88: INR | P88: 0 | Q88: 198549 | R88: 1103050 | S88: 0 | T88: 0 | U88: 305576 | V88: Tata Steel Ltd. | Z88: 58180 | AB88: 4404444838/902 | AD88: 110000 | AE88: Customer - Domestic | AF88: 501005 | AG88: Revenue DS - Domestic Sales | AI88: 501005 | AJ88: Revenue DS - Domestic Sales | AK88: 0 | AL88: 1 | AM88: S | AP88: 100004317 | AQ88: 43583 | AR88: 43582 | AS88: 0.66015046 | AT88: 0 | AU88: 0 | AX88: 1
A89: 1000 | B89: Tata BlueScope Steel Ltd | C89: 100122987 | E89: AB | F89: 1109 | G89: 2019 | H89: 6 | I89: 43738 | J89: 43738 | K89: 452671.6 | L89: =K89-Q89+T89 -> 452671.6 | M89: INR | N89: 452671.6 | O89: INR | P89: 0 | Q89: 0 | R89: 452671.6 | S89: 0 | T89: 0 | U89: 312193 | V89: Tata Steel Limited ( Kalinganagar) | X89: SI1904100039 | Z89: 2316 | AB89: 4700069343/172 | AD89: 110000 | AE89: Customer - Domestic | AF89: 110000 | AG89: Customer - Domestic | AI89: 110000 | AJ89: Customer - Domestic | AK89: 0 | AL89: 4 | AM89: S | AP89: 100173530 | AQ89: 43799 | AR89: 43739 | AS89: 0.48152778 | AT89: 0 | AU89: 0 | AX89: 5
A90: 1000 | B90: Tata BlueScope Steel Ltd | C90: 1400004573 | E90: DZ | F90: 1106 | G90: 2019 | H90: 4 | I90: 43672 | J90: 43672 | K90: -774670 | L90: =K90-Q90+T90 -> -774670 | M90: INR | N90: -774670 | O90: INR | P90: 0 | Q90: 0 | R90: -774670 | S90: 0 | T90: 0 | U90: 305576 | V90: Tata Steel Ltd. | X90: IL36701907263032|HDFCR52019072 | Y90: IL36701907263032|HDFCR520 | Z90: 1400004573 | AC90: Receipt | AD90: 310300 | AE90: Customer - Advance against Sale | AF90: 101105 | AG90: Stanchart- Clearing Pune | AI90: 101105 | AJ90: Stanchart- Clearing Pune | AK90: 0 | AL90: 19 | AM90: H | AN90: A | AP90: 100058185 | AQ90: 43677 | AR90: 43677 | AS90: 0.73195602 | AT90: 0 | AU90: 0 | AX90: 2
A91: 1000 | B91: Tata BlueScope Steel Ltd | C91: 101081 | D91: CI1904100570 | E91: RV | F91: 1109 | G91: 2019 | H91: 1 | I91: 43584 | J91: 43584 | K91: 464802 | L91: =K91-Q91+T91 -> 393900 | M91: INR | N91: 464802 | O91: INR | P91: 0 | Q91: 70902 | R91: 393900 | S91: 0 | T91: 0 | U91: 305576 | V91: Tata Steel Ltd. | Z91: 58234 | AB91: 4404452217/902 | AD91: 110000 | AE91: Customer - Domestic | AF91: 501005 | AG91: Revenue DS - Domestic Sales | AI91: 501005 | AJ91: Revenue DS - Domestic Sales | AK91: 0 | AL91: 1 | AM91: S | AP91: 100005090 | AQ91: 43585 | AR91: 43584 | AS91: 0.89168981 | AT91: 0 | AU91: 0 | AX91: 1
A92: 1000 | B92: Tata BlueScope Steel Ltd | C92: 101077 | D92: SI1904100008 | E92: RV | F92: 1109 | G92: 2019 | H92: 1 | I92: 43584 | J92: 43584 | K92: 422145 | L92: =K92-Q92+T92 -> 357750 | M92: INR | N92: 422145 | O92: INR | P92: 0 | Q92: 64395 | R92: 357750 | S92: 0 | T92: 0 | U92: 312193 | V92: Tata Steel Limited ( Kalinganagar) | Z92: 2316 | AB92: 4700069343/172 | AD92: 110000 | AE92: Customer - Domestic | AF92: 501020 | AG92: Revenue DS - Sale of Services Domestic | AI92: 501020 | AJ92: Revenue DS - Sale of Services Domestic | AK92: 0 | AL92: 1 | AM92: S | AP92: 100005107 | AQ92: 43585 | AR92: 43584 | AS92: 0.82282407 | AT92: 0 | AU92: 0 | AX92: 1
A93: 1000 | B93: Tata BlueScope Steel Ltd | C93: 100081965 | E93: AB | F93: 1101 | G93: 2019 | H93: 5 | I93: 43708 | J93: 43708 | K93: 312778.66 | L93: =K93-Q93+T93 -> 312778.66 | M93: INR | N93: 312778.66 | O93: INR | P93: 0 | Q93: 0 | R93: 312778.66 | S93: 0 | T93: 0 | U93: 304431 | V93: Tata Steel Limited (Tubes Division) | Z93: 100081965 | AD93: 310300 | AE93: Customer - Advance against Sale | AF93: 110000 | AG93: Customer - Domestic | AI93: 110000 | AJ93: Customer - Domestic | AK93: 0 | AL93: 9 | AM93: S | AN93: A | AP93: 100081965 | AQ93: 43708 | AR93: 43710 | AS93: 0.27255787 | AT93: 0 | AU93: 0 | AX93: 5
A94: 1000 | B94: Tata BlueScope Steel Ltd | C94: 100055938 | E94: AB | F94: 1106 | G94: 2019 | H94: 4 | I94: 43671 | J94: 43671 | K94: 3143638 | L94: =K94-Q94+T94 -> 3143638 | M94: INR | N94: 3143638 | O94: INR | P94: 0 | Q94: 0 | R94: 3143638 | S94: 0 | T94: 0 | U94: 305576 | V94: Tata Steel Ltd. | Z94: 100055938 | AD94: 310300 | AE94: Customer - Advance against Sale | AF94: 110000 | AG94: Customer - Domestic | AI94: 110000 | AJ94: Customer - Domestic | AK94: 0 | AL94: 9 | AM94: S | AN94: A | AP94: 100055938 | AQ94: 43671 | AR94: 43671 | AS94: 0.63813657 | AT94: 0 | AU94: 0 | AX94: 2
A95: 1000 | B95: Tata BlueScope Steel Ltd | C95: 100122987 | E95: AB | F95: 1109 | G95: 2019 | H95: 6 | I95: 43738 | J95: 43738 | K95: 564453 | L95: =K95-Q95+T95 -> 564453 | M95: INR | N95: 564453 | O95: INR | P95: 0 | Q95: 0 | R95: 564453 | S95: 0 | T95: 0 | U95: 312193 | V95: Tata Steel Limited ( Kalinganagar) | X95: SI1904100037 | Z95: 2316 | AB95: 4700069343/172 | AD95: 110000 | AE95: Customer - Domestic | AF95: 110000 | AG95: Customer - Domestic | AI95: 110000 | AJ95: Customer - Domestic | AK95: 0 | AL95: 4 | AM95: S | AP95: 100173530 | AQ95: 43799 | AR95: 43739 | AS95: 0.48152778 | AT95: 0 | AU95: 0 | AX95: 3
A96: 1000 | B96: Tata BlueScope Steel Ltd | C96: 101952 | D96: CI1904101057 | E96: RV | F96: 1109 | G96: 2019 | H96: 2 | I96: 43607 | J96: 43607 | K96: 2964560.3 | L96: =K96-Q96+T96 -> 2512339.2 | M96: INR | N96: 2964560.3 | O96: INR | P96: 0 | Q96: 452221.06 | R96: 2512339.2 | S96: 0 | T96: 0 | U96: 313029 | V96: Tata Steel Limited | Z96: 58552 | AB96: 2100552074/053 | AD96: 110000 | AE96: Customer - Domestic | AF96: 501005 | AG96: Revenue DS - Domestic Sales | AI96: 501005 | AJ96: Revenue DS - Domestic Sales | AK96: 0 | AL96: 1 | AM96: S | AP96: 100020154 | AQ96: 43611 | AR96: 43607 | AS96: 0.67262731 | AT96: 0 | AU96: 0 | AX96: 1
A97: 1000 | B97: Tata BlueScope Steel Ltd | C97: 100057890 | E97: AB | F97: 1109 | G97: 2019 | H97: 4 | I97: 43677 | J97: 43677 | K97: -1718091.8 | L97: =K97-Q97+T97 -> -1718091.8 | M97: INR | N97: -1718091.8 | O97: INR | P97: 0 | Q97: 0 | R97: -1718091.8 | S97: 0 | T97: 0 | U97: 312193 | V97: Tata Steel Limited ( Kalinganagar) | Z97: 100057890 | AD97: 110000 | AE97: Customer - Domestic | AF97: 110000 | AG97: Customer - Domestic | AI97: 110000 | AJ97: Customer - Domestic | AK97: 0 | AL97: 17 | AM97: H | AP97: 100057890 | AQ97: 43677 | AR97: 43677 | AS97: 0.62208333 | AT97: 0 | AU97: 0 | AX97: 7
A98: 1000 | B98: Tata BlueScope Steel Ltd | C98: 100122444 | E98: AB | F98: 1106 | G98: 2019 | H98: 6 | I98: 43738 | J98: 43738 | K98: 5496781.8 | L98: =K98-Q98+T98 -> 5496781.8 | M98: INR | N98: 5496781.8 | O98: INR | P98: 0 | Q98: 0 | R98: 5496781.8 | S98: 0 | T98: 0 | U98: 305576 | V98: Tata Steel Ltd. | Z98: 100122444 | AD98: 310300 | AE98: Customer - Advance against Sale | AF98: 310300 | AG98: Customer - Advance against Sale | AI98: 310300 | AJ98: Customer - Advance against Sale | AK98: 0 | AL98: 9 | AM98: S | AN98: A | AP98: 100122444 | AQ98: 43738 | AR98: 43739 | AS98: 0.45260417 | AT98: 0 | AU98: 0 | AX98: 3
A99: 1000 | B99: Tata BlueScope Steel Ltd | C99: 104208 | D99: CI1901101069 | E99: RV | F99: 1101 | G99: 2019 | H99: 4 | I99: 43650 | J99: 43650 | K99: 620375.19 | L99: =K99-Q99+T99 -> 525741.71 | M99: INR | N99: 620375.19 | O99: INR | P99: 0 | Q99: 94633.48 | R99: 525741.71 | S99: 0 | T99: 0 | U99: 318999 | V99: Tata Steel Limited | Z99: 104208 | AD99: 110000 | AE99: Customer - Domestic | AF99: 501040 | AG99: Project Revenue - Domestic | AI99: 501040 | AJ99: Project Revenue - Domestic | AK99: 0 | AL99: 1 | AM99: S | AP99: 100057912 | AQ99: 43677 | AR99: 43650 | AS99: 0.56741898 | AT99: 0 | AU99: 0 | AX99: 1
A100: 1000 | B100: Tata BlueScope Steel Ltd | C100: 104164 | D100: CI1901101056 | E100: RV | F100: 1101 | G100: 2019 | H100: 4 | I100: 43648 | J100: 43648 | K100: 350053.68 | L100: =K100-Q100+T100 -> 296655.66 | M100: INR | N100: 350053.68 | O100: INR | P100: 0 | Q100: 53398.02 | R100: 296655.66 | S100: 0 | T100: 0 | U100: 318999 | V100: Tata Steel Limited | Z100: 104164 | AD100: 110000 | AE100: Customer - Domestic | AF100: 501040 | AG100: Project Revenue - Domestic | AI100: 501040 | AJ100: Project Revenue - Domestic | AK100: 0 | AL100: 1 | AM100: S | AP100: 100057912 | AQ100: 43677 | AR100: 43648 | AS100: 0.77150463 | AT100: 0 | AU100: 0 | AX100: 1
...

Sheet Last year Items
A1: Company_Code | B1: Company_Name | C1: SAP_Doc_Number | D1: Match ID | E1: Reference | F1: SAP_Doc_Number | G1: Document_Type | H1: Doc/Chq_Date | I1: Posting_Date | J1: Amount_in_Local_Currency | K1: SOA | L1: GST_Amount | M1: Net_Amount | N1: Withholding_Tax_Base_Amount | O1: Withholding_Tax_Amount | P1: Vendor/Customer | Q1: Vendor/Customer_Name | R1: Trading_Partner | S1: Text | T1: HDR_Text | U1: Inv/SO_Reference | V1: Plant | W1: Purchasing_Document | X1: Delivery_Note | Y1: Account | Z1: Account_Description | AA1: Offsetting_Account | AB1: Offsetting_Acct_Name | AC1: GRIR_Offsetting_Account | AD1: Final_Offsetting_Account | AE1: Final_Offsetting_Acct_Name | AF1: WBS_Element | AG1: Posting_Key | AH1: Debit/Credit | AI1: Special_G/L_Ind. | AJ1: Reversal_Indicator | AK1: Clearing_Doc | AL1: Clearing_Date | AM1: Entry_date | AN1: Entry_Time | AO1: Notional_GST | AP1: Gross_Amount_In_Local_Currency | AQ1: DE_Indicator | AR1: PO_Line | AS1: Entry_Line
A2: 1000 | B2: Tata Steel Limited | C2: 51007775 | D2: 836595 | E2: CI0004108029 | F2: 51007775 | G2: RE | H2: 43529 | I2: 43558 | J2: -110831.38 | K2: -93924.9 | L2: -16906.48 | M2: -93924.9 | N2: 0 | O2: 0 | P2: T018 | Q2: TATA BLUESCOPE STEEL PRIVATE LIMIT | T2: 2300047310 | U2: 51007775 | W2: 2300047310 | Y2: 2408402 | Z2: Vendor Reconciliation Account - Domestic | AA2: 2408424 | AB2: GR/IR Account - Capital (Project System) | AC2: 5149121 | AD2: 5149121 | AE2: Purchase of Capital goods-Project System | AF2: 0 | AG2: 31 | AH2: H | AK2: 45018260 | AL2: 16-04-2019 | AM2: 03-04-2019 | AN2: 17:10:51 | AO2: 0 | AP2: -110831.38 | AS2: 1
A3: 1000 | B3: Tata Steel Limited | C3: 51015501 | D3: 836600 | E3: CI0004107732 | F3: 51015501 | G3: RE | H3: 43519 | I3: 43563 | J3: -3510796.2 | K3: -2975250.9 | L3: -535545.29 | M3: -2975250.9 | N3: 0 | O3: 0 | P3: T018 | Q3: TATA BLUESCOPE STEEL PRIVATE LIMIT | S3: Bill Receipt Date :22.03.2019 | T3: 3700786376 | U3: 51015501 | W3: 3700786376 | Y3: 2408402 | Z3: Vendor Reconciliation Account - Domestic | AA3: 2408409 | AB3: Gr/Ir For Stores And Spares | AC3: 6005101 | AD3: 6005101 | AE3: Purchase of Stores | AF3: 0 | AG3: 31 | AH3: H | AK3: 45012359 | AL3: 11-04-2019 | AM3: 08-04-2019 | AN3: 10:39:26 | AO3: 0 | AP3: -3510796.2 | AS3: 1
A4: 1000 | B4: Tata Steel Limited | C4: 51017855 | D4: 836621 | E4: OM/ARC/14 | F4: 51017855 | G4: RE | H4: 43551 | I4: 43564 | J4: -425053.85 | K4: -366426.01 | L4: -65956.68 | M4: -359097.17 | N4: -366426.01 | O4: -7328.84 | P4: T018 | Q4: TATA BLUESCOPE STEEL PRIVATE LIMIT | S4: SUPPLY AND FIXING OF SHEET | T4: 4404339865 | U4: 51017855 | W4: 4404339865 | Y4: 2408402 | Z4: Vendor Reconciliation Account - Domestic | AA4: 2408422 | AB4: GR/IR Account - Services & Capital | AC4: 5149027 | AD4: 5149027 | AE4: Civil Contract Jobs | AF4: 0 | AG4: 31 | AH4: H | AK4: 45036233 | AL4: 07-05-2019 | AM4: 09-04-2019 | AN4: 09:31:44 | AO4: 0 | AP4: -425053.85 | AS4: 2
A5: 1000 | B5: Tata Steel Limited | C5: 51017855 | D5: 836621 | E5: OM/ARC/14 | F5: 51017855 | G5: RE | H5: 43551 | I5: 43564 | J5: -215527.83 | K5: -185799.99 | L5: -33444 | M5: -182083.83 | N5: -185799.99 | O5: -3716.16 | P5: T018 | Q5: TATA BLUESCOPE STEEL PRIVATE LIMIT | S5: SUPPLY AND FIXING OF SHEET | T5: 4404339865 | U5: 51017855 | W5: 4404339865 | Y5: 2408402 | Z5: Vendor Reconciliation Account - Domestic | AA5: 2408422 | AB5: GR/IR Account - Services & Capital | AC5: 5149027 | AD5: 5149027 | AE5: Civil Contract Jobs | AF5: 0 | AG5: 31 | AH5: H | AK5: 45036233 | AL5: 07-05-2019 | AM5: 09-04-2019 | AN5: 09:31:44 | AO5: 0 | AP5: -215527.83 | AS5: 1
A6: 1000 | B6: Tata Steel Limited | C6: 51017865 | D6: 836621 | E6: OM/ARC/15 | F6: 51017865 | G6: RE | H6: 43551 | I6: 43564 | J6: -208614.2 | K6: -179840 | L6: -32371.2 | M6: -176243 | N6: -179840 | O6: -3597 | P6: T018 | Q6: TATA BLUESCOPE STEEL PRIVATE LIMIT | S6: SUPPLY AND FIXING OF SHEET | T6: 4404338210 | U6: 51017865 | W6: 4404338210 | Y6: 2408402 | Z6: Vendor Reconciliation Account - Domestic | AA6: 2408422 | AB6: GR/IR Account - Services & Capital | AC6: 5149027 | AD6: 5149027 | AE6: Civil Contract Jobs | AF6: 0 | AG6: 31 | AH6: H | AK6: 45036233 | AL6: 07-05-2019 | AM6: 09-04-2019 | AN6: 09:35:09 | AO6: 0 | AP6: -208614.2 | AS6: 1
A7: 1000 | B7: Tata Steel Limited | C7: 51017868 | D7: 836621 | E7: OM/ARC/16 | F7: 51017868 | G7: RE | H7: 43551 | I7: 43564 | J7: -106070.26 | K7: -91440 | L7: -16459.2 | M7: -89611.06 | N7: -91440 | O7: -1828.94 | P7: T018 | Q7: TATA BLUESCOPE STEEL PRIVATE LIMIT | S7: SUPPLY AND FIXING OF SHEET | T7: 4404338208 | U7: 51017868 | W7: 4404338208 | Y7: 2408402 | Z7: Vendor Reconciliation Account - Domestic | AA7: 2408422 | AB7: GR/IR Account - Services & Capital | AC7: 5149027 | AD7: 5149027 | AE7: Civil Contract Jobs | AF7: 0 | AG7: 31 | AH7: H | AK7: 45036233 | AL7: 07-05-2019 | AM7: 09-04-2019 | AN7: 09:37:32 | AO7: 0 | AP7: -106070.26 | AS7: 3
A8: 1000 | B8: Tata Steel Limited | C8: 51017868 | D8: 836621 | E8: OM/ARC/16 | F8: 51017868 | G8: RE | H8: 43551 | I8: 43564 | J8: -129212.23 | K8: -111390 | L8: -20050.2 | M8: -109162.03 | N8: -111390 | O8: -2227.97 | P8: T018 | Q8: TATA BLUESCOPE STEEL PRIVATE LIMIT | S8: SUPPLY AND FIXING OF SHEET | T8: 4404338208 | U8: 51017868 | W8: 4404338208 | Y8: 2408402 | Z8: Vendor Reconciliation Account - Domestic | AA8: 2408422 | AB8: GR/IR Account - Services & Capital | AC8: 5149027 | AD8: 5149027 | AE8: Civil Contract Jobs | AF8: 0 | AG8: 31 | AH8: H | AK8: 45036233 | AL8: 07-05-2019 | AM8: 09-04-2019 | AN8: 09:37:32 | AO8: 0 | AP8: -129212.23 | AS8: 2
A9: 1000 | B9: Tata Steel Limited | C9: 51017868 | D9: 836621 | E9: OM/ARC/16 | F9: 51017868 | G9: RE | H9: 43551 | I9: 43564 | J9: -68903.91 | K9: -59400 | L9: -10692 | M9: -58211.91 | N9: -59400 | O9: -1188.09 | P9: T018 | Q9: TATA BLUESCOPE STEEL PRIVATE LIMIT | S9: SUPPLY AND FIXING OF SHEET | T9: 4404338208 | U9: 51017868 | W9: 4404338208 | Y9: 2408402 | Z9: Vendor Reconciliation Account - Domestic | AA9: 2408422 | AB9: GR/IR Account - Services & Capital | AC9: 5149027 | AD9: 5149027 | AE9: Civil Contract Jobs | AF9: 0 | AG9: 31 | AH9: H | AK9: 45036233 | AL9: 07-05-2019 | AM9: 09-04-2019 | AN9: 09:37:32 | AO9: 0 | AP9: -68903.91 | AS9: 1
A10: 1000 | B10: Tata Steel Limited | C10: 51017875 | D10: 836621 | E10: OM/ARC/17 | F10: 51017875 | G10: RE | H10: 43551 | I10: 43564 | J10: -414990 | K10: -357750 | L10: -64395 | M10: -350595 | N10: -357750 | O10: -7155 | P10: T018 | Q10: TATA BLUESCOPE STEEL PRIVATE LIMIT | S10: SUPPLY AND FIXING OF SHEET | T10: 4404338209 | U10: 51017875 | W10: 4404338209 | Y10: 2408402 | Z10: Vendor Reconciliation Account - Domestic | AA10: 2408422 | AB10: GR/IR Account - Services & Capital | AC10: 5149027 | AD10: 5149027 | AE10: Civil Contract Jobs | AF10: 0 | AG10: 31 | AH10: H | AK10: 45036233 | AL10: 07-05-2019 | AM10: 09-04-2019 | AN10: 09:40:06 | AO10: 0 | AP10: -414990 | AS10: 1
A11: 1000 | B11: Tata Steel Limited | C11: 51019236 | D11: 836603 | E11: CI0004108179 | F11: 51019236 | G11: RE | H11: 43537 | I11: 43564 | J11: -1844550.3 | K11: -1563178.4 | L11: -281371.99 | M11: -1563178.4 | N11: 0 | O11: 0 | P11: T018 | Q11: TATA BLUESCOPE STEEL PRIVATE LIMIT | S11: Bill Receipt Date :22.03.2019 | T11: 4404040292 | U11: 51019236 | W11: 4404040292 | Y11: 2408402 | Z11: Vendor Reconciliation Account - Domestic | AA11: 2408409 | AB11: Gr/Ir For Stores And Spares | AC11: 6005101 | AD11: 6005101 | AE11: Purchase of Stores | AF11: 0 | AG11: 31 | AH11: H | AK11: 45019034 | AL11: 16-04-2019 | AM11: 09-04-2019 | AN11: 15:39:51 | AO11: 0 | AP11: -1844550.3 | AS11: 1
A12: 1000 | B12: Tata Steel Limited | C12: 51019944 | D12: 836580 | E12: CI0004107087 | F12: 51019944 | G12: RE | H12: 43492 | I12: 43565 | J12: -309.75 | K12: -262.5 | L12: -47.25 | M12: -262.5 | N12: 0 | O12: 0 | P12: T040 | Q12: TATA BLUESCOPE STEEL PRIVATE LIMIT | T12: 2300049475 | U12: 51019944 | W12: 2300049475 | Y12: 2408402 | Z12: Vendor Reconciliation Account - Domestic | AA12: 2408424 | AB12: GR/IR Account - Capital (Project System) | AC12: 5149121 | AD12: 5149121 | AE12: Purchase of Capital goods-Project System | AF12: 0 | AG12: 31 | AH12: H | AK12: 45020062 | AL12: 17-04-2019 | AM12: 10-04-2019 | AN12: 09:20:14 | AO12: 0 | AP12: -309.75 | AS12: 1
A13: 1000 | B13: Tata Steel Limited | C13: 51019945 | D13: 836581 | E13: CI0004107088 | F13: 51019945 | G13: RE | H13: 43492 | I13: 43565 | J13: -10752.75 | K13: -9112.5 | L13: -1640.25 | M13: -9112.5 | N13: 0 | O13: 0 | P13: T040 | Q13: TATA BLUESCOPE STEEL PRIVATE LIMIT | T13: 2300049475 | U13: 51019945 | W13: 2300049475 | Y13: 2408402 | Z13: Vendor Reconciliation Account - Domestic | AA13: 2408424 | AB13: GR/IR Account - Capital (Project System) | AC13: 5149121 | AD13: 5149121 | AE13: Purchase of Capital goods-Project System | AF13: 0 | AG13: 31 | AH13: H | AK13: 45020062 | AL13: 17-04-2019 | AM13: 10-04-2019 | AN13: 09:20:19 | AO13: 0 | AP13: -10752.75 | AS13: 1
A14: 1000 | B14: Tata Steel Limited | C14: 51019946 | D14: 836598 | E14: CI0004107101 | F14: 51019946 | G14: RE | H14: 43492 | I14: 43565 | J14: -1618.96 | K14: -1372 | L14: -246.96 | M14: -1372 | N14: 0 | O14: 0 | P14: T040 | Q14: TATA BLUESCOPE STEEL PRIVATE LIMIT | T14: 2300049475 | U14: 51019946 | W14: 2300049475 | Y14: 2408402 | Z14: Vendor Reconciliation Account - Domestic | AA14: 2408424 | AB14: GR/IR Account - Capital (Project System) | AC14: 5149121 | AD14: 5149121 | AE14: Purchase of Capital goods-Project System | AF14: 0 | AG14: 31 | AH14: H | AK14: 45020062 | AL14: 17-04-2019 | AM14: 10-04-2019 | AN14: 09:20:23 | AO14: 0 | AP14: -1618.96 | AS14: 1
A15: 1000 | B15: Tata Steel Limited | C15: 51019947 | D15: 836596 | E15: CI0004107102 | F15: 51019947 | G15: RE | H15: 43492 | I15: 43565 | J15: -5286.4 | K15: -4480 | L15: -806.4 | M15: -4480 | N15: 0 | O15: 0 | P15: T040 | Q15: TATA BLUESCOPE STEEL PRIVATE LIMIT | T15: 2300049475 | U15: 51019947 | W15: 2300049475 | Y15: 2408402 | Z15: Vendor Reconciliation Account - Domestic | AA15: 2408424 | AB15: GR/IR Account - Capital (Project System) | AC15: 5149121 | AD15: 5149121 | AE15: Purchase of Capital goods-Project System | AF15: 0 | AG15: 31 | AH15: H | AK15: 45020062 | AL15: 17-04-2019 | AM15: 10-04-2019 | AN15: 09:20:28 | AO15: 0 | AP15: -5286.4 | AS15: 1
A16: 1000 | B16: Tata Steel Limited | C16: 51035916 | D16: 836621 | E16: OM/CLEAN/06 | F16: 51035916 | G16: RE | H16: 43551 | I16: 43572 | J16: -165299.87 | K16: -142500 | L16: -25650 | M16: -139649.87 | N16: -142500 | O16: -2850.13 | P16: T018 | Q16: TATA BLUESCOPE STEEL PRIVATE LIMIT | S16: CLEANING OF ROOF | T16: 4404338294 | U16: 51035916 | W16: 4404338294 | Y16: 2408402 | Z16: Vendor Reconciliation Account - Domestic | AA16: 2408422 | AB16: GR/IR Account - Services & Capital | AC16: 5020001 | AD16: 5020001 | AE16: REPAIRS TO BUILDINGS. | AF16: 0 | AG16: 31 | AH16: H | AK16: 45041132 | AL16: 13-05-2019 | AM16: 17-04-2019 | AN16: 13:31:42 | AO16: 0 | AP16: -165299.87 | AS16: 2
A17: 1000 | B17: Tata Steel Limited | C17: 51035916 | D17: 836621 | E17: OM/CLEAN/06 | F17: 51035916 | G17: RE | H17: 43551 | I17: 43572 | J17: -214989.02 | K17: -185335.5 | L17: -33360.39 | M17: -181628.63 | N17: -185335.5 | O17: -3706.87 | P17: T018 | Q17: TATA BLUESCOPE STEEL PRIVATE LIMIT | S17: CLEANING OF ROOF | T17: 4404338294 | U17: 51035916 | W17: 4404338294 | Y17: 2408402 | Z17: Vendor Reconciliation Account - Domestic | AA17: 2408422 | AB17: GR/IR Account - Services & Capital | AC17: 5020001 | AD17: 5020001 | AE17: REPAIRS TO BUILDINGS. | AF17: 0 | AG17: 31 | AH17: H | AK17: 45041132 | AL17: 13-05-2019 | AM17: 17-04-2019 | AN17: 13:31:42 | AO17: 0 | AP17: -214989.02 | AS17: 1
A18: 1000 | B18: Tata Steel Limited | C18: 51038398 | D18: 836561 | E18: CI0001102734 | F18: 51038398 | G18: RE | H18: 43543 | I18: 43573 | J18: -1164518 | K18: -986879.6 | L18: -177638.4 | M18: -986879.6 | N18: 0 | O18: 0 | P18: T018 | Q18: TATA BLUESCOPE STEEL PRIVATE LIMIT | S18: CONSTRN SHEET;0.50 MM,1072 MM,2.50 RMT, | T18: 2100554502 | U18: 51038398 | W18: 2100554502 | Y18: 2408402 | Z18: Vendor Reconciliation Account - Domestic | AA18: 2408409 | AB18: Gr/Ir For Stores And Spares | AC18: 5000007 | AD18: 5000007 | AE18: Consumption of Stores | AF18: 0 | AG18: 31 | AH18: H | AK18: 45024071 | AL18: 22-04-2019 | AM18: 18-04-2019 | AN18: 15:59:16 | AO18: 0 | AP18: -1164518 | AS18: 1
A19: 1000 | B19: Tata Steel Limited | C19: 51038775 | D19: 836557 | E19: CI0001102733 | F19: 51038775 | G19: RE | H19: 43543 | I19: 43573 | J19: -974532 | K19: -825874.5 | L19: -148657.5 | M19: -825874.5 | N19: 0 | O19: 0 | P19: T018 | Q19: TATA BLUESCOPE STEEL PRIVATE LIMIT | S19: CONSTRN SHEET;0.50 MM,1072 MM,5.75 RMT, | T19: 2100553171 | U19: 51038775 | W19: 2100553171 | Y19: 2408402 | Z19: Vendor Reconciliation Account - Domestic | AA19: 2408409 | AB19: Gr/Ir For Stores And Spares | AC19: 5000007 | AD19: 5000007 | AE19: Consumption of Stores | AF19: 0 | AG19: 31 | AH19: H | AK19: 45024071 | AL19: 22-04-2019 | AM19: 18-04-2019 | AN19: 17:21:59 | AO19: 0 | AP19: -974532 | AS19: 1
A20: 1000 | B20: Tata Steel Limited | C20: 51043071 | D20: 836582 | E20: CI0004107085 | F20: 51043071 | G20: RE | H20: 43492 | I20: 43577 | J20: -832.49 | K20: -705.5 | L20: -126.99 | M20: -705.5 | N20: 0 | O20: 0 | P20: T040 | Q20: TATA BLUESCOPE STEEL PRIVATE LIMIT | S20: Mail from Abhinandan Ojha on dtd 24.04.2019 | T20: 2300049475 | U20: 51043071 | W20: 2300049475 | Y20: 2408402 | Z20: Vendor Reconciliation Account - Domestic | AA20: 2408424 | AB20: GR/IR Account - Capital (Project System) | AC20: 5149121 | AD20: 5149121 | AE20: Purchase of Capital goods-Project System | AF20: 0 | AG20: 31 | AH20: H | AK20: 45082766 | AL20: 04-07-2019 | AM20: 22-04-2019 | AN20: 10:20:38 | AO20: 0 | AP20: -832.49 | AS20: 1
A21: 1000 | B21: Tata Steel Limited | C21: 51043072 | D21: 836576 | E21: CI0004107086 | F21: 51043072 | G21: RE | H21: 43492 | I21: 43577 | J21: -27251.51 | K21: -23094.5 | L21: -4157.01 | M21: -23094.5 | N21: 0 | O21: 0 | P21: T040 | Q21: TATA BLUESCOPE STEEL PRIVATE LIMIT | S21: Mail from Abhinandan Ojha on dtd 24.04.2019 | T21: 2300049475 | U21: 51043072 | W21: 2300049475 | Y21: 2408402 | Z21: Vendor Reconciliation Account - Domestic | AA21: 2408424 | AB21: GR/IR Account - Capital (Project System) | AC21: 5149121 | AD21: 5149121 | AE21: Purchase of Capital goods-Project System | AF21: 0 | AG21: 31 | AH21: H | AK21: 45082766 | AL21: 04-07-2019 | AM21: 22-04-2019 | AN21: 10:20:43 | AO21: 0 | AP21: -27251.51 | AS21: 1
A22: 1000 | B22: Tata Steel Limited | C22: 51043074 | D22: 836590 | E22: CI0004107099 | F22: 51043074 | G22: RE | H22: 43492 | I22: 43577 | J22: -4956 | K22: -4200 | L22: -756 | M22: -4200 | N22: 0 | O22: 0 | P22: T040 | Q22: TATA BLUESCOPE STEEL PRIVATE LIMIT | S22: Mail from Abhinandan Ojha on dtd 24.04.2019 | T22: 2300049475 | U22: 51043074 | W22: 2300049475 | Y22: 2408402 | Z22: Vendor Reconciliation Account - Domestic | AA22: 2408424 | AB22: GR/IR Account - Capital (Project System) | AC22: 5149121 | AD22: 5149121 | AE22: Purchase of Capital goods-Project System | AF22: 0 | AG22: 31 | AH22: H | AK22: 45082766 | AL22: 04-07-2019 | AM22: 22-04-2019 | AN22: 10:20:47 | AO22: 0 | AP22: -4956 | AS22: 1
A23: 1000 | B23: Tata Steel Limited | C23: 51043076 | D23: 836593 | E23: CI0004107100 | F23: 51043076 | G23: RE | H23: 43492 | I23: 43577 | J23: -8673 | K23: -7350 | L23: -1323 | M23: -7350 | N23: 0 | O23: 0 | P23: T040 | Q23: TATA BLUESCOPE STEEL PRIVATE LIMIT | S23: Mail from Abhinandan Ojha on dtd 24.04.2019 | T23: 2300049475 | U23: 51043076 | W23: 2300049475 | Y23: 2408402 | Z23: Vendor Reconciliation Account - Domestic | AA23: 2408424 | AB23: GR/IR Account - Capital (Project System) | AC23: 5149121 | AD23: 5149121 | AE23: Purchase of Capital goods-Project System | AF23: 0 | AG23: 31 | AH23: H | AK23: 45082766 | AL23: 04-07-2019 | AM23: 22-04-2019 | AN23: 10:20:53 | AO23: 0 | AP23: -8673 | AS23: 1
A24: 1000 | B24: Tata Steel Limited | C24: 51047406 | D24: 836572 | E24: CI0004107078 | F24: 51047406 | G24: RE | H24: 43492 | I24: 43578 | J24: -21655.36 | K24: -18352 | L24: -3303.36 | M24: -18352 | N24: 0 | O24: 0 | P24: T040 | Q24: TATA BLUESCOPE STEEL PRIVATE LIMIT | S24: Mail from Abhinandan Ojha on dtd 24.04.2019 | T24: 2300049475 | U24: 51047406 | W24: 2300049475 | Y24: 2408402 | Z24: Vendor Reconciliation Account - Domestic | AA24: 2408424 | AB24: GR/IR Account - Capital (Project System) | AC24: 5149121 | AD24: 5149121 | AE24: Purchase of Capital goods-Project System | AF24: 0 | AG24: 31 | AH24: H | AK24: 45070150 | AL24: 19-06-2019 | AM24: 23-04-2019 | AN24: 17:58:59 | AO24: 0 | AP24: -21655.36 | AS24: 1
A25: 1000 | B25: Tata Steel Limited | C25: 51047407 | D25: 836574 | E25: CI0004107079 | F25: 51047407 | G25: RE | H25: 43492 | I25: 43578 | J25: -21655.36 | K25: -18352 | L25: -3303.36 | M25: -18352 | N25: 0 | O25: 0 | P25: T040 | Q25: TATA BLUESCOPE STEEL PRIVATE LIMIT | S25: Mail from Abhinandan Ojha on dtd 24.04.2019 | T25: 2300049475 | U25: 51047407 | W25: 2300049475 | Y25: 2408402 | Z25: Vendor Reconciliation Account - Domestic | AA25: 2408424 | AB25: GR/IR Account - Capital (Project System) | AC25: 5149121 | AD25: 5149121 | AE25: Purchase of Capital goods-Project System | AF25: 0 | AG25: 31 | AH25: H | AK25: 45070150 | AL25: 19-06-2019 | AM25: 23-04-2019 | AN25: 17:59:04 | AO25: 0 | AP25: -21655.36 | AS25: 1
A26: 1000 | B26: Tata Steel Limited | C26: 51047408 | D26: 836575 | E26: CI0004107080 | F26: 51047408 | G26: RE | H26: 43492 | I26: 43578 | J26: -7858.8 | K26: -6660 | L26: -1198.8 | M26: -6660 | N26: 0 | O26: 0 | P26: T040 | Q26: TATA BLUESCOPE STEEL PRIVATE LIMIT | S26: Mail from Abhinandan Ojha on dtd 24.04.2019 | T26: 2300049475 | U26: 51047408 | W26: 2300049475 | Y26: 2408402 | Z26: Vendor Reconciliation Account - Domestic | AA26: 2408424 | AB26: GR/IR Account - Capital (Project System) | AC26: 5149121 | AD26: 5149121 | AE26: Purchase of Capital goods-Project System | AF26: 0 | AG26: 31 | AH26: H | AK26: 45070150 | AL26: 19-06-2019 | AM26: 23-04-2019 | AN26: 17:59:08 | AO26: 0 | AP26: -7858.8 | AS26: 1
A27: 1000 | B27: Tata Steel Limited | C27: 51047409 | D27: 836591 | E27: CI0004107081 | F27: 51047409 | G27: RE | H27: 43492 | I27: 43578 | J27: -2124 | K27: -1800 | L27: -324 | M27: -1800 | N27: 0 | O27: 0 | P27: T040 | Q27: TATA BLUESCOPE STEEL PRIVATE LIMIT | S27: Mail from Abhinandan Ojha on dtd 24.04.2019 | T27: 2300049475 | U27: 51047409 | W27: 2300049475 | Y27: 2408402 | Z27: Vendor Reconciliation Account - Domestic | AA27: 2408424 | AB27: GR/IR Account - Capital (Project System) | AC27: 5149121 | AD27: 5149121 | AE27: Purchase of Capital goods-Project System | AF27: 0 | AG27: 31 | AH27: H | AK27: 45070150 | AL27: 19-06-2019 | AM27: 23-04-2019 | AN27: 17:59:13 | AO27: 0 | AP27: -2124 | AS27: 1
... A36: 1000 | B36: Tata Steel Limited | C36: 51760823 | D36: 0 | E36: 2 | F36: 51760823 | G36: RE | H36: 40382 | I36: 43908 | J36: -7802.46 | K36: -7802.46 | L36: 0 | M36: -7802.46 | N36: 0 | O36: 0 | P36: T018 | Q36: TATA BLUESCOPE STEEL PRIVATE LIMIT | S36: GRIR CLEARING >3 YRS | T36: GRIR Clearing > 3 yr | U36: 51760823 | W36: 2100204812 | Y36: 2408402 | Z36: Vendor Reconciliation Account - Domestic | AA36: 2408413 | AB36: Freight Clearing For Stores | AC36: 6005102 | AD36: 6005102 | AE36: Freight - Purchase of Stores | AF36: 0 | AG36: 31 | AH36: H | AK36: 93385931 | AL36: 28-03-2020 | AM36: 18-03-2020 | AN36: 11:47:29 | AO36: 0 | AP36: -7802.46 | AS36: 1
A37: 1000 | B37: Tata Steel Limited | C37: 51786309 | D37: 0 | E37: 1C DT.130910 | F37: 51786309 | G37: RE | H37: 40448 | I37: 43921 | J37: -12970.19 | K37: -12970.19 | L37: 0 | M37: -12970.19 | N37: 0 | O37: 0 | P37: T018 | Q37: TATA BLUESCOPE STEEL PRIVATE LIMIT | S37: GRIR Clearing > 3 years | T37: GRIR Clearing > 3 Years | U37: 51786309 | W37: 3700479949 | Y37: 2408402 | Z37: Vendor Reconciliation Account - Domestic | AA37: 2408413 | AB37: Freight Clearing For Stores | AC37: 6005102 | AD37: 6005102 | AE37: Freight - Purchase of Stores | AF37: 0 | AG37: 31 | AH37: H | AM37: 01-04-2020 | AN37: 17:32:54 | AO37: 0 | AP37: -12970.19 | AS37: 1
A38: 1000 | B38: Tata Steel Limited | C38: 51062273 | D38: 836568 | E38: CI0004107075 | F38: 51062273 | G38: RE | H38: 43492 | I38: 43585 | J38: -43091.71 | K38: -36518.4 | L38: -6573.31 | M38: -36518.4 | N38: 0 | O38: 0 | P38: T040 | Q38: TATA BLUESCOPE STEEL PRIVATE LIMIT | T38: 2300049475 | U38: 51062273 | W38: 2300049475 | Y38: 2408402 | Z38: Vendor Reconciliation Account - Domestic | AA38: 2408424 | AB38: GR/IR Account - Capital (Project System) | AC38: 5149121 | AD38: 5149121 | AE38: Purchase of Capital goods-Project System | AF38: 0 | AG38: 31 | AH38: H | AK38: 45039858 | AL38: 10-05-2019 | AM38: 30-04-2019 | AN38: 10:42:08 | AO38: 0 | AP38: -43091.71 | AS38: 1
A39: 1000 | B39: Tata Steel Limited | C39: 51062274 | D39: 836577 | E39: CI0004107076 | F39: 51062274 | G39: RE | H39: 43492 | I39: 43585 | J39: -121118.98 | K39: -102643.2 | L39: -18475.78 | M39: -102643.2 | N39: 0 | O39: 0 | P39: T040 | Q39: TATA BLUESCOPE STEEL PRIVATE LIMIT | T39: 2300049475 | U39: 51062274 | W39: 2300049475 | Y39: 2408402 | Z39: Vendor Reconciliation Account - Domestic | AA39: 2408424 | AB39: GR/IR Account - Capital (Project System) | AC39: 5149121 | AD39: 5149121 | AE39: Purchase of Capital goods-Project System | AF39: 0 | AG39: 31 | AH39: H | AK39: 45046601 | AL39: 20-05-2019 | AM39: 30-04-2019 | AN39: 10:42:13 | AO39: 0 | AP39: -121118.98 | AS39: 1
A40: 1000 | B40: Tata Steel Limited | C40: 51062276 | D40: 836569 | E40: CI0004107077 | F40: 51062276 | G40: RE | H40: 43492 | I40: 43585 | J40: -13345.8 | K40: -11310 | L40: -2035.8 | M40: -11310 | N40: 0 | O40: 0 | P40: T040 | Q40: TATA BLUESCOPE STEEL PRIVATE LIMIT | T40: 2300049475 | U40: 51062276 | W40: 2300049475 | Y40: 2408402 | Z40: Vendor Reconciliation Account - Domestic | AA40: 2408424 | AB40: GR/IR Account - Capital (Project System) | AC40: 5149121 | AD40: 5149121 | AE40: Purchase of Capital goods-Project System | AF40: 0 | AG40: 31 | AH40: H | AK40: 45039858 | AL40: 10-05-2019 | AM40: 30-04-2019 | AN40: 10:42:17 | AO40: 0 | AP40: -13345.8 | AS40: 1
A41: 1000 | B41: Tata Steel Limited | C41: 51062277 | D41: 836583 | E41: CI0004107089 | F41: 51062277 | G41: RE | H41: 43492 | I41: 43585 | J41: -2950 | K41: -2500 | L41: -450 | M41: -2500 | N41: 0 | O41: 0 | P41: T040 | Q41: TATA BLUESCOPE STEEL PRIVATE LIMIT | T41: 2300049475 | U41: 51062277 | W41: 2300049475 | Y41: 2408402 | Z41: Vendor Reconciliation Account - Domestic | AA41: 2408424 | AB41: GR/IR Account - Capital (Project System) | AC41: 5149121 | AD41: 5149121 | AE41: Purchase of Capital goods-Project System | AF41: 0 | AG41: 31 | AH41: H | AK41: 45039858 | AL41: 10-05-2019 | AM41: 30-04-2019 | AN41: 10:42:22 | AO41: 0 | AP41: -2950 | AS41: 1
A42: 1000 | B42: Tata Steel Limited | C42: 51062278 | D42: 836578 | E42: CI0004107090 | F42: 51062278 | G42: RE | H42: 43492 | I42: 43585 | J42: -4425 | K42: -3750 | L42: -675 | M42: -3750 | N42: 0 | O42: 0 | P42: T040 | Q42: TATA BLUESCOPE STEEL PRIVATE LIMIT | T42: 2300049475 | U42: 51062278 | W42: 2300049475 | Y42: 2408402 | Z42: Vendor Reconciliation Account - Domestic | AA42: 2408424 | AB42: GR/IR Account - Capital (Project System) | AC42: 5149121 | AD42: 5149121 | AE42: Purchase of Capital goods-Project System | AF42: 0 | AG42: 31 | AH42: H | AK42: 45039858 | AL42: 10-05-2019 | AM42: 30-04-2019 | AN42: 10:42:27 | AO42: 0 | AP42: -4425 | AS42: 1
A43: 1000 | B43: Tata Steel Limited | C43: 51062279 | D43: 836585 | E43: CI0004107097 | F43: 51062279 | G43: RE | H43: 43492 | I43: 43585 | J43: -3186 | K43: -2700 | L43: -486 | M43: -2700 | N43: 0 | O43: 0 | P43: T040 | Q43: TATA BLUESCOPE STEEL PRIVATE LIMIT | T43: 2300049475 | U43: 51062279 | W43: 2300049475 | Y43: 2408402 | Z43: Vendor Reconciliation Account - Domestic | AA43: 2408424 | AB43: GR/IR Account - Capital (Project System) | AC43: 5149121 | AD43: 5149121 | AE43: Purchase of Capital goods-Project System | AF43: 0 | AG43: 31 | AH43: H | AK43: 45039858 | AL43: 10-05-2019 | AM43: 30-04-2019 | AN43: 10:42:32 | AO43: 0 | AP43: -3186 | AS43: 1
A44: 1000 | B44: Tata Steel Limited | C44: 51062280 | D44: 836588 | E44: CI0004107098 | F44: 51062280 | G44: RE | H44: 43492 | I44: 43585 | J44: -660.8 | K44: -560 | L44: -100.8 | M44: -560 | N44: 0 | O44: 0 | P44: T040 | Q44: TATA BLUESCOPE STEEL PRIVATE LIMIT | T44: 2300049475 | U44: 51062280 | W44: 2300049475 | Y44: 2408402 | Z44: Vendor Reconciliation Account - Domestic | AA44: 2408424 | AB44: GR/IR Account - Capital (Project System) | AC44: 5149121 | AD44: 5149121 | AE44: Purchase of Capital goods-Project System | AF44: 0 | AG44: 31 | AH44: H | AK44: 45039858 | AL44: 10-05-2019 | AM44: 30-04-2019 | AN44: 10:42:36 | AO44: 0 | AP44: -660.8 | AS44: 1
A45: 1000 | B45: Tata Steel Limited | C45: 51786311 | D45: 0 | E45: 1B DT.130910 | F45: 51786311 | G45: RE | H45: 40448 | I45: 43921 | J45: -9016.07 | K45: -9016.07 | L45: 0 | M45: -9016.07 | N45: 0 | O45: 0 | P45: T018 | Q45: TATA BLUESCOPE STEEL PRIVATE LIMIT | S45: GRIR Clearing > 3 years | T45: GRIR Clearing > 3 Years | U45: 51786311 | W45: 3700479961 | Y45: 2408402 | Z45: Vendor Reconciliation Account - Domestic | AA45: 2408413 | AB45: Freight Clearing For Stores | AC45: 6005102 | AD45: 6005102 | AE45: Freight - Purchase of Stores | AF45: 0 | AG45: 31 | AH45: H | AM45: 01-04-2020 | AN45: 17:39:25 | AO45: 0 | AP45: -9016.07 | AS45: 1
A46: 1000 | B46: Tata Steel Limited | C46: 51786380 | D46: 0 | E46: 1A DT.130910 | F46: 51786380 | G46: RE | H46: 40448 | I46: 43921 | J46: -33456.06 | K46: -33456.06 | L46: 0 | M46: -33456.06 | N46: 0 | O46: 0 | P46: T018 | Q46: TATA BLUESCOPE STEEL PRIVATE LIMIT | S46: GRIR Clearing > 3 years | T46: GRIR Clearing > 3 Years | U46: 51786380 | W46: 3700479963 | Y46: 2408402 | Z46: Vendor Reconciliation Account - Domestic | AA46: 2408413 | AB46: Freight Clearing For Stores | AC46: 6005102 | AD46: 6005102 | AE46: Freight - Purchase of Stores | AF46: 0 | AG46: 31 | AH46: H | AM46: 02-04-2020 | AN46: 09:37:47 | AO46: 0 | AP46: -33456.06 | AS46: 1
A47: 1000 | B47: Tata Steel Limited | C47: 51093980 | D47: 836564 | E47: CI0004105707 | F47: 51093980 | G47: RE | H47: 43433 | I47: 43600 | J47: -619500 | K47: -525000 | L47: -94500 | M47: -619500 | N47: 0 | O47: 0 | P47: T018 | Q47: TATA BLUESCOPE STEEL PRIVATE LIMIT | T47: 2300049646 | U47: 51093980 | W47: 2300049646 | Y47: 2408402 | Z47: Vendor Reconciliation Account - Domestic | AA47: 2408424 | AB47: GR/IR Account - Capital (Project System) | AC47: 5149121 | AD47: 5149121 | AE47: Purchase of Capital goods-Project System | AF47: 0 | AG47: 31 | AH47: H | AK47: 45049791 | AL47: 23-05-2019 | AM47: 15-05-2019 | AN47: 18:10:12 | AO47: 0 | AP47: -619500 | AS47: 1
A48: 1000 | B48: Tata Steel Limited | C48: 51087756 | D48: 836589 | E48: CI0004105747 | F48: 51087756 | G48: RE | H48: 43434 | I48: 43599 | J48: -1937796 | K48: -1642200 | L48: -295596 | M48: -1937796 | N48: 0 | O48: 0 | P48: T018 | Q48: TATA BLUESCOPE STEEL PRIVATE LIMIT | T48: 2300049646 | U48: 51087756 | W48: 2300049646 | Y48: 2408402 | Z48: Vendor Reconciliation Account - Domestic | AA48: 2408424 | AB48: GR/IR Account - Capital (Project System) | AC48: 5149121 | AD48: 5149121 | AE48: Purchase of Capital goods-Project System | AF48: 0 | AG48: 31 | AH48: H | AK48: 45046600 | AL48: 20-05-2019 | AM48: 14-05-2019 | AN48: 11:06:56 | AO48: 0 | AP48: -1937796 | AS48: 1
A49: 1000 | B49: Tata Steel Limited | C49: 51087758 | D49: 836571 | E49: CI0004105748 | F49: 51087758 | G49: RE | H49: 43434 | I49: 43599 | J49: -1937796 | K49: -1642200 | L49: -295596 | M49: -1937796 | N49: 0 | O49: 0 | P49: T018 | Q49: TATA BLUESCOPE STEEL PRIVATE LIMIT | T49: 2300049646 | U49: 51087758 | W49: 2300049646 | Y49: 2408402 | Z49: Vendor Reconciliation Account - Domestic | AA49: 2408424 | AB49: GR/IR Account - Capital (Project System) | AC49: 5149121 | AD49: 5149121 | AE49: Purchase of Capital goods-Project System | AF49: 0 | AG49: 31 | AH49: H | AK49: 45046600 | AL49: 20-05-2019 | AM49: 14-05-2019 | AN49: 11:07:01 | AO49: 0 | AP49: -1937796 | AS49: 1
A50: 1000 | B50: Tata Steel Limited | C50: 51093981 | D50: 836567 | E50: CI0004105749 | F50: 51093981 | G50: RE | H50: 43434 | I50: 43600 | J50: -1850240 | K50: -1568000 | L50: -282240 | M50: -1850240 | N50: 0 | O50: 0 | P50: T018 | Q50: TATA BLUESCOPE STEEL PRIVATE LIMIT | T50: 2300049646 | U50: 51093981 | W50: 2300049646 | Y50: 2408402 | Z50: Vendor Reconciliation Account - Domestic | AA50: 2408424 | AB50: GR/IR Account - Capital (Project System) | AC50: 5149121 | AD50: 5149121 | AE50: Purchase of Capital goods-Project System | AF50: 0 | AG50: 31 | AH50: H | AK50: 45049791 | AL50: 23-05-2019 | AM50: 15-05-2019 | AN50: 18:10:16 | AO50: 0 | AP50: -1850240 | AS50: 1
A51: 1000 | B51: Tata Steel Limited | C51: 51093982 | D51: 836562 | E51: CI0004105750 | F51: 51093982 | G51: RE | H51: 43434 | I51: 43600 | J51: -1639610 | K51: -1389500 | L51: -250110 | M51: -1639610 | N51: 0 | O51: 0 | P51: T018 | Q51: TATA BLUESCOPE STEEL PRIVATE LIMIT | T51: 2300049646 | U51: 51093982 | W51: 2300049646 | Y51: 2408402 | Z51: Vendor Reconciliation Account - Domestic | AA51: 2408424 | AB51: GR/IR Account - Capital (Project System) | AC51: 5149121 | AD51: 5149121 | AE51: Purchase of Capital goods-Project System | AF51: 0 | AG51: 31 | AH51: H | AK51: 45049791 | AL51: 23-05-2019 | AM51: 15-05-2019 | AN51: 18:10:20 | AO51: 0 | AP51: -1639610 | AS51: 1
A52: 1000 | B52: Tata Steel Limited | C52: 51050682 | D52: 836617 | E52: GSEZ/ERE-RAB-03 | F52: 51050682 | G52: RE | H52: 43462 | I52: 43580 | J52: -11906.85 | K52: 24842.32 | L52: -36954.56 | M52: -11906.85 | N52: -9751.37 | O52: -205.39 | P52: T040 | Q52: TATA BLUESCOPE STEEL PRIVATE LIMIT | T52: 3800014331 | U52: 51050682 | W52: 3800014331 | Y52: 2408402 | Z52: Vendor Reconciliation Account - Domestic | AA52: 2408422 | AB52: GR/IR Account - Services & Capital | AC52: 5149106 | AD52: 5149106 | AE52: CAPITAL EXPENSES | AF52: 0 | AG52: 31 | AH52: H | AM52: 25-04-2019 | AN52: 12:12:59 | AO52: 0 | AP52: -11906.85 | AS52: 8
A53: 1000 | B53: Tata Steel Limited | C53: 51050682 | D53: 836617 | E53: GSEZ/ERE-RAB-03 | F53: 51050682 | G53: RE | H53: 43462 | I53: 43580 | J53: -214335.34 | K53: -218032.56 | L53: 0 | M53: -214335.34 | N53: -175534.61 | O53: -3697.22 | P53: T040 | Q53: TATA BLUESCOPE STEEL PRIVATE LIMIT | T53: 3800014331 | U53: 51050682 | W53: 3800014331 | Y53: 2408402 | Z53: Vendor Reconciliation Account - Domestic | AA53: 2408422 | AB53: GR/IR Account - Services & Capital | AC53: 5149106 | AD53: 5149106 | AE53: CAPITAL EXPENSES | AF53: 0 | AG53: 31 | AH53: H | AK53: 45028294 | AL53: 26-04-2019 | AM53: 25-04-2019 | AN53: 12:12:59 | AO53: 0 | AP53: -214335.34 | AS53: 6
A54: 1000 | B54: Tata Steel Limited | C54: 51050682 | D54: 836617 | E54: GSEZ/ERE-RAB-03 | F54: 51050682 | G54: RE | H54: 43462 | I54: 43580 | J54: -11906.85 | K54: -12112.24 | L54: 0 | M54: -11906.85 | N54: -9751.37 | O54: -205.39 | P54: T040 | Q54: TATA BLUESCOPE STEEL PRIVATE LIMIT | T54: 3800014331 | U54: 51050682 | W54: 3800014331 | Y54: 2408402 | Z54: Vendor Reconciliation Account - Domestic | AA54: 2408422 | AB54: GR/IR Account - Services & Capital | AC54: 5149106 | AD54: 5149106 | AE54: CAPITAL EXPENSES | AF54: 0 | AG54: 31 | AH54: H | AM54: 25-04-2019 | AN54: 12:12:59 | AO54: 0 | AP54: -11906.85 | AS54: 7
A55: 1000 | B55: Tata Steel Limited | C55: 51087753 | D55: 836573 | E55: CI0004106485 | F55: 51087753 | G55: RE | H55: 43464 | I55: 43599 | J55: -696683.8 | K55: -590410 | L55: -106273.8 | M55: -696683.8 | N55: 0 | O55: 0 | P55: T018 | Q55: TATA BLUESCOPE STEEL PRIVATE LIMIT | T55: 2300049646 | U55: 51087753 | W55: 2300049646 | Y55: 2408402 | Z55: Vendor Reconciliation Account - Domestic | AA55: 2408424 | AB55: GR/IR Account - Capital (Project System) | AC55: 5149121 | AD55: 5149121 | AE55: Purchase of Capital goods-Project System | AF55: 0 | AG55: 31 | AH55: H | AK55: 45046600 | AL55: 20-05-2019 | AM55: 14-05-2019 | AN55: 11:06:47 | AO55: 0 | AP55: -696683.8 | AS55: 1
A56: 1000 | B56: Tata Steel Limited | C56: 51087754 | D56: 836566 | E56: CI0004106486 | F56: 51087754 | G56: RE | H56: 43464 | I56: 43599 | J56: -2045947.2 | K56: -1733853.6 | L56: -312093.65 | M56: -2045947.2 | N56: 0 | O56: 0 | P56: T018 | Q56: TATA BLUESCOPE STEEL PRIVATE LIMIT | T56: 2300049646 | U56: 51087754 | W56: 2300049646 | Y56: 2408402 | Z56: Vendor Reconciliation Account - Domestic | AA56: 2408424 | AB56: GR/IR Account - Capital (Project System) | AC56: 5149121 | AD56: 5149121 | AE56: Purchase of Capital goods-Project System | AF56: 0 | AG56: 31 | AH56: H | AK56: 45046600 | AL56: 20-05-2019 | AM56: 14-05-2019 | AN56: 11:06:52 | AO56: 0 | AP56: -2045947.2 | AS56: 1
A57: 1000 | B57: Tata Steel Limited | C57: 51093219 | D57: 836558 | E57: CI0001102514 | F57: 51093219 | G57: RE | H57: 43522 | I57: 43600 | J57: -595900 | K57: -505000 | L57: -90900 | M57: -505000 | N57: 0 | O57: 0 | P57: T018 | Q57: TATA BLUESCOPE STEEL PRIVATE LIMIT | T57: 2300049939 | U57: 51093219 | W57: 2300049939 | Y57: 2408402 | Z57: Vendor Reconciliation Account - Domestic | AA57: 2408409 | AB57: Gr/Ir For Stores And Spares | AC57: 6005101 | AD57: 6005101 | AE57: Purchase of Stores | AF57: 0 | AG57: 31 | AH57: H | AK57: 45046600 | AL57: 20-05-2019 | AM57: 15-05-2019 | AN57: 14:56:07 | AO57: 0 | AP57: -595900 | AS57: 1
A58: 1000 | B58: Tata Steel Limited | C58: 51093319 | D58: 836565 | E58: CI0001102515 | F58: 51093319 | G58: RE | H58: 43522 | I58: 43600 | J58: -909780 | K58: -771000 | L58: -138780 | M58: -771000 | N58: 0 | O58: 0 | P58: T018 | Q58: TATA BLUESCOPE STEEL PRIVATE LIMIT | T58: 2300049939 | U58: 51093319 | W58: 2300049939 | Y58: 2408402 | Z58: Vendor Reconciliation Account - Domestic | AA58: 2408409 | AB58: Gr/Ir For Stores And Spares | AC58: 6005101 | AD58: 6005101 | AE58: Purchase of Stores | AF58: 0 | AG58: 31 | AH58: H | AK58: 45046600 | AL58: 20-05-2019 | AM58: 15-05-2019 | AN58: 15:13:58 | AO58: 0 | AP58: -909780 | AS58: 1
A59: 1000 | B59: Tata Steel Limited | C59: 51091615 | D59: 836620 | E59: GSEZ/ERE-RAB-04 | F59: 51091615 | G59: RE | H59: 43525 | I59: 43600 | J59: -14267.87 | K59: 29768.64 | L59: -44282.65 | M59: -14267.87 | N59: -12300 | O59: -246.14 | P59: T040 | Q59: TATA BLUESCOPE STEEL PRIVATE LIMIT | T59: 3800014331 | U59: 51091615 | W59: 3800014331 | Y59: 2408402 | Z59: Vendor Reconciliation Account - Domestic | AA59: 2408422 | AB59: GR/IR Account - Services & Capital | AC59: 5149106 | AD59: 5149106 | AE59: CAPITAL EXPENSES | AF59: 0 | AG59: 31 | AH59: H | AM59: 15-05-2019 | AN59: 11:36:36 | AO59: 0 | AP59: -14267.87 | AS59: 7
A60: 1000 | B60: Tata Steel Limited | C60: 51091615 | D60: 836620 | E60: GSEZ/ERE-RAB-04 | F60: 51091615 | G60: RE | H60: 43525 | I60: 43600 | J60: -256838.6 | K60: -261269.33 | L60: 0 | M60: -256838.6 | N60: -221414.68 | O60: -4430.73 | P60: T040 | Q60: TATA BLUESCOPE STEEL PRIVATE LIMIT | T60: 3800014331 | U60: 51091615 | W60: 3800014331 | Y60: 2408402 | Z60: Vendor Reconciliation Account - Domestic | AA60: 2408422 | AB60: GR/IR Account - Services & Capital | AC60: 5149106 | AD60: 5149106 | AE60: CAPITAL EXPENSES | AF60: 0 | AG60: 31 | AH60: H | AK60: 45050489 | AL60: 24-05-2019 | AM60: 15-05-2019 | AN60: 11:36:36 | AO60: 0 | AP60: -256838.6 | AS60: 6
A61: 1000 | B61: Tata Steel Limited | C61: 51091615 | D61: 836620 | E61: GSEZ/ERE-RAB-04 | F61: 51091615 | G61: RE | H61: 43525 | I61: 43600 | J61: -14267.86 | K61: -14514 | L61: 0 | M61: -14267.86 | N61: -12300 | O61: -246.14 | P61: T040 | Q61: TATA BLUESCOPE STEEL PRIVATE LIMIT | T61: 3800014331 | U61: 51091615 | W61: 3800014331 | Y61: 2408402 | Z61: Vendor Reconciliation Account - Domestic | AA61: 2408422 | AB61: GR/IR Account - Services & Capital | AC61: 5149106 | AD61: 5149106 | AE61: CAPITAL EXPENSES | AF61: 0 | AG61: 31 | AH61: H | AM61: 15-05-2019 | AN61: 11:36:36 | AO61: 0 | AP61: -14267.86 | AS61: 8
A62: 1000 | B62: Tata Steel Limited | C62: 51099503 | D62: 836563 | E62: CI0004106487 | F62: 51099503 | G62: RE | H62: 43464 | I62: 43602 | J62: -59253.32 | K62: -50214.68 | L62: -9038.64 | M62: -50214.68 | N62: 0 | O62: 0 | P62: T040 | Q62: TATA BLUESCOPE STEEL PRIVATE LIMIT | T62: 2300049475 | U62: 51099503 | W62: 2300049475 | Y62: 2408402 | Z62: Vendor Reconciliation Account - Domestic | AA62: 2408424 | AB62: GR/IR Account - Capital (Project System) | AC62: 5149121 | AD62: 5149121 | AE62: Purchase of Capital goods-Project System | AF62: 0 | AG62: 31 | AH62: H | AK62: 45053840 | AL62: 28-05-2019 | AM62: 17-05-2019 | AN62: 18:08:53 | AO62: 0 | AP62: -59253.32 | AS62: 1
A63: 1000 | B63: Tata Steel Limited | C63: 51135741 | D63: 836602 | E63: CI0004108175 | F63: 51135741 | G63: RE | H63: 43537 | I63: 43619 | J63: -1842039 | K63: -1561050 | L63: -280989 | M63: -1561050 | N63: 0 | O63: 0 | P63: T018 | Q63: TATA BLUESCOPE STEEL PRIVATE LIMIT | S63: 4404261732 | T63: 4404261732 | U63: 51135741 | W63: 4404261732 | Y63: 2408402 | Z63: Vendor Reconciliation Account - Domestic | AA63: 2408409 | AB63: Gr/Ir For Stores And Spares | AC63: 6005101 | AD63: 6005101 | AE63: Purchase of Stores | AF63: 0 | AG63: 31 | AH63: H | AK63: 45078173 | AL63: 02-07-2019 | AM63: 03-06-2019 | AN63: 16:33:07 | AO63: 0 | AP63: -1842039 | AS63: 1
A64: 1000 | B64: Tata Steel Limited | C64: 51091574 | D64: 836620 | E64: GSEZ/ERE-RAB-05 | F64: 51091574 | G64: RE | H64: 43531 | I64: 43600 | J64: -7484.01 | K64: -7613.15 | L64: 0 | M64: -7484.01 | N64: -6129.23 | O64: -129.14 | P64: T040 | Q64: TATA BLUESCOPE STEEL PRIVATE LIMIT | T64: 3800014331 | U64: 51091574 | W64: 3800014331 | Y64: 2408402 | Z64: Vendor Reconciliation Account - Domestic | AA64: 2408422 | AB64: GR/IR Account - Services & Capital | AC64: 5149106 | AD64: 5149106 | AE64: CAPITAL EXPENSES | AF64: 0 | AG64: 31 | AH64: H | AM64: 15-05-2019 | AN64: 11:34:26 | AO64: 0 | AP64: -7484.01 | AS64: 6
A65: 1000 | B65: Tata Steel Limited | C65: 51091574 | D65: 836620 | E65: GSEZ/ERE-RAB-05 | F65: 51091574 | G65: RE | H65: 43531 | I65: 43600 | J65: -134729.21 | K65: 15226.29 | L65: -152280.23 | M65: -134729.21 | N65: -110340.04 | O65: -2324.73 | P65: T040 | Q65: TATA BLUESCOPE STEEL PRIVATE LIMIT | T65: 3800014331 | U65: 51091574 | W65: 3800014331 | Y65: 2408402 | Z65: Vendor Reconciliation Account - Domestic | AA65: 2408422 | AB65: GR/IR Account - Services & Capital | AC65: 5149106 | AD65: 5149106 | AE65: CAPITAL EXPENSES | AF65: 0 | AG65: 31 | AH65: H | AK65: 45050489 | AL65: 24-05-2019 | AM65: 15-05-2019 | AN65: 11:34:26 | AO65: 0 | AP65: -134729.21 | AS65: 4
A66: 1000 | B66: Tata Steel Limited | C66: 51091574 | D66: 836620 | E66: GSEZ/ERE-RAB-05 | F66: 51091574 | G66: RE | H66: 43531 | I66: 43600 | J66: -7484.01 | K66: -7613.15 | L66: 0 | M66: -7484.01 | N66: -6129.23 | O66: -129.14 | P66: T040 | Q66: TATA BLUESCOPE STEEL PRIVATE LIMIT | T66: 3800014331 | U66: 51091574 | W66: 3800014331 | Y66: 2408402 | Z66: Vendor Reconciliation Account - Domestic | AA66: 2408422 | AB66: GR/IR Account - Services & Capital | AC66: 5149106 | AD66: 5149106 | AE66: CAPITAL EXPENSES | AF66: 0 | AG66: 31 | AH66: H | AM66: 15-05-2019 | AN66: 11:34:26 | AO66: 0 | AP66: -7484.01 | AS66: 5
A67: 1000 | B67: Tata Steel Limited | C67: 52001308 | D67: 0 | E67: CI0004107075LD | F67: 52001308 | G67: RA | H67: 43492 | I67: 43585 | J67: 45533.9 | K67: 38588.05 | L67: 6945.85 | M67: 38588.05 | N67: 0 | O67: 0 | P67: T040 | Q67: TATA BLUESCOPE STEEL PRIVATE LIMIT | S67: *LD deducted against IV No. 5106145399 @ 4% | T67: 2300049475 | U67: 52001308 | W67: 2300049475 | Y67: 2408402 | Z67: Vendor Reconciliation Account - Domestic | AA67: 5149102 | AB67: Price Difference Account - Capital (PS)-PRD | AC67: 5149121 | AD67: 5149121 | AE67: Purchase of Capital goods-Project System | AF67: 0 | AG67: 21 | AH67: S | AK67: 45039858 | AL67: 10-05-2019 | AM67: 30-04-2019 | AN67: 12:44:46 | AO67: 0 | AP67: 45533.9 | AS67: 1
K68: =SUM(K2:K67) -> -21471051

Sheet MIT
A2: Company_Code | B2: Company_Name | C2: SAP_Doc_Number | D2: Reference | F2: Document_Type | G2: SAP_Doc_Number | H2: Business_Area | I2: Fiscal_Year | J2: Posting_Period | K2: DocChq_Date | L2: Posting_Date | M2: Amount_in_Local_Currency | N2: SOA | O2: Local_Currency | P2: Amount_in_Document_Currency
A3: 1000 | B3: Tata BlueScope Steel Ltd | C3: 111055 | D3: CI1904105574 | E3: =VLOOKUP(D3,TBSL!D15:AG1803,31,0) -> #VALUE! | F3: RV | G3: 111055 | H3: 1109 | I3: 2019 | J3: 9 | K3: 43830 | L3: 43830 | M3: 3917924.2 | N3: 3320274.8 | O3: INR | P3: 3917924.2
A4: 1000 | B4: Tata BlueScope Steel Ltd | C4: 111100 | D4: CI1904105607 | E4: =VLOOKUP(D4,TBSL!D16:AG1804,31,0) -> #VALUE! | F4: RV | G4: 111100 | H4: 1109 | I4: 2019 | J4: 9 | K4: 43830 | L4: 43830 | M4: 1250608.6 | N4: 1059837.8 | O4: INR | P4: 1250608.6
A5: 1000 | B5: Tata BlueScope Steel Ltd | C5: 111487 | D5: CI1904105863 | E5: =VLOOKUP(D5,TBSL!D18:AG1806,31,0) -> #VALUE! | F5: RV | G5: 111487 | H5: 1109 | I5: 2019 | J5: 10 | K5: 43847 | L5: 43847 | M5: 781093.9 | N5: 661943.98 | O5: INR | P5: 781093.9
A6: 1000 | B6: Tata BlueScope Steel Ltd | C6: 114069 | D6: CI1901102828 | E6: =VLOOKUP(D6,TBSL!D24:AG1812,31,0) -> #VALUE! | F6: RV | G6: 114069 | H6: 1108 | I6: 2019 | J6: 12 | K6: 43907 | L6: 43907 | M6: 176487.93 | N6: 149566.03 | O6: INR | P6: 176487.93
A7: 1000 | B7: Tata BlueScope Steel Ltd | C7: 114071 | D7: CI1901102830 | E7: =VLOOKUP(D7,TBSL!D25:AG1813,31,0) -> #VALUE! | F7: RV | G7: 114071 | H7: 1108 | I7: 2019 | J7: 12 | K7: 43907 | L7: 43907 | M7: 74661.05 | N7: 63272.07 | O7: INR | P7: 74661.05
A8: 1000 | B8: Tata BlueScope Steel Ltd | C8: 114070 | D8: CI1901102829 | E8: =VLOOKUP(D8,TBSL!D26:AG1814,31,0) -> #VALUE! | F8: RV | G8: 114070 | H8: 1108 | I8: 2019 | J8: 12 | K8: 43907 | L8: 43907 | M8: 208337.22 | N8: 176556.96 | O8: INR | P8: 208337.22
A9: 1000 | B9: Tata BlueScope Steel Ltd | C9: 114072 | D9: CI1901102831 | E9: =VLOOKUP(D9,TBSL!D27:AG1815,31,0) -> #VALUE! | F9: RV | G9: 114072 | H9: 1108 | I9: 2019 | J9: 12 | K9: 43907 | L9: 43907 | M9: 49163.52 | N9: 41664 | O9: INR | P9: 49163.52
A10: 1000 | B10: Tata BlueScope Steel Ltd | C10: 114073 | D10: CI1901102832 | E10: =VLOOKUP(D10,TBSL!D28:AG1816,31,0) -> #VALUE! | F10: RV | G10: 114073 | H10: 1108 | I10: 2019 | J10: 12 | K10: 43907 | L10: 43907 | M10: 1044655.3 | N10: 885301.08 | O10: INR | P10: 1044655.3
A11: 1000 | B11: Tata BlueScope Steel Ltd | C11: 114347 | D11: CI1904107824 | E11: =VLOOKUP(D11,TBSL!D31:AG1819,31,0) -> #VALUE! | F11: RV | G11: 114347 | H11: 1109 | I11: 2019 | J11: 12 | K11: 43911 | L11: 43911 | M11: 1557104.4 | N11: 1319580 | O11: INR | P11: 1557104.4
A12: 1000 | B12: Tata BlueScope Steel Ltd | C12: 107704 | D12: RI1901100035 | E12: =VLOOKUP(D12,TBSL!D11:AG1799,31,0) -> #VALUE! | F12: RV | G12: 107704 | H12: 1101 | I12: 2019 | J12: 7 | K12: 43747 | L12: 43747 | M12: 70003.45 | N12: 59324.95 | O12: INR | P12: 70003.45
N13: =SUM(N3:N12) -> 7737321.6

Sheet Short provi
B3: Company_Code | C3: Company_Name | D3: SAP_Doc_Number | E3: Reference | G3: Document_Type | H3: SAP_Doc_Number | I3: Business_Area | J3: Fiscal_Year | K3: Posting_Period | L3: DocChq_Date | M3: Posting_Date | N3: Amount_in_Local_Currency | O3: SOA | P3: Local_Currency | Q3: Amount_in_Document_Currency
B4: 1000 | C4: Tata BlueScope Steel Ltd | D4: 100882 | E4: SI1904100005 | F4: =VLOOKUP(E4,TBSL!D5:AG1793,31,0) -> #VALUE! | G4: RV | H4: 100882 | I4: 1109 | J4: 2019 | K4: 1 | L4: 43581 | M4: 43581 | N4: 651626.68 | O4: 552226 | P4: INR | Q4: 651626.68
B5: 1000 | C5: Tata BlueScope Steel Ltd | D5: 101042 | E5: SI1904100006 | F5: =VLOOKUP(E5,TBSL!D6:AG1794,31,0) -> #VALUE! | G5: RV | H5: 101042 | I5: 1109 | J5: 2019 | K5: 1 | L5: 43584 | M5: 43584 | N5: 212211.2 | O5: 179840 | P5: INR | Q5: 212211.2
B6: 1000 | C6: Tata BlueScope Steel Ltd | D6: 101052 | E6: SI1904100007 | F6: =VLOOKUP(E6,TBSL!D7:AG1795,31,0) -> #VALUE! | G6: RV | H6: 101052 | I6: 1109 | J6: 2019 | K6: 1 | L6: 43584 | M6: 43584 | N6: 309431.4 | O6: 262230 | P6: INR | Q6: 309431.4
B7: 1000 | C7: Tata BlueScope Steel Ltd | D7: 101077 | E7: SI1904100008 | F7: =VLOOKUP(E7,TBSL!D8:AG1796,31,0) -> #VALUE! | G7: RV | H7: 101077 | I7: 1109 | J7: 2019 | K7: 1 | L7: 43584 | M7: 43584 | N7: 422145 | O7: 357750 | P7: INR | Q7: 422145
B8: 1000 | C8: Tata BlueScope Steel Ltd | D8: 107464 | E8: SI1901100041 | F8: =VLOOKUP(E8,TBSL!D10:AG1798,31,0) -> #VALUE! | G8: RV | H8: 107464 | I8: 1108 | J8: 2019 | K8: 6 | L8: 43738 | M8: 43738 | N8: 100717.43 | O8: 85353.75 | P8: INR | Q8: 100717.43
B9: 1000 | C9: Tata BlueScope Steel Ltd | D9: 109114 | E9: SI1901100055 | F9: =VLOOKUP(E9,TBSL!D13:AG1801,31,0) -> #VALUE! | G9: RV | H9: 109114 | I9: 1108 | J9: 2019 | K9: 8 | L9: 43788 | M9: 43788 | N9: 501797.01 | O9: 425251.7 | P9: INR | Q9: 501797.01
B10: 1000 | C10: Tata BlueScope Steel Ltd | D10: 109115 | E10: SI1904100043 | F10: =VLOOKUP(E10,TBSL!D14:AG1802,31,0) -> #VALUE! | G10: RV | H10: 109115 | I10: 1109 | J10: 2019 | K10: 8 | L10: 43788 | M10: 43788 | N10: 42404.1 | O10: 35935.68 | P10: INR | Q10: 42404.1
B11: 1000 | C11: Tata BlueScope Steel Ltd | D11: 111241 | E11: SI1901100063 | F11: =VLOOKUP(E11,TBSL!D17:AG1805,31,0) -> #VALUE! | G11: RV | H11: 111241 | I11: 1108 | J11: 2019 | K11: 10 | L11: 43839 | M11: 43839 | N11: 673505.06 | O11: 570767 | P11: INR | Q11: 673505.06
B12: 1000 | C12: Tata BlueScope Steel Ltd | D12: 113356 | E12: SI1904100053 | F12: =VLOOKUP(E12,TBSL!D19:AG1807,31,0) -> #VALUE! | G12: RV | H12: 113356 | I12: 1109 | J12: 2019 | K12: 11 | L12: 43889 | M12: 43889 | N12: 797495.35 | O12: 675843.52 | P12: INR | Q12: 797495.35
B13: 1000 | C13: Tata BlueScope Steel Ltd | D13: 113665 | E13: 95004890 | F13: =VLOOKUP(E13,TBSL!D20:AG1808,31,0) -> #VALUE! | G13: RV | H13: 113665 | I13: 1109 | J13: 2019 | K13: 12 | L13: 43896 | M13: 43896 | N13: 325092.93 | O13: 275502.48 | P13: INR | Q13: 325092.93
B14: 1000 | C14: Tata BlueScope Steel Ltd | D14: 113885 | E14: 95004894 | F14: =VLOOKUP(E14,TBSL!D21:AG1809,31,0) -> #VALUE! | G14: RV | H14: 113885 | I14: 1109 | J14: 2019 | K14: 12 | L14: 43903 | M14: 43903 | N14: 129302.32 | O14: 109578.24 | P14: INR | Q14: 129302.32
B15: 1000 | C15: Tata BlueScope Steel Ltd | D15: 113927 | E15: 95004896 | F15: =VLOOKUP(E15,TBSL!D22:AG1810,31,0) -> #VALUE! | G15: RV | H15: 113927 | I15: 1108 | J15: 2019 | K15: 12 | L15: 43903 | M15: 43903 | N15: 1409887.8 | O15: 1194820.2 | P15: INR | Q15: 1409887.8
B16: 1000 | C16: Tata BlueScope Steel Ltd | D16: 113881 | E16: 95004893 | F16: =VLOOKUP(E16,TBSL!D23:AG1811,31,0) -> #VALUE! | G16: RV | H16: 113881 | I16: 1108 | J16: 2019 | K16: 12 | L16: 43903 | M16: 43903 | N16: 198551.52 | O16: 168264 | P16: INR | Q16: 198551.52
B17: 1000 | C17: Tata BlueScope Steel Ltd | D17: 114172 | E17: SI1901100076 | F17: =VLOOKUP(E17,TBSL!D29:AG1817,31,0) -> #VALUE! | G17: RV | H17: 114172 | I17: 1108 | J17: 2019 | K17: 12 | L17: 43908 | M17: 43908 | N17: 391260.28 | O17: 331576.51 | P17: INR | Q17: 391260.28
B18: 1000 | C18: Tata BlueScope Steel Ltd | D18: 114301 | E18: SI1904100064 | F18: =VLOOKUP(E18,TBSL!D30:AG1818,31,0) -> #VALUE! | G18: RV | H18: 114301 | I18: 1109 | J18: 2019 | K18: 12 | L18: 43910 | M18: 43910 | N18: 122720 | O18: 104000 | P18: INR | Q18: 122720
B19: 1000 | C19: Tata BlueScope Steel Ltd | D19: 114382 | E19: SI1904100065 | F19: =VLOOKUP(E19,TBSL!D32:AG1820,31,0) -> #VALUE! | G19: RV | H19: 114382 | I19: 1109 | J19: 2019 | K19: 12 | L19: 43918 | M19: 43918 | N19: 563956.22 | O19: 477929 | P19: INR | Q19: 563956.22
B20: 1000 | C20: Tata BlueScope Steel Ltd | D20: 114391 | E20: SI1904100066 | F20: =VLOOKUP(E20,TBSL!D33:AG1821,31,0) -> #VALUE! | G20: RV | H20: 114391 | I20: 1109 | J20: 2019 | K20: 12 | L20: 43921 | M20: 43921 | N20: 107380 | O20: 91000 | P20: INR | Q20: 107380
B21: 1000 | C21: Tata BlueScope Steel Ltd | D21: 114392 | E21: SI1904100067 | F21: =VLOOKUP(E21,TBSL!D34:AG1822,31,0) -> #VALUE! | G21: RV | H21: 114392 | I21: 1109 | J21: 2019 | K21: 12 | L21: 43921 | M21: 43921 | N21: 489729.5 | O21: 415025 | P21: INR | Q21: 489729.5
B22: 1000 | C22: Tata BlueScope Steel Ltd | D22: 114393 | E22: SI1904100068 | F22: =VLOOKUP(E22,TBSL!D35:AG1823,31,0) -> #VALUE! | G22: RV | H22: 114393 | I22: 1109 | J22: 2019 | K22: 12 | L22: 43921 | M22: 43921 | N22: 417963.08 | O22: 354206 | P22: INR | Q22: 417963.08
J23: Total Unmatched service | O23: =SUM(O4:O22) -> 6667099.1
J25: Provision created | O25: -3562266.1
J27: Short provision | O27: =O23+O25 -> 3104833

Sheet Invoice Diff
A1: Company_Code | B1: Company_Name | C1: SAP_Doc_Number | D1: Reference | E1: Document_Type | F1: Business_Area | G1: BranchAlloc | H1: Fiscal_Year | I1: Posting_Period | J1: DocChq_Date | K1: Posting_Date | L1: Amount_in_Local_Currency | M1: Local_Currency | N1: Amount_in_Document_Currency | O1: Document_Currency | P1: Discount_Base_Amount | Q1: GST_Amount | R1: Net_Amount | S1: Withholding_Tax_Base_Amount | T1: Withholding_Tax_Amount | U1: VendorCustomer | V1: VendorCustomer_Name | W1: Trading_Partner | X1: Text_ | Y1: HDR_Text | Z1: InvSO_Reference | AA1: Plant | AB1: Purchasing_Document | AC1: Delivery_Note | AD1: Account | AE1: Account_Description | AF1: Offsetting_Account | AG1: Offsetting_Acct_Name | AH1: GRIR_Offsetting_Account | AI1: Final_Offsetting_Account | AJ1: Final_Offsetting_Acct_Name | AK1: WBS_Element | AL1: Posting_Key | AM1: DebitCredit | AN1: Special_GL_Ind | AO1: Reversal_Indicator | AP1: Clearing_Doc | AQ1: Clearing_Date | AR1: Entry_date | AS1: Entry_Time | AT1: Notional_GST | AU1: Gross_Amount_In_Local_Currency | AV1: DE_Indicator | AW1: PO_Line | AX1: Entry_Line | AY1: INVERSE_Amount_in_Local_Currency | AZ1: INVERSE_Amount_in_Document_Currency | BA1: Entity_Name | BB1: Transaction_Type | BC1: Reporting | BD1: Recon_Set | BE1: Recon_Entities | BF1: MatchID_copy | BG1: MatchDate_copy | BH1: Nature | BI1: Transaction_ID | BJ1: DataSourceName | BK1: IsActive | BL1: SourceFileName | BM1: ImportDate
A2: 1000 | B2: Tata BlueScope Steel Ltd | C2: 110821 | D2: SI1904100050 | E2: RV | F2: 1109 | H2: 2019 | I2: 9 | J2: 43827 | K2: 43827 | L2: 653406.83 | M2: INR | N2: 653406.83 | O2: INR | P2: 0 | Q2: 99672.23 | R2: 553734.6 | S2: 0 | T2: 0 | U2: 312193 | V2: Tata Steel Limited ( Kalinganagar) | Z2: 2495 | AB2: 4200001545/118 | AD2: 110000 | AE2: Customer - Domestic | AF2: 501020 | AG2: Revenue DS - Sale of Services Domestic | AI2: 501020 | AJ2: Revenue DS - Sale of Services Domestic | AK2: 0 | AL2: 1 | AM2: S | AP2: 100199799 | AQ2: 43830 | AR2: 43827 | AS2: 0.81033565 | AT2: 0 | AU2: 0 | AX2: 1 | AY2: -653406.83 | AZ2: -653406.83 | BA2: TATA BLUESCOPE | BB2: Customer Balance | BC2: Yes | BD2: TSL - TATA BLUESCOPE | BE2: TSL - TATA BLUESCOPE | BF2: 843556 | BG2: 43896.311 | BH2: Receivable | BI2: 438595 | BJ2: ICR_CONSOL_CUSTOMER_SAP | BK2: 1 | BL2: ICR_CUSTOMER_TBSL_TSL_31122019.csv | BM2: 43867.943
L3: =SUM(L2) -> 653406.83
A5: Company_Code | B5: Company_Name | C5: SAP_Doc_Number | D5: Reference | E5: Document_Type | F5: Business_Area | G5: BranchAlloc | H5: Fiscal_Year | I5: Posting_Period | J5: DocChq_Date | K5: Posting_Date | L5: Amount_in_Local_Currency | M5: Local_Currency | N5: Amount_in_Document_Currency | O5: Document_Currency | P5: Discount_Base_Amount | Q5: GST_Amount | R5: Net_Amount | S5: Withholding_Tax_Base_Amount | T5: Withholding_Tax_Amount | U5: VendorCustomer | V5: VendorCustomer_Name | W5: Trading_Partner | X5: Text_ | Y5: HDR_Text | Z5: InvSO_Reference | AA5: Plant | AB5: Purchasing_Document | AC5: Delivery_Note | AD5: Account | AE5: Account_Description | AF5: Offsetting_Account | AG5: Offsetting_Acct_Name | AH5: GRIR_Offsetting_Account | AI5: Final_Offsetting_Account | AJ5: Final_Offsetting_Acct_Name | AK5: WBS_Element | AL5: Posting_Key | AM5: DebitCredit | AN5: Special_GL_Ind | AO5: Reversal_Indicator | AP5: Clearing_Doc | AQ5: Clearing_Date | AR5: Entry_date | AS5: Entry_Time | AT5: Notional_GST | AU5: Gross_Amount_In_Local_Currency | AV5: DE_Indicator | AW5: PO_Line | AX5: Entry_Line | AY5: INVERSE_Amount_in_Local_Currency | AZ5: INVERSE_Amount_in_Document_Currency | BA5: Entity_Name | BB5: Transaction_Type | BC5: Reporting | BD5: Recon_Set | BE5: Recon_Entities | BF5: MatchID_copy | BG5: MatchDate_copy | BH5: Nature | BI5: Transaction_ID | BJ5: DataSourceName | BK5: IsActive | BL5: SourceFileName | BM5: ImportDate
A6: 1000 | B6: Tata Steel Limited | C6: 51724962 | D6: SI1904100050 | E6: RE | F6: 9600 | G6: CAPT | H6: 2020 | I6: 12 | J6: 43827 | K6: 43894 | L6: -600451.7 | M6: INR | N6: -600451.7 | O6: INR | P6: -610804.7 | Q6: 0 | R6: -600451.7 | S6: -517631.56 | T6: -10619.55 | U6: T040 | V6: TATA BLUESCOPE STEEL PRIVATE LIMIT | Y6: 3700796848 | Z6: 51724962 | AB6: 3700796848 | AD6: 2408402 | AE6: Vendor Reconciliation Account - Domestic | AF6: 2408422 | AG6: GR/IR Account - Services & Capital | AH6: 5149106 | AI6: 5149106 | AJ6: CAPITAL EXPENSES | AK6: 0 | AL6: 31 | AM6: H | AP6: 45262199 | AQ6: 43903 | AR6: 43894 | AS6: 0.72143519 | AT6: 0 | AU6: -600451.7 | AX6: 2 | AY6: 600451.7 | AZ6: 600451.7 | BA6: TSL | BB6: Vendor Balance | BC6: Yes | BD6: TSL - TATA BLUESCOPE | BE6: TSL - TATA BLUESCOPE | BH6: Payable | BI6: 477367 | BJ6: ICR_CONSOL_VENDOR_SAP | BK6: 1 | BL6: ICR_VENDOR_TSL_RP_31032020_02042020.csv | BM6: 43924.128
